[
    {
        "volume": "1990Supp. (1)",
        "Case Name": "KUMARI APARNA SHRIKANT BHAYE VS. STATE OF MAHARASHTRA AND ORS.",
        "Case Link": "https://digiscr.sci.gov.in/view_judgment?id=MjMzOTM=",
        "Citation": "[1990] Supp. (1) S.C.R. 1",
        "Case Type": "(SPECIAL LEAVE PETITION (CIVIL) /11493/1989)",
        "Date": "24 AUGUST 1990",
        "Judge Names": "Hon'ble Mr. Justice K. Jayachandra Reddy, Hon'ble Mr. Justice M.H. Kania\n*",
        "PDF Link": "https://digiscr.sci.gov.in/pdf_viewer?dir=YWRtaW4vanVkZ2VtZW50X2ZpbGUvanVkZ2VtZW50X3BkZi8xOTkwL1N1cHAuICgxKS9QYXJ0IEkvU18xOTkwXzEtNF8xNzAyMjcwMTE4LnBkZg=="
    },
    {
        "volume": "1990Supp. (1)",
        "Case Name": "CHAUDHARY KESAVA RAO AND ORS. ETC. VS. STATE OF ANDHRA PRADESH",
        "Case Link": "https://digiscr.sci.gov.in/view_judgment?id=MjM0MDg=",
        "Citation": "[1990] Supp. (1) S.C.R. 5",
        "Case Type": "(WRIT TO PETITION (CIVIL)... /888/1989)",
        "Date": "24 AUGUST 1990",
        "Judge Names": "Hon'ble Mr. Justice K. Ramaswamy, Hon'ble Mr. Justice N.M. Kasliwal\n*",
        "PDF Link": "https://digiscr.sci.gov.in/pdf_viewer?dir=YWRtaW4vanVkZ2VtZW50X2ZpbGUvanVkZ2VtZW50X3BkZi8xOTkwL1N1cHAuICgxKS9QYXJ0IEkvU18xOTkwXzUtMTBfMTcwMjI3MDMzOS5wZGY="
    },
    {
        "volume": "1990Supp. (1)",
        "Case Name": "STATE BANK OF INDIA VS. WORKMEN OF STATE BANK OF INDIA AND ANR.",
        "Case Link": "https://digiscr.sci.gov.in/view_judgment?id=MjM0MTU=",
        "Citation": "[1990] Supp. (1) S.C.R. 11",
        "Case Type": "(CIVIL APPEAL /4381/1990)",
        "Date": "24 AUGUST 1990",
        "Judge Names": "Hon'ble Mr. Justice K. Ramaswamy, Hon'ble Mr. Justice P.B. Sawant\n*",
        "PDF Link": "https://digiscr.sci.gov.in/pdf_viewer?dir=YWRtaW4vanVkZ2VtZW50X2ZpbGUvanVkZ2VtZW50X3BkZi8xOTkwL1N1cHAuICgxKS9QYXJ0IEkvU18xOTkwXzExLTI3XzE3MDIyNzA0NjcucGRm"
    },
    {
        "volume": "1990Supp. (1)",
        "Case Name": "SHARP BUSINESS MACHINES PVT. LTD., BANGALORE VS. COLLECTOR OF CUSTOMS, BANGALORE",
        "Case Link": "https://digiscr.sci.gov.in/view_judgment?id=MjM0MjM=",
        "Citation": "[1990] Supp. (1) S.C.R. 28",
        "Case Type": "(CIVIL APPEAL /2403/1989)",
        "Date": "24 AUGUST 1990",
        "Judge Names": "Hon'ble Mr. Justice N.M. Kasliwal\n*, Hon'ble Mr. Justice S.C. Agrawal",
        "PDF Link": "https://digiscr.sci.gov.in/pdf_viewer?dir=YWRtaW4vanVkZ2VtZW50X2ZpbGUvanVkZ2VtZW50X3BkZi8xOTkwL1N1cHAuICgxKS9QYXJ0IEkvU18xOTkwXzI4LTQzXzE3MDIyNzA1NTcucGRm"
    },
    {
        "volume": "1990Supp. (1)",
        "Case Name": "S.N. MUKHERJEE VS. UNION OF INDIA",
        "Case Link": "https://digiscr.sci.gov.in/view_judgment?id=MjM0NDI=",
        "Citation": "[1990] Supp. (1) S.C.R. 44",
        "Case Type": "(CIVIL APPEAL /417/1984)",
        "Date": "28 AUGUST 1990",
        "Judge Names": "Hon'ble Mr. Justice K. Jagannatha Shetty, Hon'ble Mr. Justice K.N. Saikia, Hon'ble Mr. Justice M.H. Kania, Hon'ble Mr. Justice S.C. Agrawal\n*, Hon'ble Mr. Justice Sabyasachi Mukherjee",
        "PDF Link": "https://digiscr.sci.gov.in/pdf_viewer?dir=YWRtaW4vanVkZ2VtZW50X2ZpbGUvanVkZ2VtZW50X3BkZi8xOTkwL1N1cHAuICgxKS9QYXJ0IEkvU18xOTkwXzQ0LTc1XzE3MDIyNzA4NDAucGRm"
    },
    {
        "volume": "1990Supp. (1)",
        "Case Name": "S. HARCHARAN SINGH VS. UNION OF INDIA",
        "Case Link": "https://digiscr.sci.gov.in/view_judgment?id=MjM0NTI=",
        "Citation": "[1990] Supp. (1) S.C.R. 76",
        "Case Type": "(CIVIL APPEAL /322/1976)",
        "Date": "28 AUGUST 1990",
        "Judge Names": "Hon'ble Mr. Justice M.M. Punchhi, Hon'ble Mr. Justice Ranganath Misra, Hon'ble Mr. Justice S.C. Agrawal\n*",
        "PDF Link": "https://digiscr.sci.gov.in/pdf_viewer?dir=YWRtaW4vanVkZ2VtZW50X2ZpbGUvanVkZ2VtZW50X3BkZi8xOTkwL1N1cHAuICgxKS9QYXJ0IEkvU18xOTkwXzc2LTkwXzE3MDIyNzA5NTMucGRm"
    },
    {
        "volume": "1990Supp. (1)",
        "Case Name": "STATE OF WEST BENGAL VS. ATUL KRISHNA SHAW AND ANR.",
        "Case Link": "https://digiscr.sci.gov.in/view_judgment?id=MjM0NjI=",
        "Citation": "[1990] Supp. (1) S.C.R. 91",
        "Case Type": "(CIVIL APPEAL /1422/1973)",
        "Date": "28 AUGUST 1990",
        "Judge Names": "Hon'ble Mr. Justice K. Ramaswamy\n*, Hon'ble Mr. Justice N.M. Kasliwal",
        "PDF Link": "https://digiscr.sci.gov.in/pdf_viewer?dir=YWRtaW4vanVkZ2VtZW50X2ZpbGUvanVkZ2VtZW50X3BkZi8xOTkwL1N1cHAuICgxKS9QYXJ0IEkvU18xOTkwXzkxLTEwNF8xNzAyMjcxMDY2LnBkZg=="
    },
    {
        "volume": "1990Supp. (1)",
        "Case Name": "KISHORE CHAND VS. STATE OF HIMACHAL PRADESH",
        "Case Link": "https://digiscr.sci.gov.in/view_judgment?id=MjM0NzI=",
        "Citation": "[1990] Supp. (1) S.C.R. 105",
        "Case Type": "(CRIMINAL APPEAL /386/1978)",
        "Date": "29 AUGUST 1990",
        "Judge Names": "Hon'ble Mr. Justice K. Ramaswamy\n*, Hon'ble Mr. Justice P.B. Sawant",
        "PDF Link": "https://digiscr.sci.gov.in/pdf_viewer?dir=YWRtaW4vanVkZ2VtZW50X2ZpbGUvanVkZ2VtZW50X3BkZi8xOTkwL1N1cHAuICgxKS9QYXJ0IEkvU18xOTkwXzEwNS0xMTdfMTcwMjI3MTE3MS5wZGY="
    },
    {
        "volume": "1990Supp. (1)",
        "Case Name": "RAM CHANDRA SINGH (DEAD) THROUGH LEGAL HEIRS VS. STATE OF U.P. AND OTHERS",
        "Case Link": "https://digiscr.sci.gov.in/view_judgment?id=MjM0ODA=",
        "Citation": "[1990] Supp. (1) S.C.R. 118",
        "Case Type": "(CIVIL APPEAL /5633/1983)",
        "Date": "30 AUGUST 1990",
        "Judge Names": "Hon'ble Mr. Justice K.N. Saikia, Hon'ble Mr. Justice S.C. Agrawal\n*",
        "PDF Link": "https://digiscr.sci.gov.in/pdf_viewer?dir=YWRtaW4vanVkZ2VtZW50X2ZpbGUvanVkZ2VtZW50X3BkZi8xOTkwL1N1cHAuICgxKS9QYXJ0IEkvU18xOTkwXzExOC0xMjVfMTcwMjI3MTI5Mi5wZGY="
    },
    {
        "volume": "1990Supp. (1)",
        "Case Name": "TEK CHAND (DEAD) BY L.RS. AND ORS. VS. UNION OF INDIA AND ORS. ETC.",
        "Case Link": "https://digiscr.sci.gov.in/view_judgment?id=MjM0OTM=",
        "Citation": "[1990] Supp. (1) S.C.R. 126",
        "Case Type": "(CIVIL APPEAL /1334/1982)",
        "Date": "31 AUGUST 1990",
        "Judge Names": "Hon'ble Mr. Justice K. Ramaswamy, Hon'ble Mr. Justice K.N. Saikia, Hon'ble Mr. Justice M.H. Kania\n*",
        "PDF Link": "https://digiscr.sci.gov.in/pdf_viewer?dir=YWRtaW4vanVkZ2VtZW50X2ZpbGUvanVkZ2VtZW50X3BkZi8xOTkwL1N1cHAuICgxKS9QYXJ0IEkvU18xOTkwXzEyNi0xMjlfMTcwMjI3MTQzOS5wZGY="
    },
    {
        "volume": "1990Supp. (1)",
        "Case Name": "U.P. JUNIOR DOCTORS` ACTION COMMITTEE VS. DR. B. SHEETAL NANDWANI AND ORS.",
        "Case Link": "https://digiscr.sci.gov.in/view_judgment?id=MjM1MTU=",
        "Citation": "[1990] Supp. (1) S.C.R. 130",
        "Case Type": "(CIVIL APPEAL /4444/1990)",
        "Date": "31 AUGUST 1990",
        "Judge Names": "Hon'ble Mr. Justice Kuldip Singh, Hon'ble Mr. Justice Ranganath Misra\n*",
        "PDF Link": "https://digiscr.sci.gov.in/pdf_viewer?dir=YWRtaW4vanVkZ2VtZW50X2ZpbGUvanVkZ2VtZW50X3BkZi8xOTkwL1N1cHAuICgxKS9QYXJ0IEkvU18xOTkwXzEzMC0xMzRfMTcwMjI3MTY1My5wZGY="
    },
    {
        "volume": "1990Supp. (1)",
        "Case Name": "DR. DINESH KUMAR AND ORS. VS. MOTI LAL NEHRU MEDICAL COLLEGE, ALLAHABAD AND ORS.",
        "Case Link": "https://digiscr.sci.gov.in/view_judgment?id=MjM1Mjk=",
        "Citation": "[1990] Supp. (1) S.C.R. 135",
        "Case Type": "(WRIT PETITION (CIVIL) /348/1985)",
        "Date": "31 AUGUST 1990",
        "Judge Names": "Hon'ble Mr. Justice Kuldip Singh, Hon'ble Mr. Justice Ranganath Misra\n*",
        "PDF Link": "https://digiscr.sci.gov.in/pdf_viewer?dir=YWRtaW4vanVkZ2VtZW50X2ZpbGUvanVkZ2VtZW50X3BkZi8xOTkwL1N1cHAuICgxKS9QYXJ0IEkvU18xOTkwXzEzNS0xNDFfMTcwMjI3MTgwNS5wZGY="
    },
    {
        "volume": "1990Supp. (1)",
        "Case Name": "DELHI TRANSPORT CORPORATION VS. D.T.C. MAZDOOR CONGRESS",
        "Case Link": "https://digiscr.sci.gov.in/view_judgment?id=MjM1NTM=",
        "Citation": "[1990] Supp. (1) S.C.R. 142",
        "Case Type": "(CIVIL APPEAL /2876/1986)",
        "Date": "04 SEPTEMBER 1990",
        "Judge Names": "Hon'ble Mr. Justice B.C. Ray\n*, Hon'ble Mr. Justice K. Ramaswamy\n*, Hon'ble Mr. Justice L.M. Sharma, Hon'ble Mr. Justice Sabyasachi Mukherjee\n*",
        "PDF Link": "https://digiscr.sci.gov.in/pdf_viewer?dir=YWRtaW4vanVkZ2VtZW50X2ZpbGUvanVkZ2VtZW50X3BkZi8xOTkwL1N1cHAuICgxKS9QYXJ0IEkvU18xOTkwXzE0Mi0zMzFfMTcwMjI3MjA5My5wZGY="
    },
    {
        "volume": "1990Supp. (1)",
        "Case Name": "SARASWATI INDUSTRIAL SYNDICATE LTD. VS. C.I.T., HARYANA, HIMACHAL PRADESH, DELHI",
        "Case Link": "https://digiscr.sci.gov.in/view_judgment?id=MjM1ODI=",
        "Citation": "[1990] Supp. (1) S.C.R. 332",
        "Case Type": "(CIVIL APPEAL /91/1976)",
        "Date": "04 SEPTEMBER 1990",
        "Judge Names": "Hon'ble Mr. Justice K.N. Singh\n*, Hon'ble Mr. Justice Kuldip Singh, Hon'ble Dr. Justice T.K. Thommen",
        "PDF Link": "https://digiscr.sci.gov.in/pdf_viewer?dir=YWRtaW4vanVkZ2VtZW50X2ZpbGUvanVkZ2VtZW50X3BkZi8xOTkwL1N1cHAuICgxKS9QYXJ0IEkvU18xOTkwXzMzMi0zMzlfMTcwMjI3MjQwNC5wZGY="
    },
    {
        "volume": "1990Supp. (1)",
        "Case Name": "JUTE CORPORATION OF INDIA LTD. VS. COMMISSIONER OF INCOME TAX AND ANR.",
        "Case Link": "https://digiscr.sci.gov.in/view_judgment?id=MjM1OTc=",
        "Citation": "[1990] Supp. (1) S.C.R. 340",
        "Case Type": "(CIVIL APPEAL /1935/1981)",
        "Date": "04 SEPTEMBER 1990",
        "Judge Names": "Hon'ble Mr. Justice K.N. Singh\n*, Hon'ble Mr. Justice Kuldip Singh, Hon'ble Dr. Justice T.K. Thommen",
        "PDF Link": "https://digiscr.sci.gov.in/pdf_viewer?dir=YWRtaW4vanVkZ2VtZW50X2ZpbGUvanVkZ2VtZW50X3BkZi8xOTkwL1N1cHAuICgxKS9QYXJ0IEkvU18xOTkwXzM0MC0zNDhfMTcwMjI3MjUzMC5wZGY="
    },
    {
        "volume": "1990Supp. (1)",
        "Case Name": "INDIRA BAI VS. NAND KISHORE",
        "Case Link": "https://digiscr.sci.gov.in/view_judgment?id=MjM2MDg=",
        "Citation": "[1990] Supp. (1) S.C.R. 349",
        "Case Type": "(CIVIL APPEAL /105/1990)",
        "Date": "05 SEPTEMBER 1990",
        "Judge Names": "Hon'ble Mr. Justice K. Jagannatha Shetty, Hon'ble Mr. Justice R.M. Sahai\n*",
        "PDF Link": "https://digiscr.sci.gov.in/pdf_viewer?dir=YWRtaW4vanVkZ2VtZW50X2ZpbGUvanVkZ2VtZW50X3BkZi8xOTkwL1N1cHAuICgxKS9QYXJ0IEkvU18xOTkwXzM0OS0zNTRfMTcwMjI3MjY0My5wZGY="
    },
    {
        "volume": "1990Supp. (1)",
        "Case Name": "DR. (MRS.) KIRTI DESHMANKAR VS. UNION OF INDIA AND ORS.",
        "Case Link": "https://digiscr.sci.gov.in/view_judgment?id=MjM2MjM=",
        "Citation": "[1990] Supp. (1) S.C.R. 355",
        "Case Type": "(CIVIL APPEAL /4479/1990)",
        "Date": "06 SEPTEMBER 1990",
        "Judge Names": "Hon'ble Mr. Justice L.M. Sharma\n*, Hon'ble Mr. Justice M.H. Kania",
        "PDF Link": "https://digiscr.sci.gov.in/pdf_viewer?dir=YWRtaW4vanVkZ2VtZW50X2ZpbGUvanVkZ2VtZW50X3BkZi8xOTkwL1N1cHAuICgxKS9QYXJ0IEkvU18xOTkwXzM1NS0zNjFfMTcwMjI3Mjc2OS5wZGY="
    },
    {
        "volume": "1990Supp. (1)",
        "Case Name": "PERIYAR AND PAREEKANNI RUBBERS LTD. VS. STATE OF KERALA",
        "Case Link": "https://digiscr.sci.gov.in/view_judgment?id=MjM2MzQ=",
        "Citation": "[1990] Supp. (1) S.C.R. 362",
        "Case Type": "(CIVIL APPEAL /543/1974)",
        "Date": "06 SEPTEMBER 1990",
        "Judge Names": "Hon'ble Mr. Justice K. Ramaswamy\n*, Hon'ble Mr. Justice L.M. Sharma",
        "PDF Link": "https://digiscr.sci.gov.in/pdf_viewer?dir=YWRtaW4vanVkZ2VtZW50X2ZpbGUvanVkZ2VtZW50X3BkZi8xOTkwL1N1cHAuICgxKS9QYXJ0IEkvU18xOTkwXzM2Mi0zODBfMTcwMjI3Mjg4NS5wZGY="
    },
    {
        "volume": "1990Supp. (1)",
        "Case Name": "YADLAPATI VENKATESWARLU VS. STATE OF ANDHRA PRADESH AND ANR.",
        "Case Link": "https://digiscr.sci.gov.in/view_judgment?id=MjM2NDY=",
        "Citation": "[1990] Supp. (1) S.C.R. 381",
        "Case Type": "(CIVIL APPEAL /2494/1978)",
        "Date": "11 SEPTEMBER 1990",
        "Judge Names": "Hon'ble Mr. Justice K.N. Saikia\n*, Hon'ble Mr. Justice Sabyasachi Mukherjee",
        "PDF Link": "https://digiscr.sci.gov.in/pdf_viewer?dir=YWRtaW4vanVkZ2VtZW50X2ZpbGUvanVkZ2VtZW50X3BkZi8xOTkwL1N1cHAuICgxKS9QYXJ0IEkvU18xOTkwXzM4MS0zOTNfMTcwMjI3Mjk4NC5wZGY="
    },
    {
        "volume": "1990Supp. (1)",
        "Case Name": "MISS LIZA ARULANANDAM VS. SMT. A.S. SULOCHANA",
        "Case Link": "https://digiscr.sci.gov.in/view_judgment?id=MjM2NTk=",
        "Citation": "[1990] Supp. (1) S.C.R. 394",
        "Case Type": "(CIVIL APPEAL /2228/1982)",
        "Date": "11 SEPTEMBER 1990",
        "Judge Names": "Hon'ble Mr. Justice K. Ramaswamy\n*, Hon'ble Mr. Justice K.N. Saikia, Hon'ble Mr. Justice M.H. Kania",
        "PDF Link": "https://digiscr.sci.gov.in/pdf_viewer?dir=YWRtaW4vanVkZ2VtZW50X2ZpbGUvanVkZ2VtZW50X3BkZi8xOTkwL1N1cHAuICgxKS9QYXJ0IEkvU18xOTkwXzM5NC00MDBfMTcwMjI3MzEwOC5wZGY="
    },
    {
        "volume": "1990Supp. (1)",
        "Case Name": "ASHOK KUMAR VS. STATE OF RAJASTHAN",
        "Case Link": "https://digiscr.sci.gov.in/view_judgment?id=MjM2NzA=",
        "Citation": "[1990] Supp. (1) S.C.R. 401",
        "Case Type": "(CRIMINAL APPEAL /453/1986)",
        "Date": "11 SEPTEMBER 1990",
        "Judge Names": "Hon'ble Mr. Justice M.M. Punchhi, Hon'ble Mr. Justice R.M. Sahai\n*",
        "PDF Link": "https://digiscr.sci.gov.in/pdf_viewer?dir=YWRtaW4vanVkZ2VtZW50X2ZpbGUvanVkZ2VtZW50X3BkZi8xOTkwL1N1cHAuICgxKS9QYXJ0IEkvU18xOTkwXzQwMS00MTBfMTcwMjI3MzIxNC5wZGY="
    },
    {
        "volume": "1990Supp. (1)",
        "Case Name": "DESH RAJ GUPTA VS. INDUSTRIAL TRIBUNAL IV, U .P. LUCKNOW AND ANOTHER",
        "Case Link": "https://digiscr.sci.gov.in/view_judgment?id=MjM4MjA=",
        "Citation": "[1990] Supp. (1) S.C.R. 411",
        "Case Type": "(CIVIL APPEAL /453/1984)",
        "Date": "12 SEPTEMBER 1990",
        "Judge Names": "Hon'ble Mr. Justice L.M. Sharma\n*, Hon'ble Mr. Justice M.N. Venkatachaliah",
        "PDF Link": "https://digiscr.sci.gov.in/pdf_viewer?dir=YWRtaW4vanVkZ2VtZW50X2ZpbGUvanVkZ2VtZW50X3BkZi8xOTkwL1N1cHAuICgxKS9QYXJ0IEkvU18xOTkwXzQxMS00MTZfMTcwMjI3NDk0OC5wZGY="
    },
    {
        "volume": "1990Supp. (1)",
        "Case Name": "BARA SINGH VS. KASHMIRA SINGH AND ORS.",
        "Case Link": "https://digiscr.sci.gov.in/view_judgment?id=MjM4MzM=",
        "Citation": "[1990] Supp. (1) S.C.R. 417",
        "Case Type": "(CIVIL APPEAL /1934/1972)",
        "Date": "12 SEPTEMBER 1990",
        "Judge Names": "Hon'ble Mr. Justice K.N. Saikia\n*, Hon'ble Mr. Justice N.M. Kasliwal, Hon'ble Dr. Justice T.K. Thommen",
        "PDF Link": "https://digiscr.sci.gov.in/pdf_viewer?dir=YWRtaW4vanVkZ2VtZW50X2ZpbGUvanVkZ2VtZW50X3BkZi8xOTkwL1N1cHAuICgxKS9QYXJ0IEkvU18xOTkwXzQxNy00MjVfMTcwMjI3NTA3NS5wZGY="
    },
    {
        "volume": "1990Supp. (1)",
        "Case Name": "KULWANT SINGH GILL VS. STATE OF PUNJAB",
        "Case Link": "https://digiscr.sci.gov.in/view_judgment?id=MjM4NDA=",
        "Citation": "[1990] Supp. (1) S.C.R. 426",
        "Case Type": "(CIVIL APPEAL /2960/1987)",
        "Date": "13 SEPTEMBER 1990",
        "Judge Names": "Hon'ble Mr. Justice K. Ramaswamy\n*, Hon'ble Mr. Justice K.N. Saikia, Hon'ble Mr. Justice M.H. Kania",
        "PDF Link": "https://digiscr.sci.gov.in/pdf_viewer?dir=YWRtaW4vanVkZ2VtZW50X2ZpbGUvanVkZ2VtZW50X3BkZi8xOTkwL1N1cHAuICgxKS9QYXJ0IEkvU18xOTkwXzQyNi00MzJfMTcwMjI3NTE2My5wZGY="
    },
    {
        "volume": "1990Supp. (1)",
        "Case Name": "P.N. VEETI NARAYANI VS. PATHUMMA BEEVI AND ANOTHER",
        "Case Link": "https://digiscr.sci.gov.in/view_judgment?id=MjM4NTM=",
        "Citation": "[1990] Supp. (1) S.C.R. 433",
        "Case Type": "(CIVIL APPEAL /229/1976)",
        "Date": "13 SEPTEMBER 1990",
        "Judge Names": "Hon'ble Mr. Justice A.M. Ahmadi, Hon'ble Mr. Justice M.M. Punchhi\n*",
        "PDF Link": "https://digiscr.sci.gov.in/pdf_viewer?dir=YWRtaW4vanVkZ2VtZW50X2ZpbGUvanVkZ2VtZW50X3BkZi8xOTkwL1N1cHAuICgxKS9QYXJ0IEkvU18xOTkwXzQzMy00NDFfMTcwMjI3NTI3MS5wZGY="
    },
    {
        "volume": "1990Supp. (1)",
        "Case Name": "ESKAYEF LIMITED VS. COLLECTOR OF CENTRAL EXCISE",
        "Case Link": "https://digiscr.sci.gov.in/view_judgment?id=MjM4NjI=",
        "Citation": "[1990] Supp. (1) S.C.R. 442",
        "Case Type": "(CIVIL APPEAL /4457/1989)",
        "Date": "14 SEPTEMBER 1990",
        "Judge Names": "Hon'ble Mr. Justice N.M. Kasliwal, Hon'ble Mr. Justice S.C. Agrawal\n*",
        "PDF Link": "https://digiscr.sci.gov.in/pdf_viewer?dir=YWRtaW4vanVkZ2VtZW50X2ZpbGUvanVkZ2VtZW50X3BkZi8xOTkwL1N1cHAuICgxKS9QYXJ0IEkvU18xOTkwXzQ0Mi00NTZfMTcwMjI3NTM1Ny5wZGY="
    },
    {
        "volume": "1990Supp. (1)",
        "Case Name": "KAMARUNNISSA ETC. ETC. VS. UNION OF INDIA AND ORS.",
        "Case Link": "https://digiscr.sci.gov.in/view_judgment?id=MjM4Nzc=",
        "Citation": "[1990] Supp. (1) S.C.R. 457",
        "Case Type": "(WRIT PETITION(CRIMINAL) /757/1990)",
        "Date": "14 SEPTEMBER 1990",
        "Judge Names": "Hon'ble Mr. Justice A.M. Ahmadi\n*, Hon'ble Mr. Justice S.C. Agrawal",
        "PDF Link": "https://digiscr.sci.gov.in/pdf_viewer?dir=YWRtaW4vanVkZ2VtZW50X2ZpbGUvanVkZ2VtZW50X3BkZi8xOTkwL1N1cHAuICgxKS9QYXJ0IEkvU18xOTkwXzQ1Ny00NzJfMTcwMjI3NTQ4OS5wZGY="
    },
    {
        "volume": "1990Supp. (1)",
        "Case Name": "INCOME TAX OFFICER, CALICUT VS. SMT. N.K. SARADA THAMPATTY",
        "Case Link": "https://digiscr.sci.gov.in/view_judgment?id=MjM4OTE=",
        "Citation": "[1990] Supp. (1) S.C.R. 473",
        "Case Type": "(CIVIL APPEAL /778/1976)",
        "Date": "14 SEPTEMBER 1990",
        "Judge Names": "Hon'ble Mr. Justice K. Jagannatha Shetty, Hon'ble Mr. Justice K.N. Singh\n*, Hon'ble Mr. Justice Kuldip Singh",
        "PDF Link": "https://digiscr.sci.gov.in/pdf_viewer?dir=YWRtaW4vanVkZ2VtZW50X2ZpbGUvanVkZ2VtZW50X3BkZi8xOTkwL1N1cHAuICgxKS9QYXJ0IEkvU18xOTkwXzQ3My00ODFfMTcwMjI3NTYyMy5wZGY="
    },
    {
        "volume": "1990Supp. (1)",
        "Case Name": "GOVT. OF ANDHRA PRADESH AND ORS. ETC. VS. M.A. KAREEM AND OTHERS ETC.",
        "Case Link": "https://digiscr.sci.gov.in/view_judgment?id=MjM5MDc=",
        "Citation": "[1990] Supp. (1) S.C.R. 482",
        "Case Type": "(CIVIL APPEAL /173/1986)",
        "Date": "14 SEPTEMBER 1990",
        "Judge Names": "Hon'ble Mr. Justice B.C. Ray, Hon'ble Mr. Justice L.M. Sharma\n*",
        "PDF Link": "https://digiscr.sci.gov.in/pdf_viewer?dir=YWRtaW4vanVkZ2VtZW50X2ZpbGUvanVkZ2VtZW50X3BkZi8xOTkwL1N1cHAuICgxKS9QYXJ0IEkvU18xOTkwXzQ4Mi00OTFfMTcwMjI3NTczOC5wZGY="
    },
    {
        "volume": "1990Supp. (1)",
        "Case Name": "BALDEV RAJ VS. STATE OF HARYANA",
        "Case Link": "https://digiscr.sci.gov.in/view_judgment?id=MjM5MjQ=",
        "Citation": "[1990] Supp. (1) S.C.R. 492",
        "Case Type": "(CRIMINAL APPEAL /206/1979)",
        "Date": "17 SEPTEMBER 1990",
        "Judge Names": "Hon'ble Ms. Justice M. Fathima Beevi\n*, Hon'ble Mr. Justice M.H. Kania",
        "PDF Link": "https://digiscr.sci.gov.in/pdf_viewer?dir=YWRtaW4vanVkZ2VtZW50X2ZpbGUvanVkZ2VtZW50X3BkZi8xOTkwL1N1cHAuICgxKS9QYXJ0IEkvU18xOTkwXzQ5Mi00OThfMTcwMjI3NTg4OS5wZGY="
    },
    {
        "volume": "1990Supp. (1)",
        "Case Name": "PUNJAB TRADERS AND ORS. VS. STATE OF PUNJAB AND ORS.",
        "Case Link": "https://digiscr.sci.gov.in/view_judgment?id=MjM5NDE=",
        "Citation": "[1990] Supp. (1) S.C.R. 499",
        "Case Type": "(CIVIL APPEAL /1372/1980)",
        "Date": "18 SEPTEMBER 1990",
        "Judge Names": "Hon'ble Mr. Justice K.N. Singh, Hon'ble Mr. Justice Kuldip Singh, Hon'ble Dr. Justice T.K. Thommen\n*",
        "PDF Link": "https://digiscr.sci.gov.in/pdf_viewer?dir=YWRtaW4vanVkZ2VtZW50X2ZpbGUvanVkZ2VtZW50X3BkZi8xOTkwL1N1cHAuICgxKS9QYXJ0IEkvU18xOTkwXzQ5OS01MDZfMTcwMjI3NjAyMC5wZGY="
    },
    {
        "volume": "1990Supp. (1)",
        "Case Name": "VEERATIALINGAM AND OTHERS VS. RAMESH AND OTHERS",
        "Case Link": "https://digiscr.sci.gov.in/view_judgment?id=MjM5NzE=",
        "Citation": "[1990] Supp. (1) S.C.R. 507",
        "Case Type": "(CIVIL APPEAL /2231/1988)",
        "Date": "18 SEPTEMBER 1990",
        "Judge Names": "Hon'ble Mr. Justice K. Ramaswamy, Hon'ble Mr. Justice L.M. Sharma\n*",
        "PDF Link": "https://digiscr.sci.gov.in/pdf_viewer?dir=YWRtaW4vanVkZ2VtZW50X2ZpbGUvanVkZ2VtZW50X3BkZi8xOTkwL1N1cHAuICgxKS9QYXJ0IEkvU18xOTkwXzUwNy01MTNfMTcwMjI3NjI2NS5wZGY="
    },
    {
        "volume": "1990Supp. (1)",
        "Case Name": "DR. TARAKPRASAD RAJARAM VS. SMT. VESTA UKARA (DEAD) BY LRS. AND ORS.",
        "Case Link": "https://digiscr.sci.gov.in/view_judgment?id=MjM5ODk=",
        "Citation": "[1990] Supp. (1) S.C.R. 514",
        "Case Type": "(CIVIL APPEAL /786/1976)",
        "Date": "18 SEPTEMBER 1990",
        "Judge Names": "Hon'ble Mr. Justice K.N. Singh\n*, Hon'ble Mr. Justice S. Ratnavel Pandian",
        "PDF Link": "https://digiscr.sci.gov.in/pdf_viewer?dir=YWRtaW4vanVkZ2VtZW50X2ZpbGUvanVkZ2VtZW50X3BkZi8xOTkwL1N1cHAuICgxKS9QYXJ0IEkvU18xOTkwXzUxNC01MjBfMTcwMjI3NjM5NC5wZGY="
    },
    {
        "volume": "1990Supp. (1)",
        "Case Name": "SHESHRAO JANGLUJI BAGDE VS. BHAIYYA S/O GOVINDRAO KARALE AND ORS.",
        "Case Link": "https://digiscr.sci.gov.in/view_judgment?id=MjQwMjU=",
        "Citation": "[1990] Supp. (1) S.C.R. 521",
        "Case Type": "(CIVIL APPEAL /2166/1987)",
        "Date": "18 SEPTEMBER 1990",
        "Judge Names": "Hon'ble Mr. Justice M.M. Punchhi, Hon'ble Mr. Justice V. Ramaswami (No. 2)\n*",
        "PDF Link": "https://digiscr.sci.gov.in/pdf_viewer?dir=YWRtaW4vanVkZ2VtZW50X2ZpbGUvanVkZ2VtZW50X3BkZi8xOTkwL1N1cHAuICgxKS9QYXJ0IEkvU18xOTkwXzUyMS01MjZfMTcwMjI3NjcxMS5wZGY="
    },
    {
        "volume": "1990Supp. (1)",
        "Case Name": "ARDHENDU BHUSAN HALDAR (DEAD) BY L.RS. ETC. ETC. VS. SMT. GANGAMONI MONDAL ETC. ETC.",
        "Case Link": "https://digiscr.sci.gov.in/view_judgment?id=MjQwMzk=",
        "Citation": "[1990] Supp. (1) S.C.R. 527",
        "Case Type": "(CIVIL APPEAL /626/1975)",
        "Date": "18 SEPTEMBER 1990",
        "Judge Names": "Hon'ble Mr. Justice K.N. Saikia, Hon'ble Mr. Justice S. Ranganathan\n*",
        "PDF Link": "https://digiscr.sci.gov.in/pdf_viewer?dir=YWRtaW4vanVkZ2VtZW50X2ZpbGUvanVkZ2VtZW50X3BkZi8xOTkwL1N1cHAuICgxKS9QYXJ0IEkvU18xOTkwXzUyNy01NDFfMTcwMjI3Njg2Mi5wZGY="
    },
    {
        "volume": "1990Supp. (1)",
        "Case Name": "U. PONNAPPA MOOTHAN SONS, PALGHAT VS. CATHOLIC SYRIAN BANK LTD. AND OTHERS",
        "Case Link": "https://digiscr.sci.gov.in/view_judgment?id=MjQwNDk=",
        "Citation": "[1990] Supp. (1) S.C.R. 542",
        "Case Type": "(CIVIL APPEAL /183/1984)",
        "Date": "18 SEPTEMBER 1990",
        "Judge Names": "Hon'ble Mr. Justice J.S. Verma, Hon'ble Mr. Justice K. Jayachandra Reddy\n*",
        "PDF Link": "https://digiscr.sci.gov.in/pdf_viewer?dir=YWRtaW4vanVkZ2VtZW50X2ZpbGUvanVkZ2VtZW50X3BkZi8xOTkwL1N1cHAuICgxKS9QYXJ0IEkvU18xOTkwXzU0Mi01NjFfMTcwMjI3Njk0OC5wZGY="
    },
    {
        "volume": "1990Supp. (1)",
        "Case Name": "JACOB M. PUTHUPARAMBIL AND ORS. ETC. ETC. VS. KERALA WATER AUTHORITY AND ORS. ETC. ETC.",
        "Case Link": "https://digiscr.sci.gov.in/view_judgment?id=MjQwNjE=",
        "Citation": "[1990] Supp. (1) S.C.R. 562",
        "Case Type": "(WRIT PETITION (CIVIL) /112/1990)",
        "Date": "19 SEPTEMBER 1990",
        "Judge Names": "Hon'ble Mr. Justice A.M. Ahmadi\n*, Hon'ble Mr. Justice K. Jayachandra Reddy",
        "PDF Link": "https://digiscr.sci.gov.in/pdf_viewer?dir=YWRtaW4vanVkZ2VtZW50X2ZpbGUvanVkZ2VtZW50X3BkZi8xOTkwL1N1cHAuICgxKS9QYXJ0IEkvU18xOTkwXzU2Mi01NzlfMTcwMjI3NzExMS5wZGY="
    },
    {
        "volume": "1990Supp. (1)",
        "Case Name": "D.M. BHARATI VS. L.M. SUD AND ORS.",
        "Case Link": "https://digiscr.sci.gov.in/view_judgment?id=MjQwNzI=",
        "Citation": "[1990] Supp. (1) S.C.R. 580",
        "Case Type": "(CIVIL APPEAL /1213/1979)",
        "Date": "19 SEPTEMBER 1990",
        "Judge Names": "Hon'ble Mr. Justice A.M. Ahmadi, Hon'ble Mr. Justice S. Ranganathan\n*",
        "PDF Link": "https://digiscr.sci.gov.in/pdf_viewer?dir=YWRtaW4vanVkZ2VtZW50X2ZpbGUvanVkZ2VtZW50X3BkZi8xOTkwL1N1cHAuICgxKS9QYXJ0IEkvU18xOTkwXzU4MC01ODlfMTcwMjI3NzIyNy5wZGY="
    },
    {
        "volume": "1990Supp. (1)",
        "Case Name": "STATE OF MADHYA PRADESH AND ANR. VS. G.S. DALL AND FLOUR MILLS",
        "Case Link": "https://digiscr.sci.gov.in/view_judgment?id=MjQwODU=",
        "Citation": "[1990] Supp. (1) S.C.R. 590",
        "Case Type": "(CIVIL APPEAL /2211/1988)",
        "Date": "19 SEPTEMBER 1990",
        "Judge Names": "Hon'ble Mr. Justice S. Ranganathan\n*, Hon'ble Mr. Justice Sabyasachi Mukherjee",
        "PDF Link": "https://digiscr.sci.gov.in/pdf_viewer?dir=YWRtaW4vanVkZ2VtZW50X2ZpbGUvanVkZ2VtZW50X3BkZi8xOTkwL1N1cHAuICgxKS9QYXJ0IEkvU18xOTkwXzU5MC02MjRfMTcwMjI3NzQwNi5wZGY="
    },
    {
        "volume": "1990Supp. (1)",
        "Case Name": "KUMARI SHRILEKHA VIDYARTHI ETC. ETC VS. STATE OF U.P. AND ORS.",
        "Case Link": "https://digiscr.sci.gov.in/view_judgment?id=MjQwOTY=",
        "Citation": "[1990] Supp. (1) S.C.R. 625",
        "Case Type": "(WRIT PETITION (CIVIL) /706/1990)",
        "Date": "20 SEPTEMBER 1990",
        "Judge Names": "Hon'ble Mr. Justice J.S. Verma\n*, Hon'ble Mr. Justice R.M. Sahai",
        "PDF Link": "https://digiscr.sci.gov.in/pdf_viewer?dir=YWRtaW4vanVkZ2VtZW50X2ZpbGUvanVkZ2VtZW50X3BkZi8xOTkwL1N1cHAuICgxKS9QYXJ0IEkvU18xOTkwXzYyNS02NjFfMTcwMjI3NzUyOC5wZGY="
    },
    {
        "volume": "1990Supp. (1)",
        "Case Name": "SHAM SUNDER VS. PURAN AND ANR.",
        "Case Link": "https://digiscr.sci.gov.in/view_judgment?id=MjQxMDg=",
        "Citation": "[1990] Supp. (1) S.C.R. 662",
        "Case Type": "(CRIMINAL APPEAL /195/1984)",
        "Date": "21 SEPTEMBER 1990",
        "Judge Names": "Hon'ble Ms. Justice M. Fathima Beevi\n*, Hon'ble Mr. Justice S. Ratnavel Pandian",
        "PDF Link": "https://digiscr.sci.gov.in/pdf_viewer?dir=YWRtaW4vanVkZ2VtZW50X2ZpbGUvanVkZ2VtZW50X3BkZi8xOTkwL1N1cHAuICgxKS9QYXJ0IEkvU18xOTkwXzY2Mi02NjhfMTcwMjI3NzY0OC5wZGY="
    }
]