[
    {
        "volume": "1995Volume 1",
        "Case Name": "STATE OF ORISSA VS. SANGRAM DAS",
        "Case Link": "https://digiscr.sci.gov.in/view_judgment?id=MTkyNjg=",
        "Citation": "[1995] 1 S.C.R. 1",
        "Case Type": "(CIVIL APPEAL /103/1995)",
        "Date": "02 JANUARY 1995",
        "Judge Names": "Hon'ble Mr. Justice K. Ramaswamy, Hon'ble Mr. Justice N. Venkatachala",
        "PDF Link": "https://digiscr.sci.gov.in/pdf_viewer?dir=YWRtaW4vanVkZ2VtZW50X2ZpbGUvanVkZ2VtZW50X3BkZi8xOTk1L3ZvbHVtZSAxL1BhcnQgSS8xOTk1XzFfMV8xNzAyMDEzNDQ4LnBkZg=="
    },
    {
        "volume": "1995Volume 1",
        "Case Name": "BIRLA CEMENT WORKS VS. G.M. WESTERN RAILWAY AND ANR.",
        "Case Link": "https://digiscr.sci.gov.in/view_judgment?id=MTkyNzk=",
        "Citation": "[1995] 1 S.C.R. 5",
        "Case Type": "(SPECIAL LEAVE PETITION (CIVIL) /21448/1994)",
        "Date": "02 JANUARY 1995",
        "Judge Names": "Hon'ble Mr. Justice K. Ramaswamy",
        "PDF Link": "https://digiscr.sci.gov.in/pdf_viewer?dir=YWRtaW4vanVkZ2VtZW50X2ZpbGUvanVkZ2VtZW50X3BkZi8xOTk1L3ZvbHVtZSAxL1BhcnQgSS8xOTk1XzFfNV8xNzAyMDEzNTYzLnBkZg=="
    },
    {
        "volume": "1995Volume 1",
        "Case Name": "STATE OF RAJASTHAN VS. SEVANIVATRA KARAMCHARI HITKARI SAMITI",
        "Case Link": "https://digiscr.sci.gov.in/view_judgment?id=MTkyOTE=",
        "Citation": "[1995] 1 S.C.R. 8",
        "Case Type": "(CIVIL APPEAL /29/1995)",
        "Date": "03 JANUARY 1995",
        "Judge Names": "Hon'ble Mr. Justice G.N. Ray\n*, Hon'ble Mr. Justice P.B. Sawant",
        "PDF Link": "https://digiscr.sci.gov.in/pdf_viewer?dir=YWRtaW4vanVkZ2VtZW50X2ZpbGUvanVkZ2VtZW50X3BkZi8xOTk1L3ZvbHVtZSAxL1BhcnQgSS8xOTk1XzFfOF8xNzAyMDEzNjc0LnBkZg=="
    },
    {
        "volume": "1995Volume 1",
        "Case Name": "SALES TAX COMMISSIONER ETC. ETC. VS. B.G. PATEL ETC. ETC.",
        "Case Link": "https://digiscr.sci.gov.in/view_judgment?id=MTkzMDQ=",
        "Citation": "[1995] 1 S.C.R. 22",
        "Case Type": "(SPECIAL LEAVE PETITION (CIVIL) /1383-92/1995)",
        "Date": "03 JANUARY 1995",
        "Judge Names": "Hon'ble Mr. Justice K. Ramaswamy, Hon'ble Mr. Justice N. Venkatachala",
        "PDF Link": "https://digiscr.sci.gov.in/pdf_viewer?dir=YWRtaW4vanVkZ2VtZW50X2ZpbGUvanVkZ2VtZW50X3BkZi8xOTk1L3ZvbHVtZSAxL1BhcnQgSS8xOTk1XzFfMjJfMTcwMjAxMzc4NS5wZGY="
    },
    {
        "volume": "1995Volume 1",
        "Case Name": "GIANI DEVENDAR SINGH SANT SEPOY SINGH VS. UNION OF INDIA AND ANOTHER",
        "Case Link": "https://digiscr.sci.gov.in/view_judgment?id=MTkzMTQ=",
        "Citation": "[1995] 1 S.C.R. 27",
        "Case Type": "(SPECIAL LEAVE PETITION (CRIMINAL) /1208-09/1994)",
        "Date": "04 JANUARY 1995",
        "Judge Names": "Hon'ble Mr. Justice P.B. Sawant, Hon'ble Mr. Justice G.N. Ray\n*",
        "PDF Link": "https://digiscr.sci.gov.in/pdf_viewer?dir=YWRtaW4vanVkZ2VtZW50X2ZpbGUvanVkZ2VtZW50X3BkZi8xOTk1L3ZvbHVtZSAxL1BhcnQgSS8xOTk1XzFfMjdfMTcwMjAxMzg3NC5wZGY="
    },
    {
        "volume": "1995Volume 1",
        "Case Name": "MUKHTIAR SINGH AND ANR. ETC. VS. STATE OF PUNJAB ETC.",
        "Case Link": "https://digiscr.sci.gov.in/view_judgment?id=MTkzMjY=",
        "Citation": "[1995] 1 S.C.R. 38",
        "Case Type": "(CRIMINAL APPEAL /434/1985)",
        "Date": "04 JANUARY 1995",
        "Judge Names": "Hon'ble Dr. Justice A.S. Anand\n*, Hon'ble Mr. Justice M.K. Mukherjee",
        "PDF Link": "https://digiscr.sci.gov.in/pdf_viewer?dir=YWRtaW4vanVkZ2VtZW50X2ZpbGUvanVkZ2VtZW50X3BkZi8xOTk1L3ZvbHVtZSAxL1BhcnQgSS8xOTk1XzFfMzhfMTcwMjAxMzk4OC5wZGY="
    },
    {
        "volume": "1995Volume 1",
        "Case Name": "M/S UNITED GLASS, BANGALORE VS. COLLECTOR OF CENTRAL EXCISE",
        "Case Link": "https://digiscr.sci.gov.in/view_judgment?id=MTkzNDU=",
        "Citation": "[1995] 1 S.C.R. 47",
        "Case Type": "(CIVIL APPEAL /2466/1989)",
        "Date": "05 JANUARY 1995",
        "Judge Names": "Hon'ble Mr. Justice B.P. Jeevan Reddy\n*, Hon'ble Mr. Justice S.B. Majmudar",
        "PDF Link": "https://digiscr.sci.gov.in/pdf_viewer?dir=YWRtaW4vanVkZ2VtZW50X2ZpbGUvanVkZ2VtZW50X3BkZi8xOTk1L3ZvbHVtZSAxL1BhcnQgSS8xOTk1XzFfNDdfMTcwMjAxNDE3MC5wZGY="
    },
    {
        "volume": "1995Volume 1",
        "Case Name": "SHRI HARISH TANDON VS. THE ADDL. DISTRICT MAGISTRATE, ALLAHABAD, U.P. AND ORS.",
        "Case Link": "https://digiscr.sci.gov.in/view_judgment?id=MTkzNTc=",
        "Citation": "[1995] 1 S.C.R. 56",
        "Case Type": "(CIVIL APPEAL /574/1993)",
        "Date": "05 JANUARY 1995",
        "Judge Names": "Hon'ble Dr. Justice A.S. Anand, Hon'ble Mr. Justice P.B. Sawant, Hon'ble Mr. Justice N.P. Singh\n*",
        "PDF Link": "https://digiscr.sci.gov.in/pdf_viewer?dir=YWRtaW4vanVkZ2VtZW50X2ZpbGUvanVkZ2VtZW50X3BkZi8xOTk1L3ZvbHVtZSAxL1BhcnQgSS8xOTk1XzFfNTZfMTcwMjAxNDI3NS5wZGY="
    },
    {
        "volume": "1995Volume 1",
        "Case Name": "R.D. HATTANGADI VS. MIS. PEST CONTROL (INDIA) PVT. LTD. AND ORS.",
        "Case Link": "https://digiscr.sci.gov.in/view_judgment?id=MTkzNzg=",
        "Citation": "[1995] 1 S.C.R. 75",
        "Case Type": "(CIVIL APPEAL /1799-1800/1989)",
        "Date": "06 JANUARY 1995",
        "Judge Names": "Hon'ble Mr. Justice A.M. Ahmadi, Hon'ble Mr. Justice N.P. Singh\n*",
        "PDF Link": "https://digiscr.sci.gov.in/pdf_viewer?dir=YWRtaW4vanVkZ2VtZW50X2ZpbGUvanVkZ2VtZW50X3BkZi8xOTk1L3ZvbHVtZSAxL1BhcnQgSS8xOTk1XzFfNzVfMTcwMjAxNDQzMi5wZGY="
    },
    {
        "volume": "1995Volume 1",
        "Case Name": "ANNASAHEB BAPUSAHEB PATIL AND ORS. VS. BALWANT@ BALASAHEB BABUSAHEB PATIL (DEAD) BY LRS. AND HEIRS ETC.",
        "Case Link": "https://digiscr.sci.gov.in/view_judgment?id=MTkzOTg=",
        "Citation": "[1995] 1 S.C.R. 88",
        "Case Type": "(CIVIL APPEAL /32/1980)",
        "Date": "06 JANUARY 1995",
        "Judge Names": "Hon'ble Mr. Justice K. Ramaswamy\n*, Hon'ble Mr. Justice N. Venkatachala, Hon'ble Mr. Justice S. Mohan",
        "PDF Link": "https://digiscr.sci.gov.in/pdf_viewer?dir=YWRtaW4vanVkZ2VtZW50X2ZpbGUvanVkZ2VtZW50X3BkZi8xOTk1L3ZvbHVtZSAxL1BhcnQgSS8xOTk1XzFfODhfMTcwMjAxNDU3Mi5wZGY="
    },
    {
        "volume": "1995Volume 1",
        "Case Name": "STATE OF ORISSA AND ANR. VS. DR. PYARI MOHAN MISRA",
        "Case Link": "https://digiscr.sci.gov.in/view_judgment?id=MTk0MjM=",
        "Citation": "[1995] 1 S.C.R. 104",
        "Case Type": "(CIVIL APPEAL /1152/1995)",
        "Date": "06 JANUARY 1995",
        "Judge Names": "Hon'ble Mr. Justice K. Ramaswamy, Hon'ble Mr. Justice N. Venkatachala",
        "PDF Link": "https://digiscr.sci.gov.in/pdf_viewer?dir=YWRtaW4vanVkZ2VtZW50X2ZpbGUvanVkZ2VtZW50X3BkZi8xOTk1L3ZvbHVtZSAxL1BhcnQgSS8xOTk1XzFfMTA0XzE3MDIwMTQ3NTMucGRm"
    },
    {
        "volume": "1995Volume 1",
        "Case Name": "M/S. NOVA STEEL (INDIA) LTD. VS. M.C.D. AND ORS.",
        "Case Link": "https://digiscr.sci.gov.in/view_judgment?id=MTk2ODI=",
        "Citation": "[1995] 1 S.C.R. 107",
        "Case Type": "(SPECIAL LEAVE PETITION (CIVIL) /22863/1994)",
        "Date": "06 JANUARY 1995",
        "Judge Names": "Hon'ble Mr. Justice K. Ramaswamy, Hon'ble Mr. Justice N. Venkatachala",
        "PDF Link": "https://digiscr.sci.gov.in/pdf_viewer?dir=YWRtaW4vanVkZ2VtZW50X2ZpbGUvanVkZ2VtZW50X3BkZi8xOTk1L3ZvbHVtZSAxL1BhcnQgSS8xOTk1XzFfMTA3XzE3MDIwMTY3NjcucGRm"
    },
    {
        "volume": "1995Volume 1",
        "Case Name": "NATWAR TEXTILE PROCESSORS PVT. LTD. AND ANR. VS. UNION OF INDIA AND ORS.",
        "Case Link": "https://digiscr.sci.gov.in/view_judgment?id=MTk3MDA=",
        "Citation": "[1995] 1 S.C.R. 109",
        "Case Type": "(CIVIL APPEAL /185/1995)",
        "Date": "09 JANUARY 1995",
        "Judge Names": "Hon'ble Mr. Justice B.P. Jeevan Reddy\n*, Hon'ble Ms. Justice Sujata V Manohar",
        "PDF Link": "https://digiscr.sci.gov.in/pdf_viewer?dir=YWRtaW4vanVkZ2VtZW50X2ZpbGUvanVkZ2VtZW50X3BkZi8xOTk1L3ZvbHVtZSAxL1BhcnQgSS8xOTk1XzFfMTA5XzE3MDIwMTY5MzAucGRm"
    },
    {
        "volume": "1995Volume 1",
        "Case Name": "U.P. JAL NIGAM AND ORS. VS. DURGA PRASAD SINGH AND ORS.",
        "Case Link": "https://digiscr.sci.gov.in/view_judgment?id=MTk3MTI=",
        "Citation": "[1995] 1 S.C.R. 119",
        "Case Type": "(CIVIL APPEAL /9214/1994)",
        "Date": "09 JANUARY 1995",
        "Judge Names": "Hon'ble Mr. Justice K. Ramaswamy, Hon'ble Mr. Justice S.C. Sen",
        "PDF Link": "https://digiscr.sci.gov.in/pdf_viewer?dir=YWRtaW4vanVkZ2VtZW50X2ZpbGUvanVkZ2VtZW50X3BkZi8xOTk1L3ZvbHVtZSAxL1BhcnQgSS8xOTk1XzFfMTE5XzE3MDIwMTcwNDQucGRm"
    },
    {
        "volume": "1995Volume 1",
        "Case Name": "SIRI PAL VS. HARYANA STATE ELECTRICITY BOARD",
        "Case Link": "https://digiscr.sci.gov.in/view_judgment?id=MTk3MjU=",
        "Citation": "[1995] 1 S.C.R. 122",
        "Case Type": "(CIVIL APPEAL /722/1995)",
        "Date": "09 JANUARY 1995",
        "Judge Names": "Hon'ble Mr. Justice K. Ramaswamy, Hon'ble Mr. Justice S.C. Sen",
        "PDF Link": "https://digiscr.sci.gov.in/pdf_viewer?dir=YWRtaW4vanVkZ2VtZW50X2ZpbGUvanVkZ2VtZW50X3BkZi8xOTk1L3ZvbHVtZSAxL1BhcnQgSS8xOTk1XzFfMTIyXzE3MDIwMTcxMzIucGRm"
    },
    {
        "volume": "1995Volume 1",
        "Case Name": "CHANDIGARH ADMINISTRATION AND ANR VS. JAGJIT SINGH AND ANR. ETC.",
        "Case Link": "https://digiscr.sci.gov.in/view_judgment?id=MTk3Mzc=",
        "Citation": "[1995] 1 S.C.R. 126",
        "Case Type": "(CIVIL APPEAL /674/1995)",
        "Date": "10 JANUARY 1995",
        "Judge Names": "Hon'ble Mr. Justice B.P. Jeevan Reddy\n*, Hon'ble Ms. Justice Sujata V Manohar",
        "PDF Link": "https://digiscr.sci.gov.in/pdf_viewer?dir=YWRtaW4vanVkZ2VtZW50X2ZpbGUvanVkZ2VtZW50X3BkZi8xOTk1L3ZvbHVtZSAxL1BhcnQgSS8xOTk1XzFfMTI2XzE3MDIwMTcyNDcucGRm"
    },
    {
        "volume": "1995Volume 1",
        "Case Name": "METAL BOX INDIA LTD. VS. THE COLLECTOR OF CENTRAL EXCISE, MADRAS",
        "Case Link": "https://digiscr.sci.gov.in/view_judgment?id=MTk3NDg=",
        "Citation": "[1995] 1 S.C.R. 136",
        "Case Type": "(CIVIL APPEAL /215-16/1989)",
        "Date": "10 JANUARY 1995",
        "Judge Names": "Hon'ble Mr. Justice B.P. Jeevan Reddy, Hon'ble Mr. Justice S.B. Majmudar\n*",
        "PDF Link": "https://digiscr.sci.gov.in/pdf_viewer?dir=YWRtaW4vanVkZ2VtZW50X2ZpbGUvanVkZ2VtZW50X3BkZi8xOTk1L3ZvbHVtZSAxL1BhcnQgSS8xOTk1XzFfMTM2XzE3MDIwMTczNTYucGRm"
    },
    {
        "volume": "1995Volume 1",
        "Case Name": "DR. BAL KRISHNA AGARWAL VS. STATE OF UTTAR PRADESH AND ORS.",
        "Case Link": "https://digiscr.sci.gov.in/view_judgment?id=MTk3NTY=",
        "Citation": "[1995] 1 S.C.R. 148",
        "Case Type": "(CIVIL APPEAL /607/1995)",
        "Date": "10 JANUARY 1995",
        "Judge Names": "Hon'ble Mr. Justice S.C. Agrawal\n*, Hon'ble Mr. Justice Faizanuddin",
        "PDF Link": "https://digiscr.sci.gov.in/pdf_viewer?dir=YWRtaW4vanVkZ2VtZW50X2ZpbGUvanVkZ2VtZW50X3BkZi8xOTk1L3ZvbHVtZSAxL1BhcnQgSS8xOTk1XzFfMTQ4XzE3MDIwMTc0NjEucGRm"
    },
    {
        "volume": "1995Volume 1",
        "Case Name": "RAJESWARI AMMA AND ANR. VS. JOSEPH AND ANR.",
        "Case Link": "https://digiscr.sci.gov.in/view_judgment?id=MTk3NzU=",
        "Citation": "[1995] 1 S.C.R. 163",
        "Case Type": "(CIVIL APPEAL /695/1986)",
        "Date": "10 JANUARY 1995",
        "Judge Names": "Hon'ble Mr. Justice K. Ramaswamy, Hon'ble Ms. Justice Sujata V Manohar",
        "PDF Link": "https://digiscr.sci.gov.in/pdf_viewer?dir=YWRtaW4vanVkZ2VtZW50X2ZpbGUvanVkZ2VtZW50X3BkZi8xOTk1L3ZvbHVtZSAxL1BhcnQgSS8xOTk1XzFfMTYzXzE3MDIwMTc2OTUucGRm"
    },
    {
        "volume": "1995Volume 1",
        "Case Name": "KARNAIL SINGH VS. ANIL KUMAR AND ANR.",
        "Case Link": "https://digiscr.sci.gov.in/view_judgment?id=MTk3OTI=",
        "Citation": "[1995] 1 S.C.R. 165",
        "Case Type": "(CIVIL APPEAL /1569/1986)",
        "Date": "10 JANUARY 1995",
        "Judge Names": "Hon'ble Mr. Justice K. Ramaswamy, Hon'ble Ms. Justice Sujata V Manohar",
        "PDF Link": "https://digiscr.sci.gov.in/pdf_viewer?dir=YWRtaW4vanVkZ2VtZW50X2ZpbGUvanVkZ2VtZW50X3BkZi8xOTk1L3ZvbHVtZSAxL1BhcnQgSS8xOTk1XzFfMTY1XzE3MDIwMTc4MjMucGRm"
    },
    {
        "volume": "1995Volume 1",
        "Case Name": "SMT. PREM LATA AND ANR. VS. M/S ISHAR DASS CHAMAN LAL AND ORS .",
        "Case Link": "https://digiscr.sci.gov.in/view_judgment?id=MTk4MDc=",
        "Citation": "[1995] 1 S.C.R. 168",
        "Case Type": "(CIVIL APPEAL /5491/1985)",
        "Date": "10 JANUARY 1995",
        "Judge Names": "Hon'ble Mr. Justice K. Ramaswamy, Hon'ble Ms. Justice Sujata V Manohar",
        "PDF Link": "https://digiscr.sci.gov.in/pdf_viewer?dir=YWRtaW4vanVkZ2VtZW50X2ZpbGUvanVkZ2VtZW50X3BkZi8xOTk1L3ZvbHVtZSAxL1BhcnQgSS8xOTk1XzFfMTY4XzE3MDIwMTc5NjAucGRm"
    },
    {
        "volume": "1995Volume 1",
        "Case Name": "CHIEF MEDICAL OFFICER VS. KHADEER KHADRI",
        "Case Link": "https://digiscr.sci.gov.in/view_judgment?id=MTk4MTg=",
        "Citation": "[1995] 1 S.C.R. 175",
        "Case Type": "(CIVIL APPEAL /748/1995)",
        "Date": "10 JANUARY 1995",
        "Judge Names": "Hon'ble Mr. Justice K. Ramaswamy, Hon'ble Ms. Justice Sujata V Manohar",
        "PDF Link": "https://digiscr.sci.gov.in/pdf_viewer?dir=YWRtaW4vanVkZ2VtZW50X2ZpbGUvanVkZ2VtZW50X3BkZi8xOTk1L3ZvbHVtZSAxL1BhcnQgSS8xOTk1XzFfMTc1XzE3MDIwMTgwNTcucGRm"
    },
    {
        "volume": "1995Volume 1",
        "Case Name": "AYUB KHAN VS. DEEP KUMAR CHAWLA AND ORS. ETC.",
        "Case Link": "https://digiscr.sci.gov.in/view_judgment?id=MTk4MzM=",
        "Citation": "[1995] 1 S.C.R. 177",
        "Case Type": "(CIVIL APPEAL /2548-2556/1986)",
        "Date": "10 JANUARY 1995",
        "Judge Names": "Hon'ble Mr. Justice K. Ramaswamy, Hon'ble Ms. Justice Sujata V Manohar",
        "PDF Link": "https://digiscr.sci.gov.in/pdf_viewer?dir=YWRtaW4vanVkZ2VtZW50X2ZpbGUvanVkZ2VtZW50X3BkZi8xOTk1L3ZvbHVtZSAxL1BhcnQgSS8xOTk1XzFfMTc3XzE3MDIwMTgxNTAucGRm"
    },
    {
        "volume": "1995Volume 1",
        "Case Name": "THE SPECIAL TEHSILDAR (LA) P.W.D. SCHEMES, VIJAYAWADA VS. M.A. JABBAR",
        "Case Link": "https://digiscr.sci.gov.in/view_judgment?id=MTk4NTQ=",
        "Citation": "[1995] 1 S.C.R. 180",
        "Case Type": "(CIVIL APPEAL /1891-92/1989)",
        "Date": "11 JANUARY 1995",
        "Judge Names": "Hon'ble Mr. Justice K. Ramaswamy, Hon'ble Ms. Justice Sujata V Manohar",
        "PDF Link": "https://digiscr.sci.gov.in/pdf_viewer?dir=YWRtaW4vanVkZ2VtZW50X2ZpbGUvanVkZ2VtZW50X3BkZi8xOTk1L3ZvbHVtZSAxL1BhcnQgSS8xOTk1XzFfMTgwXzE3MDIwMTgzMjMucGRm"
    },
    {
        "volume": "1995Volume 1",
        "Case Name": "RAJ KUMAR AND ANR. VS. STATE OF PUNJAB AND ANR.",
        "Case Link": "https://digiscr.sci.gov.in/view_judgment?id=MTk4NzI=",
        "Citation": "[1995] 1 S.C.R. 184",
        "Case Type": "(CIVIL APPEAL /783-84/1995)",
        "Date": "11 NOVEMBER 1995",
        "Judge Names": "Hon'ble Mr. Justice K. Ramaswamy, Hon'ble Ms. Justice Sujata V Manohar",
        "PDF Link": "https://digiscr.sci.gov.in/pdf_viewer?dir=YWRtaW4vanVkZ2VtZW50X2ZpbGUvanVkZ2VtZW50X3BkZi8xOTk1L3ZvbHVtZSAxL1BhcnQgSS8xOTk1XzFfMTg0XzE3MDIwMTg0NTMucGRm"
    },
    {
        "volume": "1995Volume 1",
        "Case Name": "V.M. SALGOACAR AND BROTHER LTD. VS. UNION OF INDIA",
        "Case Link": "https://digiscr.sci.gov.in/view_judgment?id=MTk4OTk=",
        "Citation": "[1995] 1 S.C.R. 188",
        "Case Type": "(CIVIL APPEAL /3800/1989)",
        "Date": "11 JANUARY 1995",
        "Judge Names": "Hon'ble Mr. Justice K. Ramaswamy, Hon'ble Ms. Justice Sujata V Manohar",
        "PDF Link": "https://digiscr.sci.gov.in/pdf_viewer?dir=YWRtaW4vanVkZ2VtZW50X2ZpbGUvanVkZ2VtZW50X3BkZi8xOTk1L3ZvbHVtZSAxL1BhcnQgSS8xOTk1XzFfMTg4XzE3MDIwMTg2NzkucGRm"
    },
    {
        "volume": "1995Volume 1",
        "Case Name": "SH. LOKRAJ AND ORS. VS. KISHAN LAL AND ORS.",
        "Case Link": "https://digiscr.sci.gov.in/view_judgment?id=MTk5MTE=",
        "Citation": "[1995] 1 S.C.R. 193",
        "Case Type": "(CIVIL APPEAL /1400/1986)",
        "Date": "11 JANUARY 1995",
        "Judge Names": "Hon'ble Mr. Justice K. Ramaswamy, Hon'ble Ms. Justice Sujata V Manohar",
        "PDF Link": "https://digiscr.sci.gov.in/pdf_viewer?dir=YWRtaW4vanVkZ2VtZW50X2ZpbGUvanVkZ2VtZW50X3BkZi8xOTk1L3ZvbHVtZSAxL1BhcnQgSS8xOTk1XzFfMTkzXzE3MDIwMTg3NjkucGRm"
    },
    {
        "volume": "1995Volume 1",
        "Case Name": "SH. JAGANNATH AND ORS. VS. STATE OF UTTAR PRADESH",
        "Case Link": "https://digiscr.sci.gov.in/view_judgment?id=MTk5MzA=",
        "Citation": "[1995] 1 S.C.R. 198",
        "Case Type": "(CRIMINAL APPEAL /63/1994)",
        "Date": "12 JANUARY 1995",
        "Judge Names": "Hon'ble Dr. Justice A.S. Anand, Hon'ble Mr. Justice M.K. Mukherjee\n*",
        "PDF Link": "https://digiscr.sci.gov.in/pdf_viewer?dir=YWRtaW4vanVkZ2VtZW50X2ZpbGUvanVkZ2VtZW50X3BkZi8xOTk1L3ZvbHVtZSAxL1BhcnQgSS8xOTk1XzFfMTk4XzE3MDIwMTg5MTkucGRm"
    },
    {
        "volume": "1995Volume 1",
        "Case Name": "STATE ROAD TRANSPORT CORPORATION AND ORS. VS. U.P. PARIVAHAN NIGAM SHISHUKHS BEROZGAR SANGH AND ORS.",
        "Case Link": "https://digiscr.sci.gov.in/view_judgment?id=MTk5Njc=",
        "Citation": "[1995] 1 S.C.R. 204",
        "Case Type": "(CIVIL APPEAL /4347-54/1990)",
        "Date": "12 JANUARY 1995",
        "Judge Names": "Hon'ble Mr. Justice Kuldip Singh, Hon'ble Mr. Justice B.L. Hansaria\n*, Hon'ble Mr. Justice S.B. Majmudar",
        "PDF Link": "https://digiscr.sci.gov.in/pdf_viewer?dir=YWRtaW4vanVkZ2VtZW50X2ZpbGUvanVkZ2VtZW50X3BkZi8xOTk1L3ZvbHVtZSAxL1BhcnQgSS8xOTk1XzFfMjA0XzE3MDIwMTkxNDgucGRm"
    },
    {
        "volume": "1995Volume 1",
        "Case Name": "ROMESH CHANDER VS. SMT. SAVITRI",
        "Case Link": "https://digiscr.sci.gov.in/view_judgment?id=MTk5ODA=",
        "Citation": "[1995] 1 S.C.R. 212",
        "Case Type": "(CIVIL APPEAL /714/1995)",
        "Date": "13 JANUARY 1995",
        "Judge Names": "Hon'ble Mr. Justice R.M. Sahai\n*, Hon'ble Mr. Justice S.B. Majmudar",
        "PDF Link": "https://digiscr.sci.gov.in/pdf_viewer?dir=YWRtaW4vanVkZ2VtZW50X2ZpbGUvanVkZ2VtZW50X3BkZi8xOTk1L3ZvbHVtZSAxL1BhcnQgSS8xOTk1XzFfMjEyXzE3MDIwMTkyNDQucGRm"
    },
    {
        "volume": "1995Volume 1",
        "Case Name": "STATE OF RAJASTHAN AND ANR. VS. GOPALDAS ETC. ETC.",
        "Case Link": "https://digiscr.sci.gov.in/view_judgment?id=MTk5OTQ=",
        "Citation": "[1995] 1 S.C.R. 214",
        "Case Type": "(CIVIL APPEAL /3528/1991)",
        "Date": "13 JANUARY 1995",
        "Judge Names": "Hon'ble Mr. Justice Kuldip Singh\n*, Hon'ble Mr. Justice B.L. Hansaria",
        "PDF Link": "https://digiscr.sci.gov.in/pdf_viewer?dir=YWRtaW4vanVkZ2VtZW50X2ZpbGUvanVkZ2VtZW50X3BkZi8xOTk1L3ZvbHVtZSAxL1BhcnQgSS8xOTk1XzFfMjE0XzE3MDIwMTkzNTAucGRm"
    },
    {
        "volume": "1995Volume 1",
        "Case Name": "DINESH PRASAD YADA V VS. STATE OF BIHAR AND ORS.",
        "Case Link": "https://digiscr.sci.gov.in/view_judgment?id=MjAwMDg=",
        "Citation": "[1995] 1 S.C.R. 220",
        "Case Type": "(CIVIL APPEAL /7423/1994)",
        "Date": "13 JANUARY 1995",
        "Judge Names": "Hon'ble Mr. Justice Kuldip Singh\n*, Hon'ble Mr. Justice B.L. Hansaria",
        "PDF Link": "https://digiscr.sci.gov.in/pdf_viewer?dir=YWRtaW4vanVkZ2VtZW50X2ZpbGUvanVkZ2VtZW50X3BkZi8xOTk1L3ZvbHVtZSAxL1BhcnQgSS8xOTk1XzFfMjIwXzE3MDIwMTk0NDEucGRm"
    },
    {
        "volume": "1995Volume 1",
        "Case Name": "COMMISSIONER OF INCOME-TAX VS. CHITTOR ELECTRIC SUPPLY CORPORATION AND ANR.",
        "Case Link": "https://digiscr.sci.gov.in/view_judgment?id=MjAwMjY=",
        "Citation": "[1995] 1 S.C.R. 231",
        "Case Type": "(CIVIL APPEAL /1413/1977)",
        "Date": "13 JANUARY 1995",
        "Judge Names": "Hon'ble Mr. Justice B.P. Jeevan Reddy\n*, Hon'ble Mr. Justice N.P. Singh, Hon'ble Mr. Justice S.C. Sen",
        "PDF Link": "https://digiscr.sci.gov.in/pdf_viewer?dir=YWRtaW4vanVkZ2VtZW50X2ZpbGUvanVkZ2VtZW50X3BkZi8xOTk1L3ZvbHVtZSAxL1BhcnQgSS8xOTk1XzFfMjMxXzE3MDIwMTk1NDYucGRm"
    },
    {
        "volume": "1995Volume 1",
        "Case Name": "P.L. KANTHA RAO AND ORS. VS. STATE OF ANDHRA PRADESH",
        "Case Link": "https://digiscr.sci.gov.in/view_judgment?id=MjAwNDU=",
        "Citation": "[1995] 1 S.C.R. 240",
        "Case Type": "(SPECIAL LEAVE PETITION (CIVIL) /23415/1994)",
        "Date": "13 JANUARY 1995",
        "Judge Names": "Hon'ble Mr. Justice K. Ramaswamy",
        "PDF Link": "https://digiscr.sci.gov.in/pdf_viewer?dir=YWRtaW4vanVkZ2VtZW50X2ZpbGUvanVkZ2VtZW50X3BkZi8xOTk1L3ZvbHVtZSAxL1BhcnQgSS8xOTk1XzFfXzE3MDIwMTk2NzcucGRm"
    },
    {
        "volume": "1995Volume 1",
        "Case Name": "COLLECTOR OF MADRAS AND ANR. VS. K. RAJAMANICKAM",
        "Case Link": "https://digiscr.sci.gov.in/view_judgment?id=MjAwNjQ=",
        "Citation": "[1995] 1 S.C.R. 243",
        "Case Type": "(CIVIL APPEAL /820/1995)",
        "Date": "13 JANUARY 1995",
        "Judge Names": "Hon'ble Mr. Justice K. Ramaswamy, Hon'ble Mr. Justice S.C. Sen",
        "PDF Link": "https://digiscr.sci.gov.in/pdf_viewer?dir=YWRtaW4vanVkZ2VtZW50X2ZpbGUvanVkZ2VtZW50X3BkZi8xOTk1L3ZvbHVtZSAxL1BhcnQgSS8xOTk1XzFfMjQzXzE3MDIwMTk4MTYucGRm"
    },
    {
        "volume": "1995Volume 1",
        "Case Name": "STATE OF ANDHRA PRADESH VS. KORRAPATI SUBRAHMANYAM AND ORS.",
        "Case Link": "https://digiscr.sci.gov.in/view_judgment?id=MjAwODA=",
        "Citation": "[1995] 1 S.C.R. 246",
        "Case Type": "(CRIMINAL APPEAL /71/1995)",
        "Date": "13 JANUARY 1995",
        "Judge Names": "Hon'ble Mr. Justice K. Ramaswamy, Hon'ble Mr. Justice S.C. Sen",
        "PDF Link": "https://digiscr.sci.gov.in/pdf_viewer?dir=YWRtaW4vanVkZ2VtZW50X2ZpbGUvanVkZ2VtZW50X3BkZi8xOTk1L3ZvbHVtZSAxL1BhcnQgSS8xOTk1XzFfMjQ2XzE3MDIwMTk5MDIucGRm"
    },
    {
        "volume": "1995Volume 1",
        "Case Name": "UNION OF INDIA VS. B.V. SAROJA AND ANR.",
        "Case Link": "https://digiscr.sci.gov.in/view_judgment?id=MjAwOTc=",
        "Citation": "[1995] 1 S.C.R. 250",
        "Case Type": "(REVIEW PETITION (CIVIL) /41/1993)",
        "Date": "13 JANUARY 1995",
        "Judge Names": "Hon'ble Dr. Justice A.S. Anand, Hon'ble Mr. Justice K. Ramaswamy",
        "PDF Link": "https://digiscr.sci.gov.in/pdf_viewer?dir=YWRtaW4vanVkZ2VtZW50X2ZpbGUvanVkZ2VtZW50X3BkZi8xOTk1L3ZvbHVtZSAxL1BhcnQgSS8xOTk1XzFfMjUwXzE3MDIwMjAwMTcucGRm"
    },
    {
        "volume": "1995Volume 1",
        "Case Name": "STATE OF HARYANA AND ANR. VS. JAGDISH CHANDER",
        "Case Link": "https://digiscr.sci.gov.in/view_judgment?id=MjAxMTA=",
        "Citation": "[1995] 1 S.C.R. 252",
        "Case Type": "(CIVIL APPEAL /1088 and 1089/1995)",
        "Date": "13 JANUARY 1995",
        "Judge Names": "Hon'ble Mr. Justice K. Ramaswamy, Hon'ble Mr. Justice S.C. Sen",
        "PDF Link": "https://digiscr.sci.gov.in/pdf_viewer?dir=YWRtaW4vanVkZ2VtZW50X2ZpbGUvanVkZ2VtZW50X3BkZi8xOTk1L3ZvbHVtZSAxL1BhcnQgSS8xOTk1XzFfMjUyXzE3MDIwMjAxMTIucGRm"
    },
    {
        "volume": "1995Volume 1",
        "Case Name": "STATE OF BIHAR AND ORS. VS. SACHCHLDANAND KISHORE PRASAD SINHA AND ORS.",
        "Case Link": "https://digiscr.sci.gov.in/view_judgment?id=MjAxMjg=",
        "Citation": "[1995] 1 S.C.R. 256",
        "Case Type": "(CIVIL APPEAL /772/1995)",
        "Date": "16 JANUARY 1995",
        "Judge Names": "Hon'ble Mr. Justice B.P. Jeevan Reddy\n*, Hon'ble Ms. Justice Sujata V Manohar",
        "PDF Link": "https://digiscr.sci.gov.in/pdf_viewer?dir=YWRtaW4vanVkZ2VtZW50X2ZpbGUvanVkZ2VtZW50X3BkZi8xOTk1L3ZvbHVtZSAxL1BhcnQgSS8xOTk1XzFfMjU2XzE3MDIwMjAyMzQucGRm"
    },
    {
        "volume": "1995Volume 1",
        "Case Name": "T. SHANTHARAM VS. STATE OF KARNATAKA AND ORS.",
        "Case Link": "https://digiscr.sci.gov.in/view_judgment?id=MjAxMzk=",
        "Citation": "[1995] 1 S.C.R. 274",
        "Case Type": "(CIVIL APPEAL /922/1955)",
        "Date": "16 JANUARY 1995",
        "Judge Names": "Hon'ble Mr. Justice K. Ramaswamy, Hon'ble Mr. Justice S.C. Sen",
        "PDF Link": "https://digiscr.sci.gov.in/pdf_viewer?dir=YWRtaW4vanVkZ2VtZW50X2ZpbGUvanVkZ2VtZW50X3BkZi8xOTk1L3ZvbHVtZSAxL1BhcnQgSS8xOTk1XzFfMjc0XzE3MDIwMjAzNDAucGRm"
    },
    {
        "volume": "1995Volume 1",
        "Case Name": "E.K. CHANDRASENAN ETC. ETC. VS. STATE OF KERALA",
        "Case Link": "https://digiscr.sci.gov.in/view_judgment?id=MjAxNTI=",
        "Citation": "[1995] 1 S.C.R. 277",
        "Case Type": "(CRIMINAL APPEAL /422/1990)",
        "Date": "17 JANUARY 1995",
        "Judge Names": "Hon'ble Mr. Justice Kuldip Singh, Hon'ble Mr. Justice B.L. Hansaria\n*",
        "PDF Link": "https://digiscr.sci.gov.in/pdf_viewer?dir=YWRtaW4vanVkZ2VtZW50X2ZpbGUvanVkZ2VtZW50X3BkZi8xOTk1L3ZvbHVtZSAxL1BhcnQgSS8xOTk1XzFfMjc3XzE3MDIwMjA0NTIucGRm"
    },
    {
        "volume": "1995Volume 1",
        "Case Name": "INDIAN COUNCIL OF LEGAL AID AND ADVICE, ETC. ETC. VS. BAR COUNCIL OF INDIA AND ANR.",
        "Case Link": "https://digiscr.sci.gov.in/view_judgment?id=MjAxNzM=",
        "Citation": "[1995] 1 S.C.R. 304",
        "Case Type": "(WRIT PETITION (CIVIL) /786/1993)",
        "Date": "17 JANUARY 1995",
        "Judge Names": "Hon'ble Mr. Justice A.M. Ahmadi\n*, Hon'ble Mr. Justice S. Mohan, Hon'ble Mr. Justice K.S. Paripoornan",
        "PDF Link": "https://digiscr.sci.gov.in/pdf_viewer?dir=YWRtaW4vanVkZ2VtZW50X2ZpbGUvanVkZ2VtZW50X3BkZi8xOTk1L3ZvbHVtZSAxL1BhcnQgSS8xOTk1XzFfMzA0XzE3MDIwMjA2MzcucGRm"
    },
    {
        "volume": "1995Volume 1",
        "Case Name": "RAMDEO BHANDARI AND ORS. ETC. ETC. VS. ELECTION COMMISSION OF INDIA AND ORS. ETC. ETC.",
        "Case Link": "https://digiscr.sci.gov.in/view_judgment?id=MjAxOTI=",
        "Citation": "[1995] 1 S.C.R. 321",
        "Case Type": "(WRIT PETITION (CIVIL) /2/1995)",
        "Date": "17 JANUARY 1995",
        "Judge Names": "Hon'ble Mr. Justice A.M. Ahmadi, Hon'ble Mr. Justice S.P. Bharucha, Hon'ble Mr. Justice K. Jayachandra Reddy",
        "PDF Link": "https://digiscr.sci.gov.in/pdf_viewer?dir=YWRtaW4vanVkZ2VtZW50X2ZpbGUvanVkZ2VtZW50X3BkZi8xOTk1L3ZvbHVtZSAxL1BhcnQgSS8xOTk1XzFfMzIxXzE3MDIwMjA3ODcucGRm"
    },
    {
        "volume": "1995Volume 1",
        "Case Name": "COCHIN DEVASWAM BOARD VS. CAPTAIN E.M. GEORGE AND ORS.",
        "Case Link": "https://digiscr.sci.gov.in/view_judgment?id=MjA0NTY=",
        "Citation": "[1995] 1 S.C.R. 328",
        "Case Type": "(CIVIL APPEAL /2312/1977)",
        "Date": "17 JANUARY 1995",
        "Judge Names": "Hon'ble Mr. Justice J.S. Verma, Hon'ble Mr. Justice K.S. Paripoornan\n*, Hon'ble Mr. Justice S.P. Bharucha",
        "PDF Link": "https://digiscr.sci.gov.in/pdf_viewer?dir=YWRtaW4vanVkZ2VtZW50X2ZpbGUvanVkZ2VtZW50X3BkZi8xOTk1L3ZvbHVtZSAxL1BhcnQgSS8xOTk1XzFfMzI4XzE3MDIwMjQ1NzAucGRm"
    },
    {
        "volume": "1995Volume 1",
        "Case Name": "NIKKI VS. UNION OF INDIA AND ANR.",
        "Case Link": "https://digiscr.sci.gov.in/view_judgment?id=MjA0NjY=",
        "Citation": "[1995] 1 S.C.R. 341",
        "Case Type": "(CIVIL APPEAL /998/1990)",
        "Date": "17 JANUARY 1995",
        "Judge Names": "Hon'ble Mr. Justice K. Ramaswamy, Hon'ble Ms. Justice Sujata V Manohar",
        "PDF Link": "https://digiscr.sci.gov.in/pdf_viewer?dir=YWRtaW4vanVkZ2VtZW50X2ZpbGUvanVkZ2VtZW50X3BkZi8xOTk1L3ZvbHVtZSAxL1BhcnQgSS8xOTk1XzFfMzQxXzE3MDIwMjQ2NjUucGRm"
    },
    {
        "volume": "1995Volume 1",
        "Case Name": "SANT SARAN GOSWAMI @ DEOJI VS. THE STATE OF BIHAR AND ORS.",
        "Case Link": "https://digiscr.sci.gov.in/view_judgment?id=MjA0Nzc=",
        "Citation": "[1995] 1 S.C.R. 344",
        "Case Type": "(CIVIL APPEAL /1216/1992)",
        "Date": "17 JANUARY 1995",
        "Judge Names": "Hon'ble Mr. Justice K. Ramaswamy, Hon'ble Ms. Justice Sujata V Manohar",
        "PDF Link": "https://digiscr.sci.gov.in/pdf_viewer?dir=YWRtaW4vanVkZ2VtZW50X2ZpbGUvanVkZ2VtZW50X3BkZi8xOTk1L3ZvbHVtZSAxL1BhcnQgSS8xOTk1XzFfMzQ0XzE3MDIwMjQ3NzAucGRm"
    },
    {
        "volume": "1995Volume 1",
        "Case Name": "UMED INDUSTRIES AND LAND DEVELOPMENT CO. AND ORS. VS. STATE OF RAJASTHAN AND ORS.",
        "Case Link": "https://digiscr.sci.gov.in/view_judgment?id=MjA1MDU=",
        "Citation": "[1995] 1 S.C.R. 348",
        "Case Type": "(CIVIL APPEAL /1299/1988)",
        "Date": "17 JANUARY 1995",
        "Judge Names": "Hon'ble Mr. Justice K. Ramaswamy, Hon'ble Ms. Justice Sujata V Manohar",
        "PDF Link": "https://digiscr.sci.gov.in/pdf_viewer?dir=YWRtaW4vanVkZ2VtZW50X2ZpbGUvanVkZ2VtZW50X3BkZi8xOTk1L3ZvbHVtZSAxL1BhcnQgSS8xOTk1XzFfMzQ4XzE3MDIwMjQ5ODYucGRm"
    },
    {
        "volume": "1995Volume 1",
        "Case Name": "UNION OF INDIA VS. SH. SHIVKUMAR BHARGAVA AND ORS.",
        "Case Link": "https://digiscr.sci.gov.in/view_judgment?id=MjA1MjA=",
        "Citation": "[1995] 1 S.C.R. 354",
        "Case Type": "(CIVIL APPEAL /1711/1993)",
        "Date": "17 JANUARY 1995",
        "Judge Names": "Hon'ble Mr. Justice K. Ramaswamy, Hon'ble Ms. Justice Sujata V Manohar",
        "PDF Link": "https://digiscr.sci.gov.in/pdf_viewer?dir=YWRtaW4vanVkZ2VtZW50X2ZpbGUvanVkZ2VtZW50X3BkZi8xOTk1L3ZvbHVtZSAxL1BhcnQgSS8xOTk1XzFfMzU0XzE3MDIwMjUwOTAucGRm"
    },
    {
        "volume": "1995Volume 1",
        "Case Name": "STATE OF KERALA AND ANR. VS. BETTY W/O L.J. MANI AND ANR.",
        "Case Link": "https://digiscr.sci.gov.in/view_judgment?id=MjA1MzM=",
        "Citation": "[1995] 1 S.C.R. 357",
        "Case Type": "(CIVIL APPEAL /1421-22/1991)",
        "Date": "17 JANUARY 1995",
        "Judge Names": "Hon'ble Mr. Justice K. Ramaswamy, Hon'ble Ms. Justice Sujata V Manohar",
        "PDF Link": "https://digiscr.sci.gov.in/pdf_viewer?dir=YWRtaW4vanVkZ2VtZW50X2ZpbGUvanVkZ2VtZW50X3BkZi8xOTk1L3ZvbHVtZSAxL1BhcnQgSS8xOTk1XzFfMzU3XzE3MDIwMjUyMDYucGRm"
    },
    {
        "volume": "1995Volume 1",
        "Case Name": "CHIEF GENERAL MANAGER (TELECOM) N.E. TELECOM CIRCLE AND ANR. VS. SH. RAJENDRA CH. BHATTACHARJEE AND ORS.",
        "Case Link": "https://digiscr.sci.gov.in/view_judgment?id=MjA1NDg=",
        "Citation": "[1995] 1 S.C.R. 360",
        "Case Type": "(CIVIL APPEAL /834/1995)",
        "Date": "18 JANUARY 1995",
        "Judge Names": "Hon'ble Mr. Justice S.C. Agrawal, Hon'ble Mr. Justice Faizanuddin\n*",
        "PDF Link": "https://digiscr.sci.gov.in/pdf_viewer?dir=YWRtaW4vanVkZ2VtZW50X2ZpbGUvanVkZ2VtZW50X3BkZi8xOTk1L3ZvbHVtZSAxL1BhcnQgSS8xOTk1XzFfMzYwXzE3MDIwMjUzMjUucGRm"
    },
    {
        "volume": "1995Volume 1",
        "Case Name": "U. P. STATE TOURISM DEVELOPMENT CORPORATION LTD. VS. I.B. MISRA AND ORS.",
        "Case Link": "https://digiscr.sci.gov.in/view_judgment?id=MjA1NjM=",
        "Citation": "[1995] 1 S.C.R. 368",
        "Case Type": "(CIVIL APPEAL /818-19/1995)",
        "Date": "18 JANUARY 1995",
        "Judge Names": "Hon'ble Mr. Justice S.C. Agrawal\n*, Hon'ble Mr. Justice G.N. Ray",
        "PDF Link": "https://digiscr.sci.gov.in/pdf_viewer?dir=YWRtaW4vanVkZ2VtZW50X2ZpbGUvanVkZ2VtZW50X3BkZi8xOTk1L3ZvbHVtZSAxL1BhcnQgSS8xOTk1XzFfMzY4XzE3MDIwMjU0NzgucGRm"
    },
    {
        "volume": "1995Volume 1",
        "Case Name": "SOCIEDADE DE FORMENTO INDUSTRIAL PVT. LTD. AND ORS. VS. MORMUGAO DOCK LABOUR BOARD AND ANR.",
        "Case Link": "https://digiscr.sci.gov.in/view_judgment?id=MjA1NzU=",
        "Citation": "[1995] 1 S.C.R. 377",
        "Case Type": "(CIVIL APPEAL /258/1985)",
        "Date": "18 JANUARY 1995",
        "Judge Names": "Hon'ble Mr. Justice P.B. Sawant, Hon'ble Mr. Justice S.C. Agrawal\n*",
        "PDF Link": "https://digiscr.sci.gov.in/pdf_viewer?dir=YWRtaW4vanVkZ2VtZW50X2ZpbGUvanVkZ2VtZW50X3BkZi8xOTk1L3ZvbHVtZSAxL1BhcnQgSS8xOTk1XzFfMzc3XzE3MDIwMjU1OTIucGRm"
    },
    {
        "volume": "1995Volume 1",
        "Case Name": "STATE OF MADHYA PRADESH VS. SURENDRA KUMAR AND ANR.",
        "Case Link": "https://digiscr.sci.gov.in/view_judgment?id=MjA1ODY=",
        "Citation": "[1995] 1 S.C.R. 396",
        "Case Type": "(CIVIL APPEAL /4452/1984)",
        "Date": "18 JANUARY 1995",
        "Judge Names": "Hon'ble Mr. Justice K. Ramaswamy, Hon'ble Mr. Justice N. Venkatachala",
        "PDF Link": "https://digiscr.sci.gov.in/pdf_viewer?dir=YWRtaW4vanVkZ2VtZW50X2ZpbGUvanVkZ2VtZW50X3BkZi8xOTk1L3ZvbHVtZSAxL1BhcnQgSS8xOTk1XzFfMzk2XzE3MDIwMjU2OTUucGRm"
    },
    {
        "volume": "1995Volume 1",
        "Case Name": "MIRZA MAJID HUSSAIN VS. STATE OF M.P. AND ANR .",
        "Case Link": "https://digiscr.sci.gov.in/view_judgment?id=MjA1OTc=",
        "Citation": "[1995] 1 S.C.R. 401",
        "Case Type": "(CIVIL APPEAL /72/1992)",
        "Date": "18 JANUARY 1995",
        "Judge Names": "Hon'ble Mr. Justice K. Ramaswamy, Hon'ble Mr. Justice N. Venkatachala",
        "PDF Link": "https://digiscr.sci.gov.in/pdf_viewer?dir=YWRtaW4vanVkZ2VtZW50X2ZpbGUvanVkZ2VtZW50X3BkZi8xOTk1L3ZvbHVtZSAxL1BhcnQgSS8yMDA3XzFfNDAxLTQwM18xNzA0MzY0NjMzLnBkZg=="
    },
    {
        "volume": "1995Volume 1",
        "Case Name": "KHANNA IMPROVEMENT TRUST VS. LAND ACQUISITION TRIBUNAL AND ORS.",
        "Case Link": "https://digiscr.sci.gov.in/view_judgment?id=MjA2MDk=",
        "Citation": "[1995] 1 S.C.R. 404",
        "Case Type": "(CIVIL APPEAL /3867/1990)",
        "Date": "18 JANUARY 1995",
        "Judge Names": "Hon'ble Mr. Justice K. Ramaswamy",
        "PDF Link": "https://digiscr.sci.gov.in/pdf_viewer?dir=YWRtaW4vanVkZ2VtZW50X2ZpbGUvanVkZ2VtZW50X3BkZi8xOTk1L3ZvbHVtZSAxL1BhcnQgSS8xOTk1XzFfNDA0XzE3MDIwMjU4OTQucGRm"
    },
    {
        "volume": "1995Volume 1",
        "Case Name": "STATE OF HARYANA VS. GURCHARAN SINGH AND ANR. ETC.",
        "Case Link": "https://digiscr.sci.gov.in/view_judgment?id=MjA2MjQ=",
        "Citation": "[1995] 1 S.C.R. 408",
        "Case Type": "(CIVIL APPEAL /4974-76/1985)",
        "Date": "18 JANUARY 1995",
        "Judge Names": "Hon'ble Mr. Justice K. Ramaswamy, Hon'ble Mr. Justice N. Venkatachala",
        "PDF Link": "https://digiscr.sci.gov.in/pdf_viewer?dir=YWRtaW4vanVkZ2VtZW50X2ZpbGUvanVkZ2VtZW50X3BkZi8xOTk1L3ZvbHVtZSAxL1BhcnQgSS8xOTk1XzFfNDA4XzE3MDIwMjYwOTMucGRm"
    },
    {
        "volume": "1995Volume 1",
        "Case Name": "GIAN CHAND VS. GOPALA AND ORS.",
        "Case Link": "https://digiscr.sci.gov.in/view_judgment?id=MjA2Mzc=",
        "Citation": "[1995] 1 S.C.R. 412",
        "Case Type": "(CIVIL APPEAL /4710/1992)",
        "Date": "18 JANUARY 1995",
        "Judge Names": "Hon'ble Mr. Justice K. Ramaswamy, Hon'ble Mr. Justice N. Venkatachala",
        "PDF Link": "https://digiscr.sci.gov.in/pdf_viewer?dir=YWRtaW4vanVkZ2VtZW50X2ZpbGUvanVkZ2VtZW50X3BkZi8xOTk1L3ZvbHVtZSAxL1BhcnQgSS8xOTk1XzFfNDEyXzE3MDIwMjYyMTIucGRm"
    },
    {
        "volume": "1995Volume 1",
        "Case Name": "STATE OF MADHYA PRADESH VS. SMT. SHANTABHAI AND ORS.",
        "Case Link": "https://digiscr.sci.gov.in/view_judgment?id=MjA2NjI=",
        "Citation": "[1995] 1 S.C.R. 416",
        "Case Type": "(CIVIL APPEAL /2944/1984)",
        "Date": "18 JANUARY 1995",
        "Judge Names": "Hon'ble Mr. Justice K. Ramaswamy, Hon'ble Mr. Justice N. Venkatachala",
        "PDF Link": "https://digiscr.sci.gov.in/pdf_viewer?dir=YWRtaW4vanVkZ2VtZW50X2ZpbGUvanVkZ2VtZW50X3BkZi8xOTk1L3ZvbHVtZSAxL1BhcnQgSS8xOTk1XzFfNDE2XzE3MDIwMjY0NjIucGRm"
    },
    {
        "volume": "1995Volume 1",
        "Case Name": "STATE OF TAMIL NADU VS. M.P.P. KAVERY CHETTY",
        "Case Link": "https://digiscr.sci.gov.in/view_judgment?id=MjA3Mjg=",
        "Citation": "[1995] 1 S.C.R. 441",
        "Case Type": "(CIVIL APPEAL /1655/1993)",
        "Date": "19 JANUARY 1995",
        "Judge Names": "Hon'ble Mr. Justice J.S. Verma, Hon'ble Mr. Justice K.S. Paripoornan, Hon'ble Mr. Justice S.P. Bharucha\n*",
        "PDF Link": "https://digiscr.sci.gov.in/pdf_viewer?dir=YWRtaW4vanVkZ2VtZW50X2ZpbGUvanVkZ2VtZW50X3BkZi8xOTk1L3ZvbHVtZSAxL1BhcnQgSS8xOTk1XzFfNDQxLTQ1NV8xNzAyMDI3MjcxLnBkZg=="
    },
    {
        "volume": "1995Volume 1",
        "Case Name": "RAMA NARANG VS. RAMESH NARANG AND ORS.",
        "Case Link": "https://digiscr.sci.gov.in/view_judgment?id=MjA3NDA=",
        "Citation": "[1995] 1 S.C.R. 456",
        "Case Type": "(CIVIL APPEAL /5620/1994)",
        "Date": "19 JANUARY 1995",
        "Judge Names": "Hon'ble Mr. Justice A.M. Ahmadi\n*, Hon'ble Mr. Justice K. Jayachandra Reddy, Hon'ble Mr. Justice R.M. Sahai",
        "PDF Link": "https://digiscr.sci.gov.in/pdf_viewer?dir=YWRtaW4vanVkZ2VtZW50X2ZpbGUvanVkZ2VtZW50X3BkZi8xOTk1L3ZvbHVtZSAxL1BhcnQgSS8xOTk1XzFfNDU2LTQ3NV8xNzAyMDI3NDk0LnBkZg=="
    },
    {
        "volume": "1995Volume 1",
        "Case Name": "GEM GRANITES AND ANR. VS. STATE OF TAMIL NADU AND ORS.",
        "Case Link": "https://digiscr.sci.gov.in/view_judgment?id=MjA3NDk=",
        "Citation": "[1995] 1 S.C.R. 476",
        "Case Type": "(WRIT PETITION (CIVIL) /819/1992)",
        "Date": "19 JANUARY 1995",
        "Judge Names": "Hon'ble Mr. Justice J.S. Verma, Hon'ble Mr. Justice S.P. Bharucha\n*, Hon'ble Mr. Justice K.S. Paripoornan",
        "PDF Link": "https://digiscr.sci.gov.in/pdf_viewer?dir=YWRtaW4vanVkZ2VtZW50X2ZpbGUvanVkZ2VtZW50X3BkZi8xOTk1L3ZvbHVtZSAxL1BhcnQgSS8xOTk1XzFfNDc2LTQ4MV8xNzAyMDI3NjMxLnBkZg=="
    },
    {
        "volume": "1995Volume 1",
        "Case Name": "STATE OF MADHYA PRADESH AND ANR. VS. SRI S.S. KOURAV AND ORS.",
        "Case Link": "https://digiscr.sci.gov.in/view_judgment?id=MjA3NTQ=",
        "Citation": "[1995] 1 S.C.R. 482",
        "Case Type": "(CIVIL APPEAL /1285/1995)",
        "Date": "19 JANUARY 1995",
        "Judge Names": "Hon'ble Mr. Justice K. Ramaswamy, Hon'ble Mr. Justice K. Venkataswami",
        "PDF Link": "https://digiscr.sci.gov.in/pdf_viewer?dir=YWRtaW4vanVkZ2VtZW50X2ZpbGUvanVkZ2VtZW50X3BkZi8xOTk1L3ZvbHVtZSAxL1BhcnQgSS8xOTk1XzFfNDgyLTQ4NV8xNzAyMDI3NzQyLnBkZg=="
    },
    {
        "volume": "1995Volume 1",
        "Case Name": "SHRI BHAGWAN SINGH VS. THE CHAIRMAN, NOIDA AND ORS.",
        "Case Link": "https://digiscr.sci.gov.in/view_judgment?id=MjA3NjI=",
        "Citation": "[1995] 1 S.C.R. 486",
        "Case Type": "(WRIT PETITION (CIVIL) /674/1992)",
        "Date": "19 JANUARY 1995",
        "Judge Names": "Hon'ble Mr. Justice K. Ramaswamy, Hon'ble Mr. Justice N. Venkatachala",
        "PDF Link": "https://digiscr.sci.gov.in/pdf_viewer?dir=YWRtaW4vanVkZ2VtZW50X2ZpbGUvanVkZ2VtZW50X3BkZi8xOTk1L3ZvbHVtZSAxL1BhcnQgSS8xOTk1XzFfNDg2LTQ4N18xNzAyMDI3OTE5LnBkZg=="
    },
    {
        "volume": "1995Volume 1",
        "Case Name": "D. KRISHNA VENI AND ANR. ETC. VS. STATE OF ORISSA AND ORS.",
        "Case Link": "https://digiscr.sci.gov.in/view_judgment?id=MjA3Njc=",
        "Citation": "[1995] 1 S.C.R. 488",
        "Case Type": "(CIVIL APPEAL /1696/1995)",
        "Date": "19 JANUARY 1995",
        "Judge Names": "Hon'ble Mr. Justice K. Ramaswamy, Hon'ble Mr. Justice N. Venkatachala",
        "PDF Link": "https://digiscr.sci.gov.in/pdf_viewer?dir=YWRtaW4vanVkZ2VtZW50X2ZpbGUvanVkZ2VtZW50X3BkZi8xOTk1L3ZvbHVtZSAxL1BhcnQgSS8xOTk1XzFfNDg4LTQ5MF8xNzAyMDI4MDE0LnBkZg=="
    },
    {
        "volume": "1995Volume 1",
        "Case Name": "MRS. MARY JOYCE POONACHA VS. MIS K.T. PLANTATIONS PVT. LTD.",
        "Case Link": "https://digiscr.sci.gov.in/view_judgment?id=MjA3NzE=",
        "Citation": "[1995] 1 S.C.R. 491",
        "Case Type": "(CIVIL APPEAL /3094/1995)",
        "Date": "19 JANUARY 1995",
        "Judge Names": "Hon'ble Mr. Justice K. Ramaswamy, Hon'ble Mr. Justice N. Venkatachala",
        "PDF Link": "https://digiscr.sci.gov.in/pdf_viewer?dir=YWRtaW4vanVkZ2VtZW50X2ZpbGUvanVkZ2VtZW50X3BkZi8xOTk1L3ZvbHVtZSAxL1BhcnQgSS8xOTk1XzFfNDkxLTQ5NV8xNzAyMDI4MTE1LnBkZg=="
    },
    {
        "volume": "1995Volume 1",
        "Case Name": "STATE OF PUNJAB VS. AJAIB SINGH",
        "Case Link": "https://digiscr.sci.gov.in/view_judgment?id=MTk2NjE=",
        "Citation": "[1995] 1 S.C.R. 496",
        "Case Type": "(CRIMINAL APPEAL /754/1980)",
        "Date": "20 JANUARY 1995",
        "Judge Names": "Hon'ble Mr. Justice P.B. Sawant, Hon'ble Mr. Justice R.M. Sahai\n*",
        "PDF Link": "https://digiscr.sci.gov.in/pdf_viewer?dir=YWRtaW4vanVkZ2VtZW50X2ZpbGUvanVkZ2VtZW50X3BkZi8xOTk1L3ZvbHVtZSAxL1BhcnQgSS8xOTk1XzFfNDk2XzE3MDIwMTY1NTAucGRm"
    },
    {
        "volume": "1995Volume 1",
        "Case Name": "M/S NEW INDIA ASSURANCE CO. LTD. VS. UNION OF INDIA AND ORS.",
        "Case Link": "https://digiscr.sci.gov.in/view_judgment?id=MTk2NDc=",
        "Citation": "[1995] 1 S.C.R. 507",
        "Case Type": "(CIVIL APPEAL /5060/1994)",
        "Date": "20 JANUARY 1995",
        "Judge Names": "Hon'ble Mr. Justice J.S. Verma\n*, Hon'ble Mr. Justice K.S. Paripoornan, Hon'ble Mr. Justice S.P. Bharucha",
        "PDF Link": "https://digiscr.sci.gov.in/pdf_viewer?dir=YWRtaW4vanVkZ2VtZW50X2ZpbGUvanVkZ2VtZW50X3BkZi8xOTk1L3ZvbHVtZSAxL1BhcnQgSS8xOTk1XzFfNTA3XzE3MDIwMTY0MjgucGRm"
    },
    {
        "volume": "1995Volume 1",
        "Case Name": "DURGA NARAYAN VS. CHAIRMAN AND MANAGING DIRECTOR, DENA BANK",
        "Case Link": "https://digiscr.sci.gov.in/view_judgment?id=MTk2MjY=",
        "Citation": "[1995] 1 S.C.R. 513",
        "Case Type": "(CIVIL APPEAL /870/1995)",
        "Date": "20 JANUARY 1995",
        "Judge Names": "Hon'ble Mr. Justice A.M. Ahmadi, Hon'ble Mr. Justice B.L. Hansaria\n*, Hon'ble Mr. Justice S.C. Sen",
        "PDF Link": "https://digiscr.sci.gov.in/pdf_viewer?dir=YWRtaW4vanVkZ2VtZW50X2ZpbGUvanVkZ2VtZW50X3BkZi8xOTk1L3ZvbHVtZSAxL1BhcnQgSS8xOTk1XzFfNTEzXzE3MDIwMTYzMTEucGRm"
    },
    {
        "volume": "1995Volume 1",
        "Case Name": "MIS HIND WIRE INDUSTRIES LTD. VS. THE COMMISSIONER OF INCOME TAX, WEST BENGAL-V",
        "Case Link": "https://digiscr.sci.gov.in/view_judgment?id=MTk2MTI=",
        "Citation": "[1995] 1 S.C.R. 519",
        "Case Type": "(CIVIL APPEAL /1323-27/1995)",
        "Date": "20 JANUARY 1995",
        "Judge Names": "Hon'ble Mr. Justice P.B. Sawant, Hon'ble Mr. Justice G.N. Ray",
        "PDF Link": "https://digiscr.sci.gov.in/pdf_viewer?dir=YWRtaW4vanVkZ2VtZW50X2ZpbGUvanVkZ2VtZW50X3BkZi8xOTk1L3ZvbHVtZSAxL1BhcnQgSS8xOTk1XzFfNTE5XzE3MDIwMTYxOTgucGRm"
    },
    {
        "volume": "1995Volume 1",
        "Case Name": "STATE OF ANDHRA PRADESH VS. SHRI S. VISHWANATHA RAJU ETC. ETC.",
        "Case Link": "https://digiscr.sci.gov.in/view_judgment?id=MTk1OTY=",
        "Citation": "[1995] 1 S.C.R. 529",
        "Case Type": "(CIVIL APPEAL /2943-50/1995)",
        "Date": "20 JANUARY 1995",
        "Judge Names": "Hon'ble Mr. Justice K. Ramaswamy, Hon'ble Mr. Justice N. Venkatachala",
        "PDF Link": "https://digiscr.sci.gov.in/pdf_viewer?dir=YWRtaW4vanVkZ2VtZW50X2ZpbGUvanVkZ2VtZW50X3BkZi8xOTk1L3ZvbHVtZSAxL1BhcnQgSS8xOTk1XzFfNTI5XzE3MDIwMTYwOTkucGRm"
    },
    {
        "volume": "1995Volume 1",
        "Case Name": "SURBUDDIN AND ANR. VS. STATE OF KERALA AND ANR.",
        "Case Link": "https://digiscr.sci.gov.in/view_judgment?id=MTk1Nzk=",
        "Citation": "[1995] 1 S.C.R. 533",
        "Case Type": "(CIVIL APPEAL /1017/1995)",
        "Date": "23 JANUARY 1995",
        "Judge Names": "Hon'ble Mr. Justice K. Ramaswamy, Hon'ble Mr. Justice B.L. Hansaria",
        "PDF Link": "https://digiscr.sci.gov.in/pdf_viewer?dir=YWRtaW4vanVkZ2VtZW50X2ZpbGUvanVkZ2VtZW50X3BkZi8xOTk1L3ZvbHVtZSAxL1BhcnQgSS8xOTk1XzFfNTMzXzE3MDIwMTU5NzUucGRm"
    },
    {
        "volume": "1995Volume 1",
        "Case Name": "MAJOR PAKHAR SINGH ATWAL AND ORS. VS. STATE OF PUNJAB AND ORS.",
        "Case Link": "https://digiscr.sci.gov.in/view_judgment?id=MTk1Njg=",
        "Citation": "[1995] 1 S.C.R. 535",
        "Case Type": "(CIVIL APPEAL /874/1986)",
        "Date": "24 JANUARY 1995",
        "Judge Names": "Hon'ble Mr. Justice K. Ramaswamy, Hon'ble Mr. Justice N. Venkatachala",
        "PDF Link": "https://digiscr.sci.gov.in/pdf_viewer?dir=YWRtaW4vanVkZ2VtZW50X2ZpbGUvanVkZ2VtZW50X3BkZi8xOTk1L3ZvbHVtZSAxL1BhcnQgSS8xOTk1XzFfNTM1XzE3MDIwMTU4NTkucGRm"
    },
    {
        "volume": "1995Volume 1",
        "Case Name": "MAHADEO SAVLARAM SHELKE AND ORS. VS. PUNA MUNICIPAL CORPORATION AND ANR.",
        "Case Link": "https://digiscr.sci.gov.in/view_judgment?id=MTk1NTU=",
        "Citation": "[1995] 1 S.C.R. 543",
        "Case Type": "(CIVIL APPEAL /1109/1979)",
        "Date": "24 JANUARY 1995",
        "Judge Names": "Hon'ble Mr. Justice K. Ramaswamy, Hon'ble Mr. Justice N. Venkatachala",
        "PDF Link": "https://digiscr.sci.gov.in/pdf_viewer?dir=YWRtaW4vanVkZ2VtZW50X2ZpbGUvanVkZ2VtZW50X3BkZi8xOTk1L3ZvbHVtZSAxL1BhcnQgSS8xOTk1XzFfNTQzXzE3MDIwMTU3NDkucGRm"
    },
    {
        "volume": "1995Volume 1",
        "Case Name": "DELHI DEVELOPMENT AUTHORITY VS. SKIPPER CONSTRUCTION AND ANR.",
        "Case Link": "https://digiscr.sci.gov.in/view_judgment?id=MTk1Mzk=",
        "Citation": "[1995] 1 S.C.R. 555",
        "Case Type": "(SPECIAL LEAVE PETITION (CIVIL) /21000/1993)",
        "Date": "25 JANUARY 1995",
        "Judge Names": "Hon'ble Mr. Justice P.B. Sawant, Hon'ble Mr. Justice S. Mohan, Hon'ble Mr. Justice B.P. Jeevan Reddy",
        "PDF Link": "https://digiscr.sci.gov.in/pdf_viewer?dir=YWRtaW4vanVkZ2VtZW50X2ZpbGUvanVkZ2VtZW50X3BkZi8xOTk1L3ZvbHVtZSAxL1BhcnQgSS8xOTk1XzFfNTU1XzE3MDIwMTU2MzEucGRm"
    },
    {
        "volume": "1995Volume 1",
        "Case Name": "P. RAM REDDY ETC. VS. LAND ACQUISITION OFFICER, HYDERABAD URBAN DEVELOPMENT AUTHORITY, HYDERABAD ETC.",
        "Case Link": "https://digiscr.sci.gov.in/view_judgment?id=MTk1MjQ=",
        "Citation": "[1995] 1 S.C.R. 584",
        "Case Type": "(CIVIL APPEAL /1037-38/1995)",
        "Date": "27 JANUARY 1995",
        "Judge Names": "Hon'ble Mr. Justice K. Ramaswamy, Hon'ble Mr. Justice N. Venkatachala\n*",
        "PDF Link": "https://digiscr.sci.gov.in/pdf_viewer?dir=YWRtaW4vanVkZ2VtZW50X2ZpbGUvanVkZ2VtZW50X3BkZi8xOTk1L3ZvbHVtZSAxL1BhcnQgSS8xOTk1XzFfNTg0XzE3MDIwMTU1MDkucGRm"
    },
    {
        "volume": "1995Volume 1",
        "Case Name": "STATE OF ORISSA AND ORS. VS. ADWAIT CHARAN MOHANTY ETC. ETC.",
        "Case Link": "https://digiscr.sci.gov.in/view_judgment?id=MTk1MTE=",
        "Citation": "[1995] 1 S.C.R. 614",
        "Case Type": "(CIVIL APPEAL /1497/1993)",
        "Date": "27 JANUARY 1995",
        "Judge Names": "Hon'ble Mr. Justice K. Ramaswamy\n*, Hon'ble Mr. Justice K. Venkataswami",
        "PDF Link": "https://digiscr.sci.gov.in/pdf_viewer?dir=YWRtaW4vanVkZ2VtZW50X2ZpbGUvanVkZ2VtZW50X3BkZi8xOTk1L3ZvbHVtZSAxL1BhcnQgSS8xOTk1XzFfNjE0XzE3MDIwMTUzODcucGRm"
    },
    {
        "volume": "1995Volume 1",
        "Case Name": "CONSUMER EDUCATION AND RESEARCH CENTRE AND ORS. VS. UNION OF INDIA AND ORS.",
        "Case Link": "https://digiscr.sci.gov.in/view_judgment?id=MTk0NzQ=",
        "Citation": "[1995] 1 S.C.R. 626",
        "Case Type": "(WRIT PETITION (CIVIL) /206/1986)",
        "Date": "27 JANUARY 1995",
        "Judge Names": "Hon'ble Mr. Justice A.M. Ahmadi, Hon'ble Mr. Justice M.M. Punchhi, Hon'ble Mr. Justice K. Ramaswamy\n*",
        "PDF Link": "https://digiscr.sci.gov.in/pdf_viewer?dir=YWRtaW4vanVkZ2VtZW50X2ZpbGUvanVkZ2VtZW50X3BkZi8xOTk1L3ZvbHVtZSAxL1BhcnQgSS8xOTk1XzFfNjI2XzE3MDIwMTUwOTIucGRm"
    },
    {
        "volume": "1995Volume 1",
        "Case Name": "UNION OF INDIA AND ORS. VS. B. RAMA MURTHY",
        "Case Link": "https://digiscr.sci.gov.in/view_judgment?id=MTk0NTc=",
        "Citation": "[1995] 1 S.C.R. 665",
        "Case Type": "(CIVIL APPEAL /2986/1995)",
        "Date": "27 JANUARY 1995",
        "Judge Names": "Hon'ble Mr. Justice K. Ramaswamy, Hon'ble Mr. Justice B.L. Hansaria",
        "PDF Link": "https://digiscr.sci.gov.in/pdf_viewer?dir=YWRtaW4vanVkZ2VtZW50X2ZpbGUvanVkZ2VtZW50X3BkZi8xOTk1L3ZvbHVtZSAxL1BhcnQgSS8xOTk1XzFfNjY1XzE3MDIwMTQ5NzYucGRm"
    },
    {
        "volume": "1995Volume 1",
        "Case Name": "ARUNABEN T. BHOJAK VS. SECRETARY, AHMEDABAD EDUCATION SOCIETY AND ORS.",
        "Case Link": "https://digiscr.sci.gov.in/view_judgment?id=MTk0Mzk=",
        "Citation": "[1995] 1 S.C.R. 668",
        "Case Type": "(CIVIL APPEAL /3010/1995)",
        "Date": "28 JANUARY 1995",
        "Judge Names": "Hon'ble Mr. Justice K. Ramaswamy, Hon'ble Mr. Justice B.L. Hansaria",
        "PDF Link": "https://digiscr.sci.gov.in/pdf_viewer?dir=YWRtaW4vanVkZ2VtZW50X2ZpbGUvanVkZ2VtZW50X3BkZi8xOTk1L3ZvbHVtZSAxL1BhcnQgSS8xOTk1XzFfNjY4XzE3MDIwMTQ4NTAucGRm"
    },
    {
        "volume": "1995Volume 1",
        "Case Name": "UNION OF INDIA VS. SMT. PRATAP KAUR (DEAD) THROUGH LRS. AND ANR. ETC.",
        "Case Link": "https://digiscr.sci.gov.in/view_judgment?id=MjA3Nzk=",
        "Citation": "[1995] 1 S.C.R. 670",
        "Case Type": "(CIVIL APPEAL /3179-81/1995)",
        "Date": "27 JANUARY 1995",
        "Judge Names": "Hon'ble Mr. Justice K. Ramaswamy, Hon'ble Mr. Justice B.L. Hansaria",
        "PDF Link": "https://digiscr.sci.gov.in/pdf_viewer?dir=YWRtaW4vanVkZ2VtZW50X2ZpbGUvanVkZ2VtZW50X3BkZi8xOTk1L3ZvbHVtZSAxL1BhcnQgSS8xOTk1XzFfNjcwLTY3NV8xNzAyMDI4MjYwLnBkZg=="
    },
    {
        "volume": "1995Volume 1",
        "Case Name": "DIRECTOR, GENERAL OF ORDNANCE SERVICES AND ORS. VS. P.N. MALHOTRA",
        "Case Link": "https://digiscr.sci.gov.in/view_judgment?id=MjA3ODU=",
        "Citation": "[1995] 1 S.C.R. 676",
        "Case Type": "(CIVIL APPEAL /1110/1995)",
        "Date": "20 JANUARY 1995",
        "Judge Names": "Hon'ble Mr. Justice B.P. Jeevan Reddy\n*, Hon'ble Ms. Justice Sujata V Manohar",
        "PDF Link": "https://digiscr.sci.gov.in/pdf_viewer?dir=YWRtaW4vanVkZ2VtZW50X2ZpbGUvanVkZ2VtZW50X3BkZi8xOTk1L3ZvbHVtZSAxL1BhcnQgSS8xOTk1XzFfNjc2LTY4MV8xNzAyMDI4MzY2LnBkZg=="
    },
    {
        "volume": "1995Volume 1",
        "Case Name": "STATE OF MAHARASHTRA VS. GULAB RAO",
        "Case Link": "https://digiscr.sci.gov.in/view_judgment?id=MjA4MTY=",
        "Citation": "[1995] 1 S.C.R. 682",
        "Case Type": "(CIVIL APPEAL /2728/1977)",
        "Date": "30 JANUARY 1995",
        "Judge Names": "Hon'ble Mr. Justice B.L. Hansaria, Hon'ble Mr. Justice Kuldip Singh, Hon'ble Mr. Justice S.B. Majmudar\n*",
        "PDF Link": "https://digiscr.sci.gov.in/pdf_viewer?dir=YWRtaW4vanVkZ2VtZW50X2ZpbGUvanVkZ2VtZW50X3BkZi8xOTk1L3ZvbHVtZSAxL1BhcnQgSS8xOTk1XzFfNjgyLTY5NF8xNzAyMDI4NzU4LnBkZg=="
    },
    {
        "volume": "1995Volume 1",
        "Case Name": "STATE OF PUNJAB AND ORS. VS. CHAMAN LAL GOYAL",
        "Case Link": "https://digiscr.sci.gov.in/view_judgment?id=MjA4MjI=",
        "Citation": "[1995] 1 S.C.R. 695",
        "Case Type": "(CIVIL APPEAL /1101/1995)",
        "Date": "31 MARCH 1995",
        "Judge Names": "Hon'ble Mr. Justice B.P. Jeevan Reddy\n*, Hon'ble Ms. Justice Sujata V Manohar",
        "PDF Link": "https://digiscr.sci.gov.in/pdf_viewer?dir=YWRtaW4vanVkZ2VtZW50X2ZpbGUvanVkZ2VtZW50X3BkZi8xOTk1L3ZvbHVtZSAxL1BhcnQgSS8xOTk1XzFfNjk1LTcwNl8xNzAyMDI4ODk4LnBkZg=="
    },
    {
        "volume": "1995Volume 1",
        "Case Name": "CONSUMER UNITY AND TRUST SOCIETY, JAIPUR VS. THE CHAIRMAN AND MANAGING DIRECTOR, BANK OF BARODA, CALCUTTA AND ANR.",
        "Case Link": "https://digiscr.sci.gov.in/view_judgment?id=MzY0MDY=",
        "Citation": "[1995] 1 S.C.R. 707",
        "Case Type": "(CIVIL APPEAL /7166/1993)",
        "Date": "31 JANUARY 1995",
        "Judge Names": "Hon'ble Mr. Justice Kuldip Singh, Hon'ble Mr. Justice R.M. Sahai\n*, Hon'ble Mr. Justice S. Mohan",
        "PDF Link": "https://digiscr.sci.gov.in/pdf_viewer?dir=YWRtaW4vanVkZ2VtZW50X2ZpbGUvanVkZ2VtZW50X3BkZi8xOTk1L3ZvbHVtZSAxL1BhcnQgSS8xOTk1XzFfNzA3LTcxMV8xNzA0MzYyOTQ3LnBkZg=="
    },
    {
        "volume": "1995Volume 1",
        "Case Name": "STATE OF TAMIL NADU VS. THIRUKKURAL PERUMAL",
        "Case Link": "https://digiscr.sci.gov.in/view_judgment?id=MjEyNTY=",
        "Citation": "[1995] 1 S.C.R. 712",
        "Case Type": "(CRIMINAL APPEAL /218/1995)",
        "Date": "31 JANUARY 1995",
        "Judge Names": "Hon'ble Dr. Justice A.S. Anand, Hon'ble Mr. Justice Faizanuddin",
        "PDF Link": "https://digiscr.sci.gov.in/pdf_viewer?dir=YWRtaW4vanVkZ2VtZW50X2ZpbGUvanVkZ2VtZW50X3BkZi8xOTk1L3ZvbHVtZSAxL1BhcnQgSS8xOTk1XzFfNzEyLTcxNF8xNzAyMDk0NDUzLnBkZg=="
    },
    {
        "volume": "1995Volume 1",
        "Case Name": "R. RAJAGOPAL REDDY (DEAD) BY LRS. AND ORS. VS. PADMINI CHANDRASEKHARAN (DEAD) BY LRS.",
        "Case Link": "https://digiscr.sci.gov.in/view_judgment?id=MjEyNTk=",
        "Citation": "[1995] 1 S.C.R. 715",
        "Case Type": "(CIVIL APPEAL /5653/1990)",
        "Date": "31 JANUARY 1995",
        "Judge Names": "Hon'ble Mr. Justice Kuldip Singh, Hon'ble Mr. Justice B.L. Hansaria, Hon'ble Mr. Justice S.B. Majmudar\n*",
        "PDF Link": "https://digiscr.sci.gov.in/pdf_viewer?dir=YWRtaW4vanVkZ2VtZW50X2ZpbGUvanVkZ2VtZW50X3BkZi8xOTk1L3ZvbHVtZSAxL1BhcnQgSS8xOTk1XzFfNzE1LTczN18xNzAyMDk0NTY4LnBkZg=="
    },
    {
        "volume": "1995Volume 1",
        "Case Name": "M/S. WARDEN AND CO., (INDIA) PVT. LTD. VS. COLLECTOR OF CENTRAL EXCISE, THANE",
        "Case Link": "https://digiscr.sci.gov.in/view_judgment?id=MjEyNjI=",
        "Citation": "[1995] 1 S.C.R. 738",
        "Case Type": "(CIVIL APPEAL /5401/1985)",
        "Date": "01 FEBRUARY 1995",
        "Judge Names": "Hon'ble Mr. Justice A.M. Ahmadi, Hon'ble Mr. Justice N.P. Singh\n*",
        "PDF Link": "https://digiscr.sci.gov.in/pdf_viewer?dir=YWRtaW4vanVkZ2VtZW50X2ZpbGUvanVkZ2VtZW50X3BkZi8xOTk1L3ZvbHVtZSAxL1BhcnQgSS8xOTk1XzFfNzM4LTc0NF8xNzAyMDk0NzQ0LnBkZg=="
    },
    {
        "volume": "1995Volume 1",
        "Case Name": "STATE OF MADHYA PRADESH AND ANR. VS. RAKESH MENON AND ANR. ETC. ETC.",
        "Case Link": "https://digiscr.sci.gov.in/view_judgment?id=MjEyNjQ=",
        "Citation": "[1995] 1 S.C.R. 745",
        "Case Type": "(CIVIL APPEAL /1256/1995)",
        "Date": "01 FEBRUARY 1995",
        "Judge Names": "Hon'ble Mr. Justice A.M. Ahmadi, Hon'ble Mr. Justice N.P. Singh\n*, Hon'ble Ms. Justice Sujata V Manohar",
        "PDF Link": "https://digiscr.sci.gov.in/pdf_viewer?dir=YWRtaW4vanVkZ2VtZW50X2ZpbGUvanVkZ2VtZW50X3BkZi8xOTk1L3ZvbHVtZSAxL1BhcnQgSS8xOTk1XzFfNzQ1LTc0Nl8xNzAyMDk0ODk3LnBkZg=="
    },
    {
        "volume": "1995Volume 1",
        "Case Name": "UNION OF INDIA VS. D. MOHAN AND ORS.",
        "Case Link": "https://digiscr.sci.gov.in/view_judgment?id=MjEyNjk=",
        "Citation": "[1995] 1 S.C.R. 747",
        "Case Type": "(CIVIL APPEAL /1250/1995)",
        "Date": "01 FEBRUARY 1995",
        "Judge Names": "Hon'ble Mr. Justice S.C. Agrawal, Hon'ble Mr. Justice Faizanuddin\n*",
        "PDF Link": "https://digiscr.sci.gov.in/pdf_viewer?dir=YWRtaW4vanVkZ2VtZW50X2ZpbGUvanVkZ2VtZW50X3BkZi8xOTk1L3ZvbHVtZSAxL1BhcnQgSS8xOTk1XzFfNzQ3LTc1NV8xNzAyMDk1MDA1LnBkZg=="
    },
    {
        "volume": "1995Volume 1",
        "Case Name": "STATE OF M.P. VS. MAHALAXMI FABRIC MILLS LTD. AND ORS.",
        "Case Link": "https://digiscr.sci.gov.in/view_judgment?id=MjEyNzQ=",
        "Citation": "[1995] 1 S.C.R. 756",
        "Case Type": "(CIVIL APPEAL /275/1994)",
        "Date": "01 FEBRUARY 1995",
        "Judge Names": "Hon'ble Mr. Justice Kuldip Singh, Hon'ble Mr. Justice B.L. Hansaria, Hon'ble Mr. Justice S.B. Majmudar\n*",
        "PDF Link": "https://digiscr.sci.gov.in/pdf_viewer?dir=YWRtaW4vanVkZ2VtZW50X2ZpbGUvanVkZ2VtZW50X3BkZi8xOTk1L3ZvbHVtZSAxL1BhcnQgSS8xOTk1XzFfNzU2LTc5M18xNzAyMDk1MTUxLnBkZg=="
    },
    {
        "volume": "1995Volume 1",
        "Case Name": "G.D. ZALANI AND ANR. ETC. VS. UNION OF INDIA AND ORS.",
        "Case Link": "https://digiscr.sci.gov.in/view_judgment?id=MjEyODA=",
        "Citation": "[1995] 1 S.C.R. 794",
        "Case Type": "(CIVIL APPEAL /1251-53/1995)",
        "Date": "02 FEBRUARY 1995",
        "Judge Names": "Hon'ble Mr. Justice B.P. Jeevan Reddy\n*, Hon'ble Mr. Justice S.C. Sen",
        "PDF Link": "https://digiscr.sci.gov.in/pdf_viewer?dir=YWRtaW4vanVkZ2VtZW50X2ZpbGUvanVkZ2VtZW50X3BkZi8xOTk1L3ZvbHVtZSAxL1BhcnQgSS8xOTk1XzFfNzk0LTgxOF8xNzAyMDk1MjYzLnBkZg=="
    },
    {
        "volume": "1995Volume 1",
        "Case Name": "HABIBULLA KHAN VS. STATE OF ORISSA AND ANR.",
        "Case Link": "https://digiscr.sci.gov.in/view_judgment?id=MjEyODc=",
        "Citation": "[1995] 1 S.C.R. 819",
        "Case Type": "(CRIMINAL APPEAL /212/1995)",
        "Date": "02 FEBRUARY 1995",
        "Judge Names": "Hon'ble Mr. Justice G.N. Ray, Hon'ble Mr. Justice P.B. Sawant\n*",
        "PDF Link": "https://digiscr.sci.gov.in/pdf_viewer?dir=YWRtaW4vanVkZ2VtZW50X2ZpbGUvanVkZ2VtZW50X3BkZi8xOTk1L3ZvbHVtZSAxL1BhcnQgSS8xOTk1XzFfODE5LTgyNl8xNzAyMDk1MzU5LnBkZg=="
    },
    {
        "volume": "1995Volume 1",
        "Case Name": "MS. SWATI GUPTA VS. STATE OF U.P. AND ORS.",
        "Case Link": "https://digiscr.sci.gov.in/view_judgment?id=MjEyOTE=",
        "Citation": "[1995] 1 S.C.R. 827",
        "Case Type": "(WRIT PETITION (CIVIL) /777/1994)",
        "Date": "02 FEBRUARY 1995",
        "Judge Names": "Hon'ble Mr. Justice R.M. Sahai, Hon'ble Mr. Justice S.C. Sen",
        "PDF Link": "https://digiscr.sci.gov.in/pdf_viewer?dir=YWRtaW4vanVkZ2VtZW50X2ZpbGUvanVkZ2VtZW50X3BkZi8xOTk1L3ZvbHVtZSAxL1BhcnQgSS8xOTk1XzFfODI3LTgzMV8xNzAyMDk1NDY2LnBkZg=="
    },
    {
        "volume": "1995Volume 1",
        "Case Name": "SRI BAGAWATI TEA ESTATES LTD. VS. GOVERNMENT OF INDIA AND ORS.",
        "Case Link": "https://digiscr.sci.gov.in/view_judgment?id=MjEzMDE=",
        "Citation": "[1995] 1 S.C.R. 832",
        "Case Type": "(WRIT PETITION (CIVIL) /974/1991)",
        "Date": "03 FEBRUARY 1995",
        "Judge Names": "Hon'ble Mr. Justice B.P. Jeevan Reddy\n*, Hon'ble Mr. Justice S.C. Sen",
        "PDF Link": "https://digiscr.sci.gov.in/pdf_viewer?dir=YWRtaW4vanVkZ2VtZW50X2ZpbGUvanVkZ2VtZW50X3BkZi8xOTk1L3ZvbHVtZSAxL1BhcnQgSS8xOTk1XzFfODMyXzE3MDIwOTU2NDMucGRm"
    },
    {
        "volume": "1995Volume 1",
        "Case Name": "M/S ISHA MARBLES ETC. ETC. VS. BIHAR STATE ELECTRICITY BOARD AND ANR. ETC. ETC.",
        "Case Link": "https://digiscr.sci.gov.in/view_judgment?id=MjEzMDc=",
        "Citation": "[1995] 1 S.C.R. 847",
        "Case Type": "(CIVIL APPEAL /1418 /1995)",
        "Date": "03 FEBRUARY 1995",
        "Judge Names": "Hon'ble Mr. Justice K.S. Paripoornan, Hon'ble Mr. Justice P.B. Sawant, Hon'ble Mr. Justice S. Mohan\n*",
        "PDF Link": "https://digiscr.sci.gov.in/pdf_viewer?dir=YWRtaW4vanVkZ2VtZW50X2ZpbGUvanVkZ2VtZW50X3BkZi8xOTk1L3ZvbHVtZSAxL1BhcnQgSS8xOTk1XzFfODQ3LTg3MF8xNzAyMDk1Nzg0LnBkZg=="
    },
    {
        "volume": "1995Volume 1",
        "Case Name": "THE NEW INDIA ASSURANCE CO. LTD. VS. SMT. SHANTI BAI AND ORS.",
        "Case Link": "https://digiscr.sci.gov.in/view_judgment?id=MjEzMTY=",
        "Citation": "[1995] 1 S.C.R. 871",
        "Case Type": "(CIVIL APPEAL /1312/1995)",
        "Date": "06 FEBRUARY 1995",
        "Judge Names": "Hon'ble Mr. Justice A.M. Ahmadi, Hon'ble Mr. Justice S.P. Bharucha, Hon'ble Ms. Justice Sujata V Manohar\n*",
        "PDF Link": "https://digiscr.sci.gov.in/pdf_viewer?dir=YWRtaW4vanVkZ2VtZW50X2ZpbGUvanVkZ2VtZW50X3BkZi8xOTk1L3ZvbHVtZSAxL1BhcnQgSS8xOTk1XzFfODcxLTg3Nl8xNzAyMDk1ODk1LnBkZg=="
    },
    {
        "volume": "1995Volume 1",
        "Case Name": "LAL BABU HUSSEIN AND ORS. VS. ELECTORAL REGISTRATION OFFICER AND ORS.",
        "Case Link": "https://digiscr.sci.gov.in/view_judgment?id=MjEzMjY=",
        "Citation": "[1995] 1 S.C.R. 877",
        "Case Type": "(WRIT PETITION (CIVIL) /731/1994)",
        "Date": "06 FEBRUARY 1995",
        "Judge Names": "Hon'ble Mr. Justice A.M. Ahmadi\n*, Hon'ble Mr. Justice N.P. Singh, Hon'ble Ms. Justice Sujata V Manohar",
        "PDF Link": "https://digiscr.sci.gov.in/pdf_viewer?dir=YWRtaW4vanVkZ2VtZW50X2ZpbGUvanVkZ2VtZW50X3BkZi8xOTk1L3ZvbHVtZSAxL1BhcnQgSS8xOTk1XzFfODc3LTg5Nl8xNzAyMDk2MDU3LnBkZg=="
    },
    {
        "volume": "1995Volume 1",
        "Case Name": "STATE OF M.P. AND ANR. VS. RAM KISHNA BALOTHIA AND ANR.",
        "Case Link": "https://digiscr.sci.gov.in/view_judgment?id=MjEzMzY=",
        "Citation": "[1995] 1 S.C.R. 897",
        "Case Type": "(CIVIL APPEAL /1343/1995)",
        "Date": "06 FEBRUARY 1995",
        "Judge Names": "Hon'ble Mr. Justice B.P. Jeevan Reddy, Hon'ble Ms. Justice Sujata V Manohar\n*",
        "PDF Link": "https://digiscr.sci.gov.in/pdf_viewer?dir=YWRtaW4vanVkZ2VtZW50X2ZpbGUvanVkZ2VtZW50X3BkZi8xOTk1L3ZvbHVtZSAxL1BhcnQgSS8xOTk1XzFfODk3LSA5MDdfMTcwMjA5NjE2OC5wZGY="
    },
    {
        "volume": "1995Volume 1",
        "Case Name": "MADAN LAL AND ORS. VS. STATE OF JAMMU AND KASHMIR AND ORS.",
        "Case Link": "https://digiscr.sci.gov.in/view_judgment?id=MjE0MTk=",
        "Citation": "[1995] 1 S.C.R. 908",
        "Case Type": "(WRIT PETITION (CIVIL) /546/1994)",
        "Date": "06 FEBRUARY 1995",
        "Judge Names": "Hon'ble Mr. Justice J.S. Verma, Hon'ble Mr. Justice S.B. Majmudar\n*",
        "PDF Link": "https://digiscr.sci.gov.in/pdf_viewer?dir=YWRtaW4vanVkZ2VtZW50X2ZpbGUvanVkZ2VtZW50X3BkZi8xOTk1L3ZvbHVtZSAxL1BhcnQgSS8xOTk1XzFfOTA4LTkzNF8xNzAyMDk3MzQ3LnBkZg=="
    },
    {
        "volume": "1995Volume 1",
        "Case Name": "ELECTION COMMISSION OF INDIA VS. STATE BANK OF INDIA STAFF ASSOCIATION LOCAL HEAD OFFICE UNIT, PATNA AND ORS. ETC.",
        "Case Link": "https://digiscr.sci.gov.in/view_judgment?id=MjE0MDk=",
        "Citation": "[1995] 1 S.C.R. 935",
        "Case Type": "(CIVIL APPEAL /6026/1993)",
        "Date": "07 FEBRUARY 1995",
        "Judge Names": "Hon'ble Mr. Justice A.M. Ahmadi\n*, Hon'ble Mr. Justice S. Mohan, Hon'ble Mr. Justice N.P. Singh",
        "PDF Link": "https://digiscr.sci.gov.in/pdf_viewer?dir=YWRtaW4vanVkZ2VtZW50X2ZpbGUvanVkZ2VtZW50X3BkZi8xOTk1L3ZvbHVtZSAxL1BhcnQgSS8xOTk1XzFfOTM1LTk0Nl8xNzAyMDk3MjM0LnBkZg=="
    },
    {
        "volume": "1995Volume 1",
        "Case Name": "M/S VOLTAS LTD. BOMBAY VS. UNION OF INDIA AND ORS.",
        "Case Link": "https://digiscr.sci.gov.in/view_judgment?id=MjE0MDE=",
        "Citation": "[1995] 1 S.C.R. 947",
        "Case Type": "(CIVIL APPEAL /2252/1994)",
        "Date": "07 FEBRUARY 1995",
        "Judge Names": "Hon'ble Mr. Justice A.M. Ahmadi, Hon'ble Mr. Justice S. Mohan, Hon'ble Mr. Justice N.P. Singh\n*",
        "PDF Link": "https://digiscr.sci.gov.in/pdf_viewer?dir=YWRtaW4vanVkZ2VtZW50X2ZpbGUvanVkZ2VtZW50X3BkZi8xOTk1L3ZvbHVtZSAxL1BhcnQgSS8xOTk1XzFfOTQ3LTk2Nl8xNzAyMDk3MTE5LnBkZg=="
    },
    {
        "volume": "1995Volume 1",
        "Case Name": "SHARMIK UTTARSH SABHA VS. RAYMOND WOOLLEN MILLS LTD. AND ORS.",
        "Case Link": "https://digiscr.sci.gov.in/view_judgment?id=MjEzOTE=",
        "Citation": "[1995] 1 S.C.R. 967",
        "Case Type": "(CIVIL APPEAL /1408/1995)",
        "Date": "07 FEBRUARY 1995",
        "Judge Names": "Hon'ble Mr. Justice A.M. Ahmadi, Hon'ble Mr. Justice S.P. Bharucha\n*",
        "PDF Link": "https://digiscr.sci.gov.in/pdf_viewer?dir=YWRtaW4vanVkZ2VtZW50X2ZpbGUvanVkZ2VtZW50X3BkZi8xOTk1L3ZvbHVtZSAxL1BhcnQgSS8xOTk1XzFfOTY3LTk3N18xNzAyMDk2OTYxLnBkZg=="
    },
    {
        "volume": "1995Volume 1",
        "Case Name": "M/S NOORULLA GHAZANFARULLA VS. 1. THE MUNICIPAL BOARD OF ALIGARH, ALIGARH 2. THE STATE OF UTTAR PRADESH, LUCKNOW 3. SH. R.N. MATHUR, OFFICER-ON-SPECIAL DUTY, NAGAR PALIKA, ALIGARH.",
        "Case Link": "https://digiscr.sci.gov.in/view_judgment?id=MjEzNzY=",
        "Citation": "[1995] 1 S.C.R. 978",
        "Case Type": "(CIVIL APPEAL /3459/1982)",
        "Date": "07 FEBRUARY 1995",
        "Judge Names": "Hon'ble Mr. Justice N. Venkatachala\n*, Hon'ble Mr. Justice P.B. Sawant",
        "PDF Link": "https://digiscr.sci.gov.in/pdf_viewer?dir=YWRtaW4vanVkZ2VtZW50X2ZpbGUvanVkZ2VtZW50X3BkZi8xOTk1L3ZvbHVtZSAxL1BhcnQgSS8xOTk1XzFfOTc4LTk1XzE3MDIwOTY3MTEucGRm"
    },
    {
        "volume": "1995Volume 1",
        "Case Name": "MANSUKHLAL DHANRAJ JAIN AND ORS. ETC. VS. EKNATH VITHAL OGALE ETC.",
        "Case Link": "https://digiscr.sci.gov.in/view_judgment?id=MjEzNjI=",
        "Citation": "[1995] 1 S.C.R. 996",
        "Case Type": "(CIVIL APPEAL /4913/1989)",
        "Date": "08 FEBRUARY 1995",
        "Judge Names": "Hon'ble Mr. Justice S. Mohan, Hon'ble Mr. Justice S.B. Majmudar\n*",
        "PDF Link": "https://digiscr.sci.gov.in/pdf_viewer?dir=YWRtaW4vanVkZ2VtZW50X2ZpbGUvanVkZ2VtZW50X3BkZi8xOTk1L3ZvbHVtZSAxL1BhcnQgSS8xOTk1XzFfOTk2LTEwMDlfMTcwMjA5NjQ5Mi5wZGY="
    },
    {
        "volume": "1995Volume 1",
        "Case Name": "DELHI DEVELOPMENT AUTHORITY VS. SKIPPER CONSTRUCTION AND ANR. ETC.",
        "Case Link": "https://digiscr.sci.gov.in/view_judgment?id=MjEzNDk=",
        "Citation": "[1995] 1 S.C.R. 1010",
        "Case Type": "(SPECIAL LEAVE PETITION (CIVIL) /21000/1993)",
        "Date": "08 FEBRUARY 1995",
        "Judge Names": "Hon'ble Mr. Justice P.B. Sawant, Hon'ble Mr. Justice S. Mohan, Hon'ble Mr. Justice B.P. Jeevan Reddy",
        "PDF Link": "https://digiscr.sci.gov.in/pdf_viewer?dir=YWRtaW4vanVkZ2VtZW50X2ZpbGUvanVkZ2VtZW50X3BkZi8xOTk1L3ZvbHVtZSAxL1BhcnQgSS8xOTk1XzFfMTAxMC0xMTkxXzE3MDIwOTYzMzgucGRm"
    },
    {
        "volume": "1995Volume 1",
        "Case Name": "RAVI PAUL AND ORS. VS. UNION OF INDIA AND ORS.",
        "Case Link": "https://digiscr.sci.gov.in/view_judgment?id=MzU3Mjc=",
        "Citation": "[1995] 1 S.C.R. 419",
        "Case Type": "(WRIT PETITION (CIVIL) /146/1992)",
        "Date": "19 JANUARY 1995",
        "Judge Names": "Hon'ble Mr. Justice B.L. Hansaria, Hon'ble Mr. Justice Kuldip Singh, Hon'ble Mr. Justice S.C. Agrawal\n*",
        "PDF Link": "https://digiscr.sci.gov.in/pdf_viewer?dir=YWRtaW4vanVkZ2VtZW50X2ZpbGUvanVkZ2VtZW50X3BkZi8xOTk1L3ZvbHVtZSAxL1BhcnQgSS8xOTk1XzFfNDE5LTQ0MF8xNzAzMzI3NjAwLnBkZg=="
    },
    {
        "volume": "1995Volume 1",
        "Case Name": "THE SECRETARY, MINISTRY OF INFORMATION AND BROADCASTING, GOVERNMENT OF INDIA AND ORS. VS. CRICKET ASSOCIATION OF BENGAL AND ORS. AND VICE VERSA",
        "Case Link": "https://digiscr.sci.gov.in/view_judgment?id=MzY0NDA=",
        "Citation": "[1995] 1 S.C.R. 1036",
        "Case Type": "(CIVIL APPEAL /1429/1995)",
        "Date": "09 FEBRUARY 1995",
        "Judge Names": "Hon'ble Mr. Justice B.P. Jeevan Reddy, Hon'ble Mr. Justice P.B. Sawant\n*, Hon'ble Mr. Justice S. Mohan",
        "PDF Link": "https://digiscr.sci.gov.in/pdf_viewer?dir=YWRtaW4vanVkZ2VtZW50X2ZpbGUvanVkZ2VtZW50X3BkZi8xOTk1L3ZvbHVtZSAxL1BhcnQgSS8xOTk1XzFfMTAzNi0xMTkxXzE3MDUzODY1MTgucGRm"
    }
]