[
    {
        "volume": "1995Volume 3",
        "Case Name": "M/S. BOMBAY CHEMICAL PRIVATE LIMITED VS. THE COLLECTOR OF CENTRAL EXCISE, BOMBAY I, BOMBAY",
        "Case Link": "https://digiscr.sci.gov.in/view_judgment?id=NjA5Mw==",
        "Citation": "[1995] 3 S.C.R. 369",
        "Case Type": "(CIVIL APPEAL /2276/1986)",
        "Date": "18 APRIL 1995",
        "Judge Names": "Hon'ble Mr. Justice R.M. Sahai\n*, Hon'ble Mr. Justice S.B. Majmudar, Hon'ble Ms. Justice Sujata V Manohar",
        "PDF Link": "https://digiscr.sci.gov.in/pdf_viewer?dir=YWRtaW4vanVkZ2VtZW50X2ZpbGUvanVkZ2VtZW50X3BkZi8xOTk1L3ZvbHVtZSAzL1BhcnQgSS8xOTk1XzNfMzY5LTM3Nl8xNzAyOTYzMzU5LnBkZg=="
    },
    {
        "volume": "1995Volume 3",
        "Case Name": "FENNER (INDIA) LTD. VS. COLLECTOR OF CENTRAL EXCISE, MADURAI",
        "Case Link": "https://digiscr.sci.gov.in/view_judgment?id=MTIzNjA=",
        "Citation": "[1995] 3 S.C.R. 1",
        "Case Type": "(CIVIL APPEAL /4600/1989)",
        "Date": "28 MARCH 1995",
        "Judge Names": "Hon'ble Mr. Justice A.M. Ahmadi, Hon'ble Mr. Justice S.P. Bharucha\n*, Hon'ble Mr. Justice K.S. Paripoornan",
        "PDF Link": "https://digiscr.sci.gov.in/pdf_viewer?dir=YWRtaW4vanVkZ2VtZW50X2ZpbGUvanVkZ2VtZW50X3BkZi8xOTk1L3ZvbHVtZSAzL1BhcnQgSS9GZW5uZXIgKGluZGlhKSBMdGQuIF8gQ29sbGVjdG9yIE9mIENlbnRyYWwgRXhjaXNlLCBNYWR1cmFpXzE3MDE0OTUyNzEucGRm"
    },
    {
        "volume": "1995Volume 3",
        "Case Name": "NAGAR PALIKA, JIND VS. JAGAT.SINGH, ADVOCATE",
        "Case Link": "https://digiscr.sci.gov.in/view_judgment?id=MTIzNjc=",
        "Citation": "[1995] 3 S.C.R. 9",
        "Case Type": "()",
        "Date": "28 MARCH 1995",
        "Judge Names": "Hon'ble Mr. Justice J.S. Verma, Hon'ble Mr. Justice N.P. Singh\n*, Hon'ble Mr. Justice K. Venkataswami",
        "PDF Link": "https://digiscr.sci.gov.in/pdf_viewer?dir=YWRtaW4vanVkZ2VtZW50X2ZpbGUvanVkZ2VtZW50X3BkZi8xOTk1L3ZvbHVtZSAzL1BhcnQgSS9OYWdhciBQYWxpa2EsIEppbmQgXyBKYWdhdC5zaW5naCwgQWR2b2NhdGVfMTcwMTQ5NTQ0Mi5wZGY="
    },
    {
        "volume": "1995Volume 3",
        "Case Name": "THE UNION OF INDIA AND ORS. VS. M/S.J.M.A. INDUSTRIES",
        "Case Link": "https://digiscr.sci.gov.in/view_judgment?id=MTIzODI=",
        "Citation": "[1995] 3 S.C.R. 19",
        "Case Type": "(CIVIL APPEAL /753/1988)",
        "Date": "28 MARCH 1995",
        "Judge Names": "Hon'ble Mr. Justice R.M. Sahai, Hon'ble Mr. Justice S.B. Majmudar",
        "PDF Link": "https://digiscr.sci.gov.in/pdf_viewer?dir=YWRtaW4vanVkZ2VtZW50X2ZpbGUvanVkZ2VtZW50X3BkZi8xOTk1L3ZvbHVtZSAzL1BhcnQgSS8xOTk1XzNfMTktIDIyXzE3MDMyMzk0NTMucGRm"
    },
    {
        "volume": "1995Volume 3",
        "Case Name": "M/S GARWARE NYLONS LTD. VS. PIMPRI CHINCHWAD MAHANAGAR PALIKA AND ORS.",
        "Case Link": "https://digiscr.sci.gov.in/view_judgment?id=MTIzOTc=",
        "Citation": "[1995] 3 S.C.R. 23",
        "Case Type": "(CIVIL APPEAL /1662/1988)",
        "Date": "28 MARCH 1995",
        "Judge Names": "Hon'ble Mr. Justice R.M. Sahai, Hon'ble Mr. Justice S.B. Majmudar",
        "PDF Link": "https://digiscr.sci.gov.in/pdf_viewer?dir=YWRtaW4vanVkZ2VtZW50X2ZpbGUvanVkZ2VtZW50X3BkZi8xOTk1L3ZvbHVtZSAzL1BhcnQgSS8xOTk1XzNfMjMgLSAyNl8xNzAzMjM5NTI5LnBkZg=="
    },
    {
        "volume": "1995Volume 3",
        "Case Name": "GULABCHAND VS. STATE OF MADHYA PRADESH",
        "Case Link": "https://digiscr.sci.gov.in/view_judgment?id=MTI0MDY=",
        "Citation": "[1995] 3 S.C.R. 27",
        "Case Type": "(CRIMINAL APPEAL /140 AND 140A/1984)",
        "Date": "28 MARCH 1995",
        "Judge Names": "Hon'ble Mr. Justice G.N. Ray, Hon'ble Mr. Justice Faizanuddin",
        "PDF Link": "https://digiscr.sci.gov.in/pdf_viewer?dir=YWRtaW4vanVkZ2VtZW50X2ZpbGUvanVkZ2VtZW50X3BkZi8xOTk1L3ZvbHVtZSAzL1BhcnQgSS9HdWxhYmNoYW5kIF8gU3RhdGUgT2YgTWFkaHlhIFByYWRlc2hfMTcwMTQ5NjYzMC5wZGY="
    },
    {
        "volume": "1995Volume 3",
        "Case Name": "PARIMAL CHANDRA AND ORS. VS. LIFE INSURANCE CORPORATION OF INDIA AND ORS.",
        "Case Link": "https://digiscr.sci.gov.in/view_judgment?id=MTI0MTI=",
        "Citation": "[1995] 3 S.C.R. 34",
        "Case Type": "()",
        "Date": "29 MARCH 1995",
        "Judge Names": "Hon'ble Mr. Justice P.B. Sawant\n*, Hon'ble Mr. Justice S.B. Majmudar",
        "PDF Link": "https://digiscr.sci.gov.in/pdf_viewer?dir=YWRtaW4vanVkZ2VtZW50X2ZpbGUvanVkZ2VtZW50X3BkZi8xOTk1L3ZvbHVtZSAzL1BhcnQgSS9QYXJpbWFsIENoYW5kcmEgQW5kIE9ycy4gXyBMaWZlIEluc3VyYW5jZSBDb3Jwb3JhdGlvbiBPZiBJbmRpYSBBbmQgT3JzLl8xNzAxNDk2ODM5LnBkZg=="
    },
    {
        "volume": "1995Volume 3",
        "Case Name": "M/S COMMERCE INTERNATIONAL VS. COLLECTOR OF CUSTOMS",
        "Case Link": "https://digiscr.sci.gov.in/view_judgment?id=MTI0MTg=",
        "Citation": "[1995] 3 S.C.R. 69",
        "Case Type": "(CIVIL APPEAL /2198/1988)",
        "Date": "29 MARCH 1995",
        "Judge Names": "Hon'ble Mr. Justice R.M. Sahai, Hon'ble Mr. Justice S.C. Sen",
        "PDF Link": "https://digiscr.sci.gov.in/pdf_viewer?dir=YWRtaW4vanVkZ2VtZW50X2ZpbGUvanVkZ2VtZW50X3BkZi8xOTk1L3ZvbHVtZSAzL1BhcnQgSS8xOTk1XzNfNjkgLSA3MV8xNzAzMjM5NTgyLnBkZg=="
    },
    {
        "volume": "1995Volume 3",
        "Case Name": "JAGDISH SINGH AND ANR. VS. UNION OF INDIA AND ANR.",
        "Case Link": "https://digiscr.sci.gov.in/view_judgment?id=MTI0Mjg=",
        "Citation": "[1995] 3 S.C.R. 72",
        "Case Type": "(CIVIL APPEAL /4341/1995)",
        "Date": "29 MARCH 1995",
        "Judge Names": "Hon'ble Mr. Justice K. Ramaswamy, Hon'ble Mr. Justice B.L. Hansaria",
        "PDF Link": "https://digiscr.sci.gov.in/pdf_viewer?dir=YWRtaW4vanVkZ2VtZW50X2ZpbGUvanVkZ2VtZW50X3BkZi8xOTk1L3ZvbHVtZSAzL1BhcnQgSS9KYWdkaXNoIFNpbmdoIEFuZCBBbnIuIF8gVW5pb24gT2YgSW5kaWEgQW5kIEFuci5fMTcwMTQ5NzM3Ni5wZGY="
    },
    {
        "volume": "1995Volume 3",
        "Case Name": "BUTU PRASAD KUMBHAR AND ORS. VS. STEEL AUTHORITY OF INDIA LTD. AND ORS.",
        "Case Link": "https://digiscr.sci.gov.in/view_judgment?id=MTI0MzA=",
        "Citation": "[1995] 3 S.C.R. 76",
        "Case Type": "(WRIT PETITION (CIVIL) /167/1992)",
        "Date": "20 MARCH 1995",
        "Judge Names": "Hon'ble Mr. Justice R.M. Sahai\n*, Hon'ble Mr. Justice S.B. Majmudar",
        "PDF Link": "https://digiscr.sci.gov.in/pdf_viewer?dir=YWRtaW4vanVkZ2VtZW50X2ZpbGUvanVkZ2VtZW50X3BkZi8xOTk1L3ZvbHVtZSAzL1BhcnQgSS9CdXR1IFByYXNhZCBLdW1iaGFyIEFuZCBPcnMuIF8gU3RlZWwgQXV0aG9yaXR5IE9mIEluZGlhIEx0ZC4gQW5kIE9ycy5fMTcwMTQ5NzUxMy5wZGY="
    },
    {
        "volume": "1995Volume 3",
        "Case Name": "COLLECTOR` CENTRAL EXCISE, BOMBAY VS. M/S. S.D. FINE CHEMICALS PVT. LTD.",
        "Case Link": "https://digiscr.sci.gov.in/view_judgment?id=MTI0MzU=",
        "Citation": "[1995] 3 S.C.R. 84",
        "Case Type": "(CIVIL APPEAL /2532/1992)",
        "Date": "30 MARCH 1995",
        "Judge Names": "Hon'ble Mr. Justice B.P. Jeevan Reddy\n*, Hon'ble Mr. Justice S.C. Sen",
        "PDF Link": "https://digiscr.sci.gov.in/pdf_viewer?dir=YWRtaW4vanVkZ2VtZW50X2ZpbGUvanVkZ2VtZW50X3BkZi8xOTk1L3ZvbHVtZSAzL1BhcnQgSS8xOTk1XzNfODQgLSA5NCBfMTcwMzIzOTYyMy5wZGY="
    },
    {
        "volume": "1995Volume 3",
        "Case Name": "JHUMMAN SINGH AND ORS. VS. CENTRAL BOARD OF INVESTIGATION AND ORS.",
        "Case Link": "https://digiscr.sci.gov.in/view_judgment?id=MTI0NDE=",
        "Citation": "[1995] 3 S.C.R. 95",
        "Case Type": "(WRIT PETITION (CIVIL) /487/1994)",
        "Date": "30 MARCH 1995",
        "Judge Names": "Hon'ble Mr. Justice B.P. Jeevan Reddy\n*, Hon'ble Mr. Justice S.C. Sen",
        "PDF Link": "https://digiscr.sci.gov.in/pdf_viewer?dir=YWRtaW4vanVkZ2VtZW50X2ZpbGUvanVkZ2VtZW50X3BkZi8xOTk1L3ZvbHVtZSAzL1BhcnQgSS9KaHVtbWFuIFNpbmdoIEFuZCBPcnMuIF8gQ2VudHJhbCBCb2FyZCBPZiBJbnZlc3RpZ2F0aW9uIEFuZCBPcnMuXzE3MDE0OTc4MTEucGRm"
    },
    {
        "volume": "1995Volume 3",
        "Case Name": "A.N. SEHGAL AND ORS. VS. RAJE RAM SHEORAN AND ORS.",
        "Case Link": "https://digiscr.sci.gov.in/view_judgment?id=MTI0NDc=",
        "Citation": "[1995] 3 S.C.R. 104",
        "Case Type": "(CONTEMPT PETITION (CIVIL) /4094/1984)",
        "Date": "31 MARCH 1995",
        "Judge Names": "Hon'ble Mr. Justice K. Ramaswamy, Hon'ble Mr. Justice N. Venkatachala",
        "PDF Link": "https://digiscr.sci.gov.in/pdf_viewer?dir=YWRtaW4vanVkZ2VtZW50X2ZpbGUvanVkZ2VtZW50X3BkZi8xOTk1L3ZvbHVtZSAzL1BhcnQgSS9BLm4uIFNlaGdhbCBBbmQgT3JzLiBfIFJhamUgUmFtIFNoZW9yYW4gQW5kIE9ycy5fMTcwMTQ5Nzk0OC5wZGY="
    },
    {
        "volume": "1995Volume 3",
        "Case Name": "DADAN BAI WD/O BHAGCHAND SINDHI VS. ARJUNDAS",
        "Case Link": "https://digiscr.sci.gov.in/view_judgment?id=MTI0NTY=",
        "Citation": "[1995] 3 S.C.R. 109",
        "Case Type": "(CIVIL APPEAL /4183/1995)",
        "Date": "31 MARCH 1995",
        "Judge Names": "Hon'ble Mr. Justice R.M. Sahai, Hon'ble Mr. Justice S.B. Majmudar",
        "PDF Link": "https://digiscr.sci.gov.in/pdf_viewer?dir=YWRtaW4vanVkZ2VtZW50X2ZpbGUvanVkZ2VtZW50X3BkZi8xOTk1L3ZvbHVtZSAzL1BhcnQgSS8xOTk1XzNfMTA5IC0gMTEwXzE3MDMyMzk2NjIucGRm"
    },
    {
        "volume": "1995Volume 3",
        "Case Name": "KAMLA SHANKAR VS. THE DIRECTOR OF BOARD OF TECHNICAL EDUCATION, KANPUR AND ANR.",
        "Case Link": "https://digiscr.sci.gov.in/view_judgment?id=MTI0NjQ=",
        "Citation": "[1995] 3 S.C.R. 111",
        "Case Type": "(CIVIL APPEAL /4597/1995)",
        "Date": "31 MARCH 1995",
        "Judge Names": "Hon'ble Mr. Justice K. Ramaswamy, Hon'ble Mr. Justice N. Venkatachala",
        "PDF Link": "https://digiscr.sci.gov.in/pdf_viewer?dir=YWRtaW4vanVkZ2VtZW50X2ZpbGUvanVkZ2VtZW50X3BkZi8xOTk1L3ZvbHVtZSAzL1BhcnQgSS9LYW1sYSBTaGFua2FyIF8gVGhlIERpcmVjdG9yIE9mIEJvYXJkIE9mIFRlY2huaWNhbCBFZHVjYXRpb24sIEthbnB1ciBBbmQgQW5yLl8xNzAxNDk4MjQ5LnBkZg=="
    },
    {
        "volume": "1995Volume 3",
        "Case Name": "THE IMPROVEMENT TRUST, PATIALA VS. THE LAND ACQUISITION TRIBUNAL AND ORS.",
        "Case Link": "https://digiscr.sci.gov.in/view_judgment?id=MTI0ODE=",
        "Citation": "[1995] 3 S.C.R. 113",
        "Case Type": "(CIVIL APPEAL /4695/1995)",
        "Date": "31 MARCH 1995",
        "Judge Names": "Hon'ble Mr. Justice K. Ramaswamy, Hon'ble Mr. Justice N. Venkatachala",
        "PDF Link": "https://digiscr.sci.gov.in/pdf_viewer?dir=YWRtaW4vanVkZ2VtZW50X2ZpbGUvanVkZ2VtZW50X3BkZi8xOTk1L3ZvbHVtZSAzL1BhcnQgSS9UaGUgSW1wcm92ZW1lbnQgVHJ1c3QsIFBhdGlhbGEgXyBUaGUgTGFuZCBBY3F1aXNpdGlvbiBUcmlidW5hbCBBbmQgT3JzLl8xNzAxNDk4NTA1LnBkZg=="
    },
    {
        "volume": "1995Volume 3",
        "Case Name": "DR. KASHINATH NAGAYYA IBATTE VS. STATE OF MAHARASHTRA AND ORS.",
        "Case Link": "https://digiscr.sci.gov.in/view_judgment?id=MTI0OTQ=",
        "Citation": "[1995] 3 S.C.R. 115",
        "Case Type": "(CIVIL APPEAL /4724/1995)",
        "Date": "31 MARCH 1995",
        "Judge Names": "Hon'ble Mr. Justice K. Ramaswamy, Hon'ble Mr. Justice N. Venkatachala",
        "PDF Link": "https://digiscr.sci.gov.in/pdf_viewer?dir=YWRtaW4vanVkZ2VtZW50X2ZpbGUvanVkZ2VtZW50X3BkZi8xOTk1L3ZvbHVtZSAzL1BhcnQgSS9Eci4gS2FzaGluYXRoIE5hZ2F5eWEgSWJhdHRlIF8gU3RhdGUgT2YgTWFoYXJhc2h0cmEgQW5kIE9ycy5fMTcwMTQ5ODY2MC5wZGY="
    },
    {
        "volume": "1995Volume 3",
        "Case Name": "SAIYAD MOHD. SAIYAD UMAR SAIYED AND ORS. VS. THE STATE OF GUJARAT",
        "Case Link": "https://digiscr.sci.gov.in/view_judgment?id=MTI1MTI=",
        "Citation": "[1995] 3 S.C.R. 117",
        "Case Type": "(CRIMINAL APPEAL /485/1995)",
        "Date": "03 APRIL 1995",
        "Judge Names": "Hon'ble Mr. Justice A.M. Ahmadi, Hon'ble Mr. Justice S.P. Bharucha\n*, Hon'ble Mr. Justice G.T. Nanavati",
        "PDF Link": "https://digiscr.sci.gov.in/pdf_viewer?dir=YWRtaW4vanVkZ2VtZW50X2ZpbGUvanVkZ2VtZW50X3BkZi8xOTk1L3ZvbHVtZSAzL1BhcnQgSS9TYWl5YWQgTW9oZC4gU2FpeWFkIFVtYXIgU2FpeWVkIEFuZCBPcnMuIF8gVGhlIFN0YXRlIE9mIEd1amFyYXRfMTcwMTQ5ODkxMS5wZGY="
    },
    {
        "volume": "1995Volume 3",
        "Case Name": "REV. FR. M.S. POULOSE VS. VARGHESE AND ORS.",
        "Case Link": "https://digiscr.sci.gov.in/view_judgment?id=MTI1MjI=",
        "Citation": "[1995] 3 S.C.R. 126",
        "Case Type": "(CIVIL APPEAL /4307/1995)",
        "Date": "30 MARCH 1995",
        "Judge Names": "Hon'ble Mr. Justice K. Ramaswamy, Hon'ble Mr. Justice B.L. Hansaria",
        "PDF Link": "https://digiscr.sci.gov.in/pdf_viewer?dir=YWRtaW4vanVkZ2VtZW50X2ZpbGUvanVkZ2VtZW50X3BkZi8xOTk1L3ZvbHVtZSAzL1BhcnQgSS9SZXYuIEZyLiBNLnMuIFBvdWxvc2UgXyBWYXJnaGVzZSBBbmQgT3JzLl8xNzAxNDk5MDYxLnBkZg=="
    },
    {
        "volume": "1995Volume 3",
        "Case Name": "G. RABINATHAN VS. STATE OF KARNATAKA AND ORS.",
        "Case Link": "https://digiscr.sci.gov.in/view_judgment?id=MTI1MzI=",
        "Citation": "[1995] 3 S.C.R. 129",
        "Case Type": "(CIVIL APPEAL /4430- 31/1995)",
        "Date": "03 APRIL 1995",
        "Judge Names": "Hon'ble Mr. Justice B.L. Hansaria, Hon'ble Mr. Justice K. Ramaswamy",
        "PDF Link": "https://digiscr.sci.gov.in/pdf_viewer?dir=YWRtaW4vanVkZ2VtZW50X2ZpbGUvanVkZ2VtZW50X3BkZi8xOTk1L3ZvbHVtZSAzL1BhcnQgSS9HLiBSYWJpbmF0aGFuIF8gU3RhdGUgT2YgS2FybmF0YWthIEFuZCBPcnMuXzE3MDE0OTkyMzUucGRm"
    },
    {
        "volume": "1995Volume 3",
        "Case Name": "LAL MANDI VS. THE STATE OF WEST BENGAL",
        "Case Link": "https://digiscr.sci.gov.in/view_judgment?id=MTI1NTE=",
        "Citation": "[1995] 3 S.C.R. 134",
        "Case Type": "(CRIMINAL APPEAL /745/1991)",
        "Date": "04 APRIL 1995",
        "Judge Names": "Hon'ble Dr. Justice A.S. Anand\n*, Hon'ble Mr. Justice M.K. Mukherjee",
        "PDF Link": "https://digiscr.sci.gov.in/pdf_viewer?dir=YWRtaW4vanVkZ2VtZW50X2ZpbGUvanVkZ2VtZW50X3BkZi8xOTk1L3ZvbHVtZSAzL1BhcnQgSS9MYWwgTWFuZGkgXyBUaGUgU3RhdGUgT2YgV2VzdCBCZW5nYWxfMTcwMTQ5OTU4OC5wZGY="
    },
    {
        "volume": "1995Volume 3",
        "Case Name": "V.CHARULATHA AND OTHERS VS. S. GUNALAN, CHAIRMAN, RAILWAY RECRUITMENT BOARD, MADRAS AND ORS.",
        "Case Link": "https://digiscr.sci.gov.in/view_judgment?id=MTI1NzM=",
        "Citation": "[1995] 3 S.C.R. 140",
        "Case Type": "(CIVIL APPEAL /2577-2616/1991)",
        "Date": "04 APRIL 1995",
        "Judge Names": "Hon'ble Mr. Justice R.M. Sahai\n*, Hon'ble Mr. Justice S.B. Majmudar",
        "PDF Link": "https://digiscr.sci.gov.in/pdf_viewer?dir=YWRtaW4vanVkZ2VtZW50X2ZpbGUvanVkZ2VtZW50X3BkZi8xOTk1L3ZvbHVtZSAzL1BhcnQgSS9WLmNoYXJ1bGF0aGEgQW5kIE90aGVycyBfIFMuIEd1bmFsYW4sIENoYWlybWFuLCBSYWlsd2F5IFJlY3J1aXRtZW50IEJvYXJkLCBNYWRyYXMgQW5kIE9ycy5fMTcwMTQ5OTkxOC5wZGY="
    },
    {
        "volume": "1995Volume 3",
        "Case Name": "M/S. SAHNEY PARIS RHONE LTD. VS. THE COLLECTOR OF CENTRAL EXCISE, HYDERABAD",
        "Case Link": "https://digiscr.sci.gov.in/view_judgment?id=MTI1ODE=",
        "Citation": "[1995] 3 S.C.R. 150",
        "Case Type": "(CIVIL APPEAL /3939/1987)",
        "Date": "04 APRIL 1995",
        "Judge Names": "Hon'ble Mr. Justice R.M. Sahai, Hon'ble Mr. Justice S.B. Majmudar\n*, Hon'ble Ms. Justice Sujata V Manohar",
        "PDF Link": "https://digiscr.sci.gov.in/pdf_viewer?dir=YWRtaW4vanVkZ2VtZW50X2ZpbGUvanVkZ2VtZW50X3BkZi8xOTk1L3ZvbHVtZSAzL1BhcnQgSS8xOTk1XzNfMTUwIC0gMTU4XzE3MDMyMzk3MjUucGRm"
    },
    {
        "volume": "1995Volume 3",
        "Case Name": "COLLECTOR OF CENTRAL EXCISE, BOMBAY VS. M/S KOHINOOR MILLS BOMBAY",
        "Case Link": "https://digiscr.sci.gov.in/view_judgment?id=MTI1OTQ=",
        "Citation": "[1995] 3 S.C.R. 159",
        "Case Type": "(CIVIL APPEAL /10304/1988)",
        "Date": "04 APRIL 1995",
        "Judge Names": "Hon'ble Mr. Justice R.M. Sahai, Hon'ble Mr. Justice S.B. Majmudar\n*",
        "PDF Link": "https://digiscr.sci.gov.in/pdf_viewer?dir=YWRtaW4vanVkZ2VtZW50X2ZpbGUvanVkZ2VtZW50X3BkZi8xOTk1L3ZvbHVtZSAzL1BhcnQgSS8xOTk1XzNfMTU5IC0gMTY5XzE3MDMyMzk4MTEucGRm"
    },
    {
        "volume": "1995Volume 3",
        "Case Name": "COMMISSIONER OF INCOME TAX, CALCUTTA VS. BIJOY KUMAR ALMAL",
        "Case Link": "https://digiscr.sci.gov.in/view_judgment?id=MTI2MTA=",
        "Citation": "[1995] 3 S.C.R. 170",
        "Case Type": "(CIVIL APPEAL /2298/1977)",
        "Date": "04 APRIL 1995",
        "Judge Names": "Hon'ble Mr. Justice B.P. Jeevan Reddy\n*, Hon'ble Mr. Justice G.T. Nanavati",
        "PDF Link": "https://digiscr.sci.gov.in/pdf_viewer?dir=YWRtaW4vanVkZ2VtZW50X2ZpbGUvanVkZ2VtZW50X3BkZi8xOTk1L3ZvbHVtZSAzL1BhcnQgSS9Db21taXNzaW9uZXIgT2YgSW5jb21lIFRheCwgQ2FsY3V0aWEgXyBCaWpveSBLdW1hciBBbG1hbF8xNzAxNTAwNDUwLnBkZg=="
    },
    {
        "volume": "1995Volume 3",
        "Case Name": "LAXMI ENGINEERING WORKS VS. P.S.G. INDUSTRIAL INSTITUTE",
        "Case Link": "https://digiscr.sci.gov.in/view_judgment?id=MTI2MjA=",
        "Citation": "[1995] 3 S.C.R. 174",
        "Case Type": "(CIVIL APPEAL /4193/1995)",
        "Date": "04 APRIL 1995",
        "Judge Names": "Hon'ble Mr. Justice B.P. Jeevan Reddy\n*, Hon'ble Ms. Justice Sujata V Manohar",
        "PDF Link": "https://digiscr.sci.gov.in/pdf_viewer?dir=YWRtaW4vanVkZ2VtZW50X2ZpbGUvanVkZ2VtZW50X3BkZi8xOTk1L3ZvbHVtZSAzL1BhcnQgSS9MYXhtaSBFbmdpbmVlcmluZyBXb3JrcyBfIFAucy5nLiBJbmR1c3RyaWFsIEluc3RpdHV0ZV8xNzAxNTAwNTg5LnBkZg=="
    },
    {
        "volume": "1995Volume 3",
        "Case Name": "DIRECTOR, CENTRAL BUREAU OF INVESTIGATION AND ORS. VS. NIYAMAVEDI REPRESENTED BY ITS MEMBER K. NANDINI, ADVOCATE AND ORS.",
        "Case Link": "https://digiscr.sci.gov.in/view_judgment?id=MTI2MzI=",
        "Citation": "[1995] 3 S.C.R. 196",
        "Case Type": "(SPECIAL LEAVE PETITION (CRIMINAL) /942/1995)",
        "Date": "05 APRIL 1995",
        "Judge Names": "Hon'ble Mr. Justice A.M. Ahmadi, Hon'ble Mr. Justice K.S. Paripoornan, Hon'ble Ms. Justice Sujata V Manohar\n*",
        "PDF Link": "https://digiscr.sci.gov.in/pdf_viewer?dir=YWRtaW4vanVkZ2VtZW50X2ZpbGUvanVkZ2VtZW50X3BkZi8xOTk1L3ZvbHVtZSAzL1BhcnQgSS9EaXJlY3RvciwgQ2VudHJhbCBCdXJlYXUgT2YgSW52ZXN0aWdhdGlvbiBBbmQgT3JzLiBfIE5peWFtYXZlZGkgUmVwcmVzZW50ZWQgQnkgSXRzIE1lbWJlciBLLiBOYW5kaW5pLCBBZHZvY2F0ZSBBbmQgT3JzLl8xNzAxNTAwNzQ3LnBkZg=="
    },
    {
        "volume": "1995Volume 3",
        "Case Name": "SHAHABUDDIN ABDUL KAHLIK SHAIKH VS. STATE OF GUJARAT",
        "Case Link": "https://digiscr.sci.gov.in/view_judgment?id=MTI2NDc=",
        "Citation": "[1995] 3 S.C.R. 200",
        "Case Type": "(CRIMINAL APPEAL /242/1994)",
        "Date": "05 APRIL 1995",
        "Judge Names": "Hon'ble Dr. Justice A.S. Anand, Hon'ble Mr. Justice M.K. Mukherjee\n*",
        "PDF Link": "https://digiscr.sci.gov.in/pdf_viewer?dir=YWRtaW4vanVkZ2VtZW50X2ZpbGUvanVkZ2VtZW50X3BkZi8xOTk1L3ZvbHVtZSAzL1BhcnQgSS9TaGFoYWJ1ZGRpbiBBYmR1bCBLYWhsaWsgU2hhaWtoIF8gU3RhdGUgT2YgR3VqYXJhdF8xNzAxNTAwOTE1LnBkZg=="
    },
    {
        "volume": "1995Volume 3",
        "Case Name": "SMT. KEWAL PATI VS. STATE OF U.P AND ORS.",
        "Case Link": "https://digiscr.sci.gov.in/view_judgment?id=MTI2NzA=",
        "Citation": "[1995] 3 S.C.R. 207",
        "Case Type": "(WRIT PETITION(CRIMINAL) /1119/1991)",
        "Date": "06 APRIL 1995",
        "Judge Names": "Hon'ble Mr. Justice R.M. Sahai, Hon'ble Mr. Justice S.B. Majmudar",
        "PDF Link": "https://digiscr.sci.gov.in/pdf_viewer?dir=YWRtaW4vanVkZ2VtZW50X2ZpbGUvanVkZ2VtZW50X3BkZi8xOTk1L3ZvbHVtZSAzL1BhcnQgSS9TbXQuIEtld2FsIFBhdGkgXyBTdGF0ZSBPZiBVLnAgQW5kIE9ycy5fMTcwMTUwMTI1OC5wZGY="
    },
    {
        "volume": "1995Volume 3",
        "Case Name": "STATE OF U.P. AND ORS. VS. COMMITTEE OF MANAGEMENT OF S.K.M. INTER COLLEGE AND ANR.",
        "Case Link": "https://digiscr.sci.gov.in/view_judgment?id=MTI2ODI=",
        "Citation": "[1995] 3 S.C.R. 210",
        "Case Type": "(CIVIL APPEAL /4851/1995)",
        "Date": "06 APRIL 1995",
        "Judge Names": "Hon'ble Mr. Justice K. Ramaswamy, Hon'ble Mr. Justice B.L. Hansaria",
        "PDF Link": "https://digiscr.sci.gov.in/pdf_viewer?dir=YWRtaW4vanVkZ2VtZW50X2ZpbGUvanVkZ2VtZW50X3BkZi8xOTk1L3ZvbHVtZSAzL1BhcnQgSS9TdGF0ZSBPZiBVLnAuIEFuZCBPcnMuIF8gQ29tbWl0aWVlIE9mIE1hbmFnZW1lbnQgT2YgUy5rLm0uIEludGVyIENvbGxlZ2UgQW5kIEFuci5fMTcwMTUwMTQ4NS5wZGY="
    },
    {
        "volume": "1995Volume 3",
        "Case Name": "R.MANICKA NAICKER ETC. VS. E. ELUMALAI NAICKER ETC.",
        "Case Link": "https://digiscr.sci.gov.in/view_judgment?id=MTI2OTg=",
        "Citation": "[1995] 3 S.C.R. 217",
        "Case Type": "(CIVIL APPEAL /111 and 112/1984)",
        "Date": "07 APRIL 1995",
        "Judge Names": "Hon'ble Mr. Justice S.C. Agrawal, Hon'ble Ms. Justice Sujata V Manohar\n*",
        "PDF Link": "https://digiscr.sci.gov.in/pdf_viewer?dir=YWRtaW4vanVkZ2VtZW50X2ZpbGUvanVkZ2VtZW50X3BkZi8xOTk1L3ZvbHVtZSAzL1BhcnQgSS9SLm1hbmlja2EgTmFpY2tlciBFdGMuIF8gRS4gRWx1bWFsYWkgTmFpY2tlciBFdGMuXzE3MDE1MDE3MTAucGRm"
    },
    {
        "volume": "1995Volume 3",
        "Case Name": "M/S KAJARIA EXPORTS LTD. AND ORS. VS. UNION OF INDIA AND ORS.",
        "Case Link": "https://digiscr.sci.gov.in/view_judgment?id=MTI3MDc=",
        "Citation": "[1995] 3 S.C.R. 227",
        "Case Type": "(CIVIL APPEAL /4922-23/1994)",
        "Date": "07 APRIL 1995",
        "Judge Names": "Hon'ble Mr. Justice S.C. Agrawal, Hon'ble Ms. Justice Sujata V Manohar\n*",
        "PDF Link": "https://digiscr.sci.gov.in/pdf_viewer?dir=YWRtaW4vanVkZ2VtZW50X2ZpbGUvanVkZ2VtZW50X3BkZi8xOTk1L3ZvbHVtZSAzL1BhcnQgSS8xOTk1XzNfMjI3IC0gMjMzXzE3MDMyMzk5NTkucGRm"
    },
    {
        "volume": "1995Volume 3",
        "Case Name": "DAHIBEN W/O RANCHHODJI JIVANJI AND ORS. ETC. VS. VASANJI KEVALBHAI (DEAD) AND ORS. ETC.",
        "Case Link": "https://digiscr.sci.gov.in/view_judgment?id=MTI3MTY=",
        "Citation": "[1995] 3 S.C.R. 234",
        "Case Type": "(CIVIL APPEAL /1578/1974)",
        "Date": "07 APRIL 1995",
        "Judge Names": "Hon'ble Mr. Justice B.L. Hansaria\n*, Hon'ble Mr. Justice K. Ramaswamy",
        "PDF Link": "https://digiscr.sci.gov.in/pdf_viewer?dir=YWRtaW4vanVkZ2VtZW50X2ZpbGUvanVkZ2VtZW50X3BkZi8xOTk1L3ZvbHVtZSAzL1BhcnQgSS8xOTk1XzNfMjM0IC0gMjQ1XzE3MDMyMzk5OTYucGRm"
    },
    {
        "volume": "1995Volume 3",
        "Case Name": "INDIAN OIL CORPORATION LTD. VS. MUNICIPAL CORPORATION AND ANR.",
        "Case Link": "https://digiscr.sci.gov.in/view_judgment?id=MTI3Mjk=",
        "Citation": "[1995] 3 S.C.R. 246",
        "Case Type": "(SPECIAL LEAVE PETITION (CIVIL) /7504/1995)",
        "Date": "07 APRIL 1995",
        "Judge Names": "Hon'ble Mr. Justice J.S. Verma, Hon'ble Ms. Justice Sujata V Manohar",
        "PDF Link": "https://digiscr.sci.gov.in/pdf_viewer?dir=YWRtaW4vanVkZ2VtZW50X2ZpbGUvanVkZ2VtZW50X3BkZi8xOTk1L3ZvbHVtZSAzL1BhcnQgSS9JbmRpYW4gT2lsIENvcnBvcmF0aW9uIEx0ZC4gXyBNdW5pY2lwYWwgQ29ycG9yYXRpb24gQW5kIEFuci5fMTcwMTUwMjM2MC5wZGY="
    },
    {
        "volume": "1995Volume 3",
        "Case Name": "PRASHANT RAMACHANDRA DESHPANDE VS. MARUTI BALARAM HAIBATTI",
        "Case Link": "https://digiscr.sci.gov.in/view_judgment?id=MTI3OTE=",
        "Citation": "[1995] 3 S.C.R. 254",
        "Case Type": "(CIVIL APPEAL /4587/1995)",
        "Date": "07 APRIL 1995",
        "Judge Names": "Hon'ble Mr. Justice R.M. Sahai, Hon'ble Mr. Justice N. Venkatachala",
        "PDF Link": "https://digiscr.sci.gov.in/pdf_viewer?dir=YWRtaW4vanVkZ2VtZW50X2ZpbGUvanVkZ2VtZW50X3BkZi8xOTk1L3ZvbHVtZSAzL1BhcnQgSS9QcmFzaGFudCBSYW1hY2hhbmRyYSBEZXNocGFuZGUgXyBNYXJ1dGkgQmFsYXJhbSBIYWliYXR0aV8xNzAxNjY1MzcxLnBkZg=="
    },
    {
        "volume": "1995Volume 3",
        "Case Name": "GOVERNMENT OF TAMIL NADU AND ANR. VS. VASANTHA BAI",
        "Case Link": "https://digiscr.sci.gov.in/view_judgment?id=MTI3OTQ=",
        "Citation": "[1995] 3 S.C.R. 258",
        "Case Type": "(CIVIL APPEAL /4608/1995)",
        "Date": "07 APRIL 1995",
        "Judge Names": "",
        "PDF Link": "https://digiscr.sci.gov.in/pdf_viewer?dir=YWRtaW4vanVkZ2VtZW50X2ZpbGUvanVkZ2VtZW50X3BkZi8xOTk1L3ZvbHVtZSAzL1BhcnQgSS9Hb3Zlcm5tZW50IE9mIFRhbWlsIE5hZHUgQW5kIEFuci4gXyBWYXNhbnRoYSBCYWlfMTcwMTY2NTUxMC5wZGY="
    },
    {
        "volume": "1995Volume 3",
        "Case Name": "MOHAN SINGH ETC VS. STATE OF PUNJAB AND ORS. ETC.",
        "Case Link": "https://digiscr.sci.gov.in/view_judgment?id=MTI3OTg=",
        "Citation": "[1995] 3 S.C.R. 264",
        "Case Type": "(CIVIL APPEAL /5205/1995)",
        "Date": "10 APRIL 1995",
        "Judge Names": "Hon'ble Mr. Justice K. Ramaswamy, Hon'ble Mr. Justice B.L. Hansaria",
        "PDF Link": "https://digiscr.sci.gov.in/pdf_viewer?dir=YWRtaW4vanVkZ2VtZW50X2ZpbGUvanVkZ2VtZW50X3BkZi8xOTk1L3ZvbHVtZSAzL1BhcnQgSS9Nb2hhbiBTaW5naCBFdGMgXyBTdGF0ZSBPZiBQdW5qYWIgQW5kIE9ycy4gRXRjLl8xNzAxNjY1Njc5LnBkZg=="
    },
    {
        "volume": "1995Volume 3",
        "Case Name": "SH. JAI KISHAN VS. COMMISSIONER OF POLICE AND ANR.",
        "Case Link": "https://digiscr.sci.gov.in/view_judgment?id=MTI4MDE=",
        "Citation": "[1995] 3 S.C.R. 268",
        "Case Type": "(CIVIL APPEAL /5210/1995)",
        "Date": "10 APRIL 1995",
        "Judge Names": "Hon'ble Mr. Justice K. Ramaswamy, Hon'ble Mr. Justice B.L. Hansaria",
        "PDF Link": "https://digiscr.sci.gov.in/pdf_viewer?dir=YWRtaW4vanVkZ2VtZW50X2ZpbGUvanVkZ2VtZW50X3BkZi8xOTk1L3ZvbHVtZSAzL1BhcnQgSS9TaC4gSmFpIEtpc2hhbiBfIENvbW1pc3Npb25lciBPZiBQb2xpY2UgQW5kIEFuci5fMTcwMTY2NTc5MS5wZGY="
    },
    {
        "volume": "1995Volume 3",
        "Case Name": "RAMBHAI LAKHANBAI BHAKT VS. STATE OF GUJARAT AND ORS.",
        "Case Link": "https://digiscr.sci.gov.in/view_judgment?id=MTI4MDc=",
        "Citation": "[1995] 3 S.C.R. 272",
        "Case Type": "(SPECIAL LEAVE PETITION (CIVIL) /378/1995)",
        "Date": "10 APRIL 1995",
        "Judge Names": "Hon'ble Mr. Justice K. Ramaswamy, Hon'ble Mr. Justice B.L. Hansaria",
        "PDF Link": "https://digiscr.sci.gov.in/pdf_viewer?dir=YWRtaW4vanVkZ2VtZW50X2ZpbGUvanVkZ2VtZW50X3BkZi8xOTk1L3ZvbHVtZSAzL1BhcnQgSS9SYW1iaGFpIExha2hhbmJhaSBCaGFrdCBfIFN0YXRlIE9mIEd1amFyYXQgQW5kIE9ycy5fMTcwMTY2NTkzNi5wZGY="
    },
    {
        "volume": "1995Volume 3",
        "Case Name": "KAMLESHKUMAR ISHWARDAS PATEL ETC. ETC. VS. UNION OF INDIA AND ORS. ETC. ETC.",
        "Case Link": "https://digiscr.sci.gov.in/view_judgment?id=MTI4MjA=",
        "Citation": "[1995] 3 S.C.R. 279",
        "Case Type": "(CRIMINAL APPEAL /764-65/1994)",
        "Date": "17 APRIL 1995",
        "Judge Names": "Hon'ble Mr. Justice A.M. Ahmadi, Hon'ble Mr. Justice S.P. Bharucha, Hon'ble Mr. Justice S.C. Agrawal\n*, Hon'ble Mr. Justice K.S. Paripoornan, Hon'ble Ms. Justice Sujata V Manohar",
        "PDF Link": "https://digiscr.sci.gov.in/pdf_viewer?dir=YWRtaW4vanVkZ2VtZW50X2ZpbGUvanVkZ2VtZW50X3BkZi8xOTk1L3ZvbHVtZSAzL1BhcnQgSS9LYW1sZXNoa3VtYXIgSXNod2FyZGFzIFBhdGVsIEV0Yy4gRXRjLiBfIFVuaW9uIE9mIEluZGlhIEFuZCBPcnMuIEV0Yy4gRXRjLl8xNzAxNjY2MjY0LnBkZg=="
    },
    {
        "volume": "1995Volume 3",
        "Case Name": "STATE OF RAJASTHAN AND ORS. VS. NOOR BANO ETC. ETC.",
        "Case Link": "https://digiscr.sci.gov.in/view_judgment?id=MTI4MjY=",
        "Citation": "[1995] 3 S.C.R. 309",
        "Case Type": "(CIVIL APPEAL /5167/1995)",
        "Date": "17 APRIL 1995",
        "Judge Names": "Hon'ble Mr. Justice K. Ramaswamy, Hon'ble Mr. Justice B.L. Hansaria\n*",
        "PDF Link": "https://digiscr.sci.gov.in/pdf_viewer?dir=YWRtaW4vanVkZ2VtZW50X2ZpbGUvanVkZ2VtZW50X3BkZi8xOTk1L3ZvbHVtZSAzL1BhcnQgSS9TdGF0ZSBPZiBSYWphc3RoYW4gQW5kIE9ycy4gXyBOb29yIEJhbm8gRXRjLiBFdGMuXzE3MDE2NjY0MjEucGRm"
    },
    {
        "volume": "1995Volume 3",
        "Case Name": "S.V.R. MUDALIAR (DEAD) BY LRS. AND ORS. VS. MRS. RAJABU F. BUHARI (DEAD) BY LRS. AND ORS.",
        "Case Link": "https://digiscr.sci.gov.in/view_judgment?id=MTI5Njg=",
        "Citation": "[1995] 3 S.C.R. 312",
        "Case Type": "(CIVIL APPEAL /224/1974)",
        "Date": "17 APRIL 1995",
        "Judge Names": "Hon'ble Mr. Justice B.L. Hansaria\n*, Hon'ble Mr. Justice K. Ramaswamy",
        "PDF Link": "https://digiscr.sci.gov.in/pdf_viewer?dir=YWRtaW4vanVkZ2VtZW50X2ZpbGUvanVkZ2VtZW50X3BkZi8xOTk1L3ZvbHVtZSAzL1BhcnQgSS9TLnYuci4gTXVkYWxpYXIgKGRlYWQpIEJ5IExycy4gQW5kIE9ycy4gXyBNcnMuIFJhamFidSBGLiBCdWhhcmkgKGRlYWQpIEJ5IExycy4gQW5kIE9ycy5fMTcwMTY2ODg3OS5wZGY="
    },
    {
        "volume": "1995Volume 3",
        "Case Name": "M.J. SIVANI AND ORS. VS. STATE OF KARNATAKA AND ORS.",
        "Case Link": "https://digiscr.sci.gov.in/view_judgment?id=MTI5ODA=",
        "Citation": "[1995] 3 S.C.R. 329",
        "Case Type": "(CIVIL APPEAL /4564/1995)",
        "Date": "17 APRIL 1995",
        "Judge Names": "Hon'ble Mr. Justice K. Ramaswamy\n*, Hon'ble Mr. Justice B.L. Hansaria",
        "PDF Link": "https://digiscr.sci.gov.in/pdf_viewer?dir=YWRtaW4vanVkZ2VtZW50X2ZpbGUvanVkZ2VtZW50X3BkZi8xOTk1L3ZvbHVtZSAzL1BhcnQgSS9NLmouIFNpdmFuaSBBbmQgT3JzLiBfIFN0YXRlIE9mIEthcm5hdGFrYSBBbmQgT3JzLl8xNzAxNjY5MDQ0LnBkZg=="
    },
    {
        "volume": "1995Volume 3",
        "Case Name": "WARDINGTON LYNGDOH AND ORS. VS. THE COLLECTOR, MAWKYRWAT",
        "Case Link": "https://digiscr.sci.gov.in/view_judgment?id=MTMwMDc=",
        "Citation": "[1995] 3 S.C.R. 354",
        "Case Type": "(SPECIAL LEAVE PETITION (CIVIL) /11083/1995)",
        "Date": "17 APRIL 1995",
        "Judge Names": "Hon'ble Mr. Justice K. Ramaswamy, Hon'ble Mr. Justice B.L. Hansaria",
        "PDF Link": "https://digiscr.sci.gov.in/pdf_viewer?dir=YWRtaW4vanVkZ2VtZW50X2ZpbGUvanVkZ2VtZW50X3BkZi8xOTk1L3ZvbHVtZSAzL1BhcnQgSS9XYXJkaW5ndG9uIEx5bmdkb2ggQW5kIE9ycy4gXyBUaGUgQ29sbGVjdG9yLCBNYXdreXJ3YXRfMTcwMTY2OTY2Ni5wZGY="
    },
    {
        "volume": "1995Volume 3",
        "Case Name": "BUTA SINGH (DEAD) BY L.RS. VS. UNION OF INDIA",
        "Case Link": "https://digiscr.sci.gov.in/view_judgment?id=MTMwMjQ=",
        "Citation": "[1995] 3 S.C.R. 359",
        "Case Type": "(CIVIL APPEAL /5285/1995)",
        "Date": "17 APRIL 1995",
        "Judge Names": "Hon'ble Mr. Justice B.L. Hansaria, Hon'ble Mr. Justice K. Ramaswamy",
        "PDF Link": "https://digiscr.sci.gov.in/pdf_viewer?dir=YWRtaW4vanVkZ2VtZW50X2ZpbGUvanVkZ2VtZW50X3BkZi8xOTk1L3ZvbHVtZSAzL1BhcnQgSS9CdXRhIFNpbmdoIChkZWFkKSBCeSBMLnJzLiBfIFVuaW9uIE9mIEluZGlhXzE3MDE2Njk5OTIucGRm"
    },
    {
        "volume": "1995Volume 3",
        "Case Name": "STATE OF MANIPUR AND ORS. VS. SMT. A. ONGBI MEMCHA DEVI AND ANR.",
        "Case Link": "https://digiscr.sci.gov.in/view_judgment?id=MTMwMzA=",
        "Citation": "[1995] 3 S.C.R. 367",
        "Case Type": "(CIVIL APPEAL /5710/1995)",
        "Date": "17 APRIL 1995",
        "Judge Names": "Hon'ble Mr. Justice K. Ramaswamy, Hon'ble Mr. Justice B.L. Hansaria",
        "PDF Link": "https://digiscr.sci.gov.in/pdf_viewer?dir=YWRtaW4vanVkZ2VtZW50X2ZpbGUvanVkZ2VtZW50X3BkZi8xOTk1L3ZvbHVtZSAzL1BhcnQgSS9TdGF0ZSBPZiBNYW5pcHVyIEFuZCBPcnMuIF8gU210LiBBLiBPbmdiaSBNZW1jaGEgRGV2aSBBbmQgQW5yLl8xNzAxNjcwMTEyLnBkZg=="
    },
    {
        "volume": "1995Volume 3",
        "Case Name": "MAHARASHTRA RAJYA SAHKARI SAKKAR KARKHANA SANGH LTD. ETC. ETC. VS. STATE OF MAHARASHTRA AND ORS. ETC. ETC.",
        "Case Link": "https://digiscr.sci.gov.in/view_judgment?id=MTMwNDU=",
        "Citation": "[1995] 3 S.C.R. 377",
        "Case Type": "(CIVIL APPEAL /522/1989)",
        "Date": "18 APRIL 1995",
        "Judge Names": "Hon'ble Mr. Justice R.M. Sahai\n*, Hon'ble Mr. Justice B.P. Jeevan Reddy, Hon'ble Mr. Justice S.C. Sen",
        "PDF Link": "https://digiscr.sci.gov.in/pdf_viewer?dir=YWRtaW4vanVkZ2VtZW50X2ZpbGUvanVkZ2VtZW50X3BkZi8xOTk1L3ZvbHVtZSAzL1BhcnQgSS9NYWhhcmFzaHRyYSBSYWp5YSBTYWhrYXJpIFNha2thciBLYXJraGFuYSBTYW5naCBMdGQuIEV0Yy4gRXRjLiBfIFN0YXRlIE9mIE1haGFyYXNodHJhIEFuZCBPcnMuIEV0Yy4gRXRjLl8xNzAxNjcwMzk1LnBkZg=="
    },
    {
        "volume": "1995Volume 3",
        "Case Name": "UNION OF INDIA AND ORS. VS. DR. DEVENDRA VIR SAHI",
        "Case Link": "https://digiscr.sci.gov.in/view_judgment?id=MTMwODc=",
        "Citation": "[1995] 3 S.C.R. 426",
        "Case Type": "(CIVIL APPEAL /4470/1995)",
        "Date": "18 APRIL 1995",
        "Judge Names": "Hon'ble Mr. Justice J.S. Verma, Hon'ble Ms. Justice Sujata V Manohar\n*",
        "PDF Link": "https://digiscr.sci.gov.in/pdf_viewer?dir=YWRtaW4vanVkZ2VtZW50X2ZpbGUvanVkZ2VtZW50X3BkZi8xOTk1L3ZvbHVtZSAzL1BhcnQgSS9VbmlvbiBPZiBJbmRpYSBBbmQgT3JzLiBfIERyLiBEZXZlbmRyYSBWaXIgU2FoaV8xNzAxNjcwOTYzLnBkZg=="
    },
    {
        "volume": "1995Volume 3",
        "Case Name": "DIRECTOR OF TRIBAL WELFARE GOVERNMENT OF ANDHRA PRADESH VS. LAVETI GIRI AND ANR",
        "Case Link": "https://digiscr.sci.gov.in/view_judgment?id=MTMxMDA=",
        "Citation": "[1995] 3 S.C.R. 430",
        "Case Type": "(CIVIL APPEAL /4545/1995)",
        "Date": "18 APRIL 1995",
        "Judge Names": "Hon'ble Mr. Justice K. Ramaswamy\n*, Hon'ble Mr. Justice N. Venkatachala",
        "PDF Link": "https://digiscr.sci.gov.in/pdf_viewer?dir=YWRtaW4vanVkZ2VtZW50X2ZpbGUvanVkZ2VtZW50X3BkZi8xOTk1L3ZvbHVtZSAzL1BhcnQgSS9EaXJlY3RvciBPZiBUcmliYWwgV2VsZmFyZSBHb3Zlcm5tZW50IE9mIEFuZGhyYSBQcmFkZXNoIF8gTGF2ZXRpIEdpcmkgQW5kIEFucl8xNzAxNjcxMTc5LnBkZg=="
    },
    {
        "volume": "1995Volume 3",
        "Case Name": "M/S. ANGILE INSULATIONS VS. M/S. DAVY ASHMORE INDIA LTD. AND ANR.",
        "Case Link": "https://digiscr.sci.gov.in/view_judgment?id=MTMxMTk=",
        "Citation": "[1995] 3 S.C.R. 443",
        "Case Type": "(CIVIL APPEAL /5185/1995)",
        "Date": "18 APRIL 1995",
        "Judge Names": "Hon'ble Mr. Justice B.L. Hansaria, Hon'ble Mr. Justice K. Ramaswamy",
        "PDF Link": "https://digiscr.sci.gov.in/pdf_viewer?dir=YWRtaW4vanVkZ2VtZW50X2ZpbGUvanVkZ2VtZW50X3BkZi8xOTk1L3ZvbHVtZSAzL1BhcnQgSS8xOTk1XzNfNDQzIC0gNDQ2XzE3MDMyNDAwODEucGRm"
    },
    {
        "volume": "1995Volume 3",
        "Case Name": "MADANAGOPAL VS. P.K.A. RAMACHANDRA MUDALIAR (DEAD) BY LRS. AND ORS.",
        "Case Link": "https://digiscr.sci.gov.in/view_judgment?id=MTMxMzE=",
        "Citation": "[1995] 3 S.C.R. 447",
        "Case Type": "(CIVIL APPEAL /2134-35/1979)",
        "Date": "18 APRIL 1995",
        "Judge Names": "Hon'ble Mr. Justice K. Ramaswamy, Hon'ble Mr. Justice B.L. Hansaria",
        "PDF Link": "https://digiscr.sci.gov.in/pdf_viewer?dir=YWRtaW4vanVkZ2VtZW50X2ZpbGUvanVkZ2VtZW50X3BkZi8xOTk1L3ZvbHVtZSAzL1BhcnQgSS9NYWRhbmFnb3BhbCBfIFAuay5hLiBSYW1hY2hhbmRyYSBNdWRhbGlhciAoZGVhZCkgQnkgTHJzLiBBbmQgT3JzLl8xNzAxNjcxNjgzLnBkZg=="
    },
    {
        "volume": "1995Volume 3",
        "Case Name": "IN RE: SANJIV DATTA AND ORS VS. IN RE: SANJIV DATTA AND ORS",
        "Case Link": "https://digiscr.sci.gov.in/view_judgment?id=MTMxNDI=",
        "Citation": "[1995] 3 S.C.R. 450",
        "Case Type": "(CONTEMPT PETITION (CIVIL) /101/1995)",
        "Date": "19 APRIL 1995",
        "Judge Names": "Hon'ble Mr. Justice P.B. Sawant\n*, Hon'ble Mr. Justice B.P. Jeevan Reddy",
        "PDF Link": "https://digiscr.sci.gov.in/pdf_viewer?dir=YWRtaW4vanVkZ2VtZW50X2ZpbGUvanVkZ2VtZW50X3BkZi8xOTk1L3ZvbHVtZSAzL1BhcnQgSS8xNzAxNjcxODM4LnBkZg=="
    },
    {
        "volume": "1995Volume 3",
        "Case Name": "A.K. KAUL AND ANR. VS. UNION OF INDIA",
        "Case Link": "https://digiscr.sci.gov.in/view_judgment?id=MTMxNzI=",
        "Citation": "[1995] 3 S.C.R. 469",
        "Case Type": "(CIVIL APPEAL /4495-96/1995)",
        "Date": "19 APRIL 1995",
        "Judge Names": "Hon'ble Mr. Justice S.C. Agrawal\n*, Hon'ble Mr. Justice Faizanuddin",
        "PDF Link": "https://digiscr.sci.gov.in/pdf_viewer?dir=YWRtaW4vanVkZ2VtZW50X2ZpbGUvanVkZ2VtZW50X3BkZi8xOTk1L3ZvbHVtZSAzL1BhcnQgSS9BLmsuIEthdWwgQW5kIEFuci4gXyBVbmlvbiBPZiBJbmRpYV8xNzAxNjcyMjEzLnBkZg=="
    },
    {
        "volume": "1995Volume 3",
        "Case Name": "UNION OF INDIA AND ORS. VS. INDIAN ALUMINIUM CO. LTD. AND ANR.",
        "Case Link": "https://digiscr.sci.gov.in/view_judgment?id=MTMzNTk=",
        "Citation": "[1995] 3 S.C.R. 497",
        "Case Type": "(CIVIL APPEAL /4676/1995)",
        "Date": "19 APRIL 1995",
        "Judge Names": "Hon'ble Mr. Justice A.M. Ahmadi",
        "PDF Link": "https://digiscr.sci.gov.in/pdf_viewer?dir=YWRtaW4vanVkZ2VtZW50X2ZpbGUvanVkZ2VtZW50X3BkZi8xOTk1L3ZvbHVtZSAzL1BhcnQgSS9VbmlvbiBPZiBJbmRpYSBBbmQgT3JzLiBfIEluZGlhbiBBbHVtaW5pdW0gQ28uIEx0ZC4gQW5kIEFuci5fMTcwMTY3OTUyNS5wZGY="
    },
    {
        "volume": "1995Volume 3",
        "Case Name": "RADHAKISAN RATHI VS. ADDITIONAL COLLECTOR, DURG AND ORS.",
        "Case Link": "https://digiscr.sci.gov.in/view_judgment?id=MTMzNjQ=",
        "Citation": "[1995] 3 S.C.R. 510",
        "Case Type": "(CIVIL APPEAL /597/1975)",
        "Date": "19 APRIL 1995",
        "Judge Names": "Hon'ble Mr. Justice P.B. Sawant, Hon'ble Mr. Justice S.B. Majmudar\n*",
        "PDF Link": "https://digiscr.sci.gov.in/pdf_viewer?dir=YWRtaW4vanVkZ2VtZW50X2ZpbGUvanVkZ2VtZW50X3BkZi8xOTk1L3ZvbHVtZSAzL1BhcnQgSS9SYWRoYWtpc2FuIFJhdGhpIF8gQWRkaXRpb25hbCBDb2xsZWN0b3IsIER1cmcgQW5kIE9ycy5fMTcwMTY3OTcxNS5wZGY="
    },
    {
        "volume": "1995Volume 3",
        "Case Name": "RAJANNA VS. UNION OF INDIA",
        "Case Link": "https://digiscr.sci.gov.in/view_judgment?id=MTMzNjk=",
        "Citation": "[1995] 3 S.C.R. 524",
        "Case Type": "(CIVIL APPEAL /4584/1995)",
        "Date": "19 APRIL 1995",
        "Judge Names": "Hon'ble Mr. Justice J.S. Verma\n*, Hon'ble Ms. Justice Sujata V Manohar",
        "PDF Link": "https://digiscr.sci.gov.in/pdf_viewer?dir=YWRtaW4vanVkZ2VtZW50X2ZpbGUvanVkZ2VtZW50X3BkZi8xOTk1L3ZvbHVtZSAzL1BhcnQgSS9SYWphbm5hIF8gVW5pb24gT2YgSW5kaWFfMTcwMTY3OTg4OC5wZGY="
    },
    {
        "volume": "1995Volume 3",
        "Case Name": "M/S. SHABI CONSTRUCTION COMPANY VS. CITY AND INDUSTRIAL DEVELOPMENT CORPORATION AND ANR.",
        "Case Link": "https://digiscr.sci.gov.in/view_judgment?id=MTMzNzQ=",
        "Citation": "[1995] 3 S.C.R. 534",
        "Case Type": "(CIVIL APPEAL /4487/1990)",
        "Date": "19 APRIL 1995",
        "Judge Names": "Hon'ble Mr. Justice Deepak Verma, Hon'ble Mr. Justice M.K. Mukherjee\n*, Hon'ble Mr. Justice N.P. Singh",
        "PDF Link": "https://digiscr.sci.gov.in/pdf_viewer?dir=YWRtaW4vanVkZ2VtZW50X2ZpbGUvanVkZ2VtZW50X3BkZi8xOTk1L3ZvbHVtZSAzL1BhcnQgSS8xOTk1XzNfNTM0IC0gNTQzXzE3MDMyNDAxNjYucGRm"
    },
    {
        "volume": "1995Volume 3",
        "Case Name": "M.T. PUTTALINGAPPA, MAJOR AND ORS. ETC. VS. STATE OF KARNATAKA AND ORS. ETC.",
        "Case Link": "https://digiscr.sci.gov.in/view_judgment?id=MTMzODE=",
        "Citation": "[1995] 3 S.C.R. 544",
        "Case Type": "(CIVIL APPEAL /1953-55/1989)",
        "Date": "19 APRIL 1995",
        "Judge Names": "Hon'ble Mr. Justice B.L. Hansaria, Hon'ble Mr. Justice R.M. Sahai",
        "PDF Link": "https://digiscr.sci.gov.in/pdf_viewer?dir=YWRtaW4vanVkZ2VtZW50X2ZpbGUvanVkZ2VtZW50X3BkZi8xOTk1L3ZvbHVtZSAzL1BhcnQgSS9NLnQuIFB1dHRhbGluZ2FwcGEsIE1ham9yIEFuZCBPcnMuIEV0Yy4gXyBTdGF0ZSBPZiBLYXJuYXRha2EgQW5kIE9ycy4gRXRjLl8xNzAxNjgwMjY4LnBkZg=="
    },
    {
        "volume": "1995Volume 3",
        "Case Name": "SH. GANESH NARYAN HEDGE VS. SH.S. BANGARAPPA AND ORS.",
        "Case Link": "https://digiscr.sci.gov.in/view_judgment?id=MTMzOTE=",
        "Citation": "[1995] 3 S.C.R. 549",
        "Case Type": "(CRIMINAL APPEAL /564/1995)",
        "Date": "20 APRIL 1995",
        "Judge Names": "Hon'ble Mr. Justice B.P. Jeevan Reddy\n*, Hon'ble Mr. Justice S.B. Majmudar",
        "PDF Link": "https://digiscr.sci.gov.in/pdf_viewer?dir=YWRtaW4vanVkZ2VtZW50X2ZpbGUvanVkZ2VtZW50X3BkZi8xOTk1L3ZvbHVtZSAzL1BhcnQgSS9TaC4gR2FuZXNoIE5hcnlhbiBIZWRnZSBfIFNoLnMuIEJhbmdhcmFwcGEgQW5kIE9ycy5fMTcwMTY4MDYwMC5wZGY="
    },
    {
        "volume": "1995Volume 3",
        "Case Name": "MISS RADHA BAI VS. THE UNION TERRITORY OF PONDICHERRY REPRESENTED BY ITS CHIEF SECRETARY AND ORS.",
        "Case Link": "https://digiscr.sci.gov.in/view_judgment?id=MTMzOTg=",
        "Citation": "[1995] 3 S.C.R. 561",
        "Case Type": "(CIVIL APPEAL /117/1986)",
        "Date": "20 APRIL 1995",
        "Judge Names": "Hon'ble Mr. Justice Kuldip Singh, Hon'ble Mr. Justice K.S. Paripoornan\n*",
        "PDF Link": "https://digiscr.sci.gov.in/pdf_viewer?dir=YWRtaW4vanVkZ2VtZW50X2ZpbGUvanVkZ2VtZW50X3BkZi8xOTk1L3ZvbHVtZSAzL1BhcnQgSS9NaXNzIFJhZGhhIEJhaSBfIFRoZSBVbmlvbiBUZXJyaXRvcnkgT2YgUG9uZGljaGVycnkgUmVwcmVzZW50ZWQgQnkgSXRzIENoaWVmIFNlY3JldGFyeSBBbmQgT3JzLl8xNzAxNjgwNzM5LnBkZg=="
    },
    {
        "volume": "1995Volume 3",
        "Case Name": "DR. RASHMI SRIVASTAVA AND DR. B.D. SRIVASTAVA AND ORS. VS. VIKRAM UNIVERSITY AND ORS.",
        "Case Link": "https://digiscr.sci.gov.in/view_judgment?id=MTM0MDM=",
        "Citation": "[1995] 3 S.C.R. 572",
        "Case Type": "(CIVIL APPEAL /6001/1994)",
        "Date": "30 APRIL 1995",
        "Judge Names": "Hon'ble Mr. Justice P.B. Sawant, Hon'ble Mr. Justice S.B. Majmudar\n*",
        "PDF Link": "https://digiscr.sci.gov.in/pdf_viewer?dir=YWRtaW4vanVkZ2VtZW50X2ZpbGUvanVkZ2VtZW50X3BkZi8xOTk1L3ZvbHVtZSAzL1BhcnQgSS9Eci4gUmFzaG1pIFNyaXZhc3RhdmEgQW5kIERyLiBCLmQuIFNyaXZhc3RhdmEgQW5kIE9ycy4gXyBWaWtyYW0gVW5pdmVyc2l0eSBBbmQgT3JzLl8xNzAxNjgwOTc3LnBkZg=="
    },
    {
        "volume": "1995Volume 3",
        "Case Name": "STATE OF ORISSA AND ORS. VS. MAHANADI COALFIELDS LTD. AND ORS.",
        "Case Link": "https://digiscr.sci.gov.in/view_judgment?id=MTM0NTY=",
        "Citation": "[1995] 3 S.C.R. 639",
        "Case Type": "(CIVIL APPEAL /330-604/1995)",
        "Date": "21 APRIL 1995",
        "Judge Names": "Hon'ble Mr. Justice A.M. Ahmadi, Hon'ble Mr. Justice S.P. Bharucha, Hon'ble Mr. Justice K.S. Paripoornan\n*",
        "PDF Link": "https://digiscr.sci.gov.in/pdf_viewer?dir=YWRtaW4vanVkZ2VtZW50X2ZpbGUvanVkZ2VtZW50X3BkZi8xOTk1L3ZvbHVtZSAzL1BhcnQgSS9TdGF0ZSBPZiBPcmlzc2EgQW5kIE9ycy4gXyBNYWhhbmFkaSBDb2FsZmllbGRzIEx0ZC4gQW5kIE9ycy5fMTcwMTY4MjgxMS5wZGY="
    },
    {
        "volume": "1995Volume 3",
        "Case Name": "TRUSTEES OF PORT OF MADRAS VS. M/S. NAGAVEDU LUNGI AND COMPANY AND ORS.",
        "Case Link": "https://digiscr.sci.gov.in/view_judgment?id=MTM0NzQ=",
        "Citation": "[1995] 3 S.C.R. 669",
        "Case Type": "(CIVIL APPEAL /1519/1982)",
        "Date": "21 APRIL 1995",
        "Judge Names": "Hon'ble Mr. Justice Kuldip Singh, Hon'ble Mr. Justice N. Venkatachala\n*, Hon'ble Mr. Justice S. Saghir Ahmad",
        "PDF Link": "https://digiscr.sci.gov.in/pdf_viewer?dir=YWRtaW4vanVkZ2VtZW50X2ZpbGUvanVkZ2VtZW50X3BkZi8xOTk1L3ZvbHVtZSAzL1BhcnQgSS8xOTk1XzNfNjY5IC0gNjcxIF8xNzAzMjQwMjMyLnBkZg=="
    },
    {
        "volume": "1995Volume 3",
        "Case Name": "S.B. SHAHANE AND ORS. VS. THE STATE OF MAHARASHTRA AND ANR.",
        "Case Link": "https://digiscr.sci.gov.in/view_judgment?id=MTM0ODU=",
        "Citation": "[1995] 3 S.C.R. 672",
        "Case Type": "(CIVIL APPEAL /676/1982)",
        "Date": "21 APRIL 1995",
        "Judge Names": "Hon'ble Mr. Justice Kuldip Singh, Hon'ble Mr. Justice N. Venkatachala\n*",
        "PDF Link": "https://digiscr.sci.gov.in/pdf_viewer?dir=YWRtaW4vanVkZ2VtZW50X2ZpbGUvanVkZ2VtZW50X3BkZi8xOTk1L3ZvbHVtZSAzL1BhcnQgSS9TLmIuIFNoYWhhbmUgQW5kIE9ycy4gXyBUaGUgU3RhdGUgT2YgTWFoYXJhc2h0cmEgQW5kIEFuci5fMTcwMTY4MzQyMi5wZGY="
    },
    {
        "volume": "1995Volume 3",
        "Case Name": "ORISSA STATE ELECTRICITY BOARD AND ANR. ETC. VS. M/S IPI STEEL LTD. ETC.",
        "Case Link": "https://digiscr.sci.gov.in/view_judgment?id=MTM0OTI=",
        "Citation": "[1995] 3 S.C.R. 684",
        "Case Type": "(CIVIL APPEAL /4689/1995)",
        "Date": "21 APRIL 1995",
        "Judge Names": "Hon'ble Mr. Justice B.P. Jeevan Reddy\n*, Hon'ble Mr. Justice S.C. Sen",
        "PDF Link": "https://digiscr.sci.gov.in/pdf_viewer?dir=YWRtaW4vanVkZ2VtZW50X2ZpbGUvanVkZ2VtZW50X3BkZi8xOTk1L3ZvbHVtZSAzL1BhcnQgSS8xOTk1XzNfNjg0IC0gNzExXzE3MDMyNDAzMzIucGRm"
    },
    {
        "volume": "1995Volume 3",
        "Case Name": "BURN STANDARD CO. LTD. AND ORS. VS. SH. DINABANDHU MAJUMDAR AND ANR.",
        "Case Link": "https://digiscr.sci.gov.in/view_judgment?id=MTM1Mzc=",
        "Citation": "[1995] 3 S.C.R. 712",
        "Case Type": "(CIVIL APPEAL /4725/1995)",
        "Date": "21 APRIL 1995",
        "Judge Names": "Hon'ble Mr. Justice A.M. Ahmadi, Hon'ble Mr. Justice N. Venkatachala\n*",
        "PDF Link": "https://digiscr.sci.gov.in/pdf_viewer?dir=YWRtaW4vanVkZ2VtZW50X2ZpbGUvanVkZ2VtZW50X3BkZi8xOTk1L3ZvbHVtZSAzL1BhcnQgSS9CdXJuIFN0YW5kYXJkIENvLiBMdGQuIEFuZCBPcnMuIF8gU2guIERpbmFiYW5kaHUgTWFqdW1kYXIgQW5kIEFuci5fMTcwMTY4NDk1MS5wZGY="
    },
    {
        "volume": "1995Volume 3",
        "Case Name": "BALRAM CHANDRA VS. STATE OF U.P.",
        "Case Link": "https://digiscr.sci.gov.in/view_judgment?id=MTM1NDA=",
        "Citation": "[1995] 3 S.C.R. 726",
        "Case Type": "(SPECIAL LEAVE PETITION (CIVIL) /9056/1995)",
        "Date": "24 APRIL 1995",
        "Judge Names": "Hon'ble Mr. Justice B.L. Hansaria, Hon'ble Mr. Justice K. Ramaswamy",
        "PDF Link": "https://digiscr.sci.gov.in/pdf_viewer?dir=YWRtaW4vanVkZ2VtZW50X2ZpbGUvanVkZ2VtZW50X3BkZi8xOTk1L3ZvbHVtZSAzL1BhcnQgSS9CYWxyYW0gQ2hhbmRyYSBfIFN0YXRlIE9mIFUucC5fMTcwMTY4NTA0OS5wZGY="
    },
    {
        "volume": "1995Volume 3",
        "Case Name": "U.P. AVAS EVAM VIKAS PARISHAD AND ANR. VS. FRIENDS COOPERATIVE HOUSING SOCIETY LTD. AND ANR.",
        "Case Link": "https://digiscr.sci.gov.in/view_judgment?id=MTM1NDc=",
        "Citation": "[1995] 3 S.C.R. 729",
        "Case Type": "(CIVIL APPEAL /5433/1995)",
        "Date": "24 APRIL 1995",
        "Judge Names": "Hon'ble Mr. Justice K. Ramaswamy, Hon'ble Mr. Justice B.L. Hansaria",
        "PDF Link": "https://digiscr.sci.gov.in/pdf_viewer?dir=YWRtaW4vanVkZ2VtZW50X2ZpbGUvanVkZ2VtZW50X3BkZi8xOTk1L3ZvbHVtZSAzL1BhcnQgSS9VLnAuIEF2YXMgRXZhbSBWaWthcyBQYXJpc2hhZCBBbmQgQW5yLiBfIEZyaWVuZHMgQ29vcGVyYXRpdmUgSG91c2luZyBTb2NpZXR5IEx0ZC4gQW5kIEFuci5fMTcwMTY4NTIzNC5wZGY="
    },
    {
        "volume": "1995Volume 3",
        "Case Name": "VINOD KUMAR SANGAL VS. UNION OF INDIA AND ORS.",
        "Case Link": "https://digiscr.sci.gov.in/view_judgment?id=MTM1NTQ=",
        "Citation": "[1995] 3 S.C.R. 734",
        "Case Type": "(CIVIL APPEAL /4721/1995)",
        "Date": "25 APRIL 1995",
        "Judge Names": "Hon'ble Mr. Justice S.C. Agrawal\n*, Hon'ble Mr. Justice S. Saghir Ahmad",
        "PDF Link": "https://digiscr.sci.gov.in/pdf_viewer?dir=YWRtaW4vanVkZ2VtZW50X2ZpbGUvanVkZ2VtZW50X3BkZi8xOTk1L3ZvbHVtZSAzL1BhcnQgSS9WaW5vZCBLdW1hciBTYW5nYWwgXyBVbmlvbiBPZiBJbmRpYSBBbmQgT3JzLl8xNzAxNjg1NDU1LnBkZg=="
    },
    {
        "volume": "1995Volume 3",
        "Case Name": "PREETI SINGH VS. SANDEEP SINGH AND ORS.",
        "Case Link": "https://digiscr.sci.gov.in/view_judgment?id=MTM1NjM=",
        "Citation": "[1995] 3 S.C.R. 743",
        "Case Type": "(CRIMINAL MISCELLANEOUS PETITION /1207/1992)",
        "Date": "25 APRIL 1995",
        "Judge Names": "Hon'ble Mr. Justice K. Ramaswamy, Hon'ble Mr. Justice B.L. Hansaria",
        "PDF Link": "https://digiscr.sci.gov.in/pdf_viewer?dir=YWRtaW4vanVkZ2VtZW50X2ZpbGUvanVkZ2VtZW50X3BkZi8xOTk1L3ZvbHVtZSAzL1BhcnQgSS9QcmVldGkgU2luZ2ggXyBTYW5kZWVwIFNpbmdoIEFuZCBPcnMuXzE3MDE2ODU2MjAucGRm"
    },
    {
        "volume": "1995Volume 3",
        "Case Name": "FAQIR (DEAD) THROUGH SHYAM DEO VS. KISHORI @ LALLOO AND ANR.",
        "Case Link": "https://digiscr.sci.gov.in/view_judgment?id=MTM1Nzg=",
        "Citation": "[1995] 3 S.C.R. 745",
        "Case Type": "(CIVIL APPEAL /1691/1987)",
        "Date": "25 APRIL 1995",
        "Judge Names": "Hon'ble Mr. Justice Kuldip Singh, Hon'ble Mr. Justice N. Venkatachala, Hon'ble Mr. Justice S. Saghir Ahmad\n*",
        "PDF Link": "https://digiscr.sci.gov.in/pdf_viewer?dir=YWRtaW4vanVkZ2VtZW50X2ZpbGUvanVkZ2VtZW50X3BkZi8xOTk1L3ZvbHVtZSAzL1BhcnQgSS8xOTk1XzNfNzQ1LTc1M18xNzA0NDMzOTY3LnBkZg=="
    },
    {
        "volume": "1995Volume 3",
        "Case Name": "STATE OF BIHAR AND ORS. VS. MOHD. IDRIS ANSARI",
        "Case Link": "https://digiscr.sci.gov.in/view_judgment?id=MzYzNzU=",
        "Citation": "[1995] 3 S.C.R. 754",
        "Case Type": "(CIVIL APPEAL /4970/1995)",
        "Date": "25 APRIL 1995",
        "Judge Names": "Hon'ble Mr. Justice B.P. Jeevan Reddy, Hon'ble Mr. Justice S.B. Majmudar\n*",
        "PDF Link": "https://digiscr.sci.gov.in/pdf_viewer?dir=YWRtaW4vanVkZ2VtZW50X2ZpbGUvanVkZ2VtZW50X3BkZi8xOTk1L3ZvbHVtZSAzL1BhcnQgSS8xOTk1XzNfNzU0LTc2NF8xNzA0MTc2OTM1LnBkZg=="
    },
    {
        "volume": "1995Volume 3",
        "Case Name": "MATHUNNI MATHAI VS. M/S. HINDUSTAN ORGANIC CHEMICALS LTD. AND ANR.",
        "Case Link": "https://digiscr.sci.gov.in/view_judgment?id=MTM1ODg=",
        "Citation": "[1995] 3 S.C.R. 765",
        "Case Type": "(CIVIL APPEAL /5117/1995)",
        "Date": "25 APRIL 1995",
        "Judge Names": "Hon'ble Mr. Justice N.P. Singh, Hon'ble Mr. Justice R.M. Sahai\n*",
        "PDF Link": "https://digiscr.sci.gov.in/pdf_viewer?dir=YWRtaW4vanVkZ2VtZW50X2ZpbGUvanVkZ2VtZW50X3BkZi8xOTk1L3ZvbHVtZSAzL1BhcnQgSS8xOTk1XzNfNzY1IC0gNzcyXzE3MDMyNDA0NTgucGRm"
    },
    {
        "volume": "1995Volume 3",
        "Case Name": "UNION OF INDIA AND ANR. VS. S.S. RANADE",
        "Case Link": "https://digiscr.sci.gov.in/view_judgment?id=MTM1OTI=",
        "Citation": "[1995] 3 S.C.R. 773",
        "Case Type": "(CIVIL APPEAL /5110/1995)",
        "Date": "25 APRIL 1995",
        "Judge Names": "Hon'ble Mr. Justice S.C. Agrawal",
        "PDF Link": "https://digiscr.sci.gov.in/pdf_viewer?dir=YWRtaW4vanVkZ2VtZW50X2ZpbGUvanVkZ2VtZW50X3BkZi8xOTk1L3ZvbHVtZSAzL1BhcnQgSS8xOTk1XzNfNzczLTc4NF8xNzA0NDM0MDk1LnBkZg=="
    },
    {
        "volume": "1995Volume 3",
        "Case Name": "THE REGIONAL EXECUTIVE, KERALA FISHERMEN`S WELFARE FUND BOARDS VS. M/S. FANCY FOOD AND ANR. ETC. ETC.",
        "Case Link": "https://digiscr.sci.gov.in/view_judgment?id=MTM1OTc=",
        "Citation": "[1995] 3 S.C.R. 785",
        "Case Type": "(CIVIL APPEAL /3058/1995)",
        "Date": "25 APRIL 1995",
        "Judge Names": "Hon'ble Mr. Justice R.M. Sahai\n*",
        "PDF Link": "https://digiscr.sci.gov.in/pdf_viewer?dir=YWRtaW4vanVkZ2VtZW50X2ZpbGUvanVkZ2VtZW50X3BkZi8xOTk1L3ZvbHVtZSAzL1BhcnQgSS8xOTk1XzNfNzg1IC0gNzk2XzE3MDMyNDA1MTYucGRm"
    },
    {
        "volume": "1995Volume 3",
        "Case Name": "TRILOCHAN LENKA AND ORS. STATE OF ORISSA AND ANR. VS. MANDI MOHAN SETHI AND ANR. DR. BISWA KALYANA PATTNAIK AND ORS.",
        "Case Link": "https://digiscr.sci.gov.in/view_judgment?id=MTM2MDI=",
        "Citation": "[1995] 3 S.C.R. 797",
        "Case Type": "(CIVIL APPEAL /1847/1989)",
        "Date": "26 APRIL 1995",
        "Judge Names": "Hon'ble Mr. Justice B.L. Hansaria\n*, Hon'ble Mr. Justice R.M. Sahai",
        "PDF Link": "https://digiscr.sci.gov.in/pdf_viewer?dir=YWRtaW4vanVkZ2VtZW50X2ZpbGUvanVkZ2VtZW50X3BkZi8xOTk1L3ZvbHVtZSAzL1BhcnQgSS9Ucmlsb2NoYW4gTGVua2EgQW5kIE9ycy4gU3RhdGUgT2YgT3Jpc3NhIEFuZCBBbnIuIF8gTWFuZGkgTW9oYW4gU2V0aGkgQW5kIEFuci4gRHIuIEJpc3dhIEthbHlhbmEgUGF0dG5haWsgQW5kIE9ycy5fMTcwMTY4NjUyMC5wZGY="
    },
    {
        "volume": "1995Volume 3",
        "Case Name": "SH. NARAYAN YESHWANT GORE VS. UNION OF INDIA AND ORS.",
        "Case Link": "https://digiscr.sci.gov.in/view_judgment?id=MTM2MDg=",
        "Citation": "[1995] 3 S.C.R. 803",
        "Case Type": "(CIVIL APPEAL /2896/1989)",
        "Date": "26 APRIL 1995",
        "Judge Names": "Hon'ble Mr. Justice R.M. Sahai, Hon'ble Ms. Justice Sujata V Manohar",
        "PDF Link": "https://digiscr.sci.gov.in/pdf_viewer?dir=YWRtaW4vanVkZ2VtZW50X2ZpbGUvanVkZ2VtZW50X3BkZi8xOTk1L3ZvbHVtZSAzL1BhcnQgSS9TaC4gTmFyYXlhbiBZZXNod2FudCBHb3JlIF8gVW5pb24gT2YgSW5kaWEgQW5kIE9ycy5fMTcwMTY4NjY3MS5wZGY="
    },
    {
        "volume": "1995Volume 3",
        "Case Name": "M/S HINDUSTAN LEVER LTD. VS. THE MUNICIPAL CORPORATION OF GREATER BOMBAY AND ORS.",
        "Case Link": "https://digiscr.sci.gov.in/view_judgment?id=MTM2MTQ=",
        "Citation": "[1995] 3 S.C.R. 807",
        "Case Type": "(CIVIL APPEAL /2312/1979)",
        "Date": "26 APRIL 1995",
        "Judge Names": "Hon'ble Mr. Justice K. Ramaswamy",
        "PDF Link": "https://digiscr.sci.gov.in/pdf_viewer?dir=YWRtaW4vanVkZ2VtZW50X2ZpbGUvanVkZ2VtZW50X3BkZi8xOTk1L3ZvbHVtZSAzL1BhcnQgSS8xOTk1XzNfODA3IC0gIDgxNl8xNzAzMjQwNzE2LnBkZg=="
    },
    {
        "volume": "1995Volume 3",
        "Case Name": "PARRIPATI CHANDRASEKHARRAO AND SONS VS. ALAPATI JALAIAH",
        "Case Link": "https://digiscr.sci.gov.in/view_judgment?id=MTM2MjE=",
        "Citation": "[1995] 3 S.C.R. 817",
        "Case Type": "(CIVIL APPEAL /5479-81/1993)",
        "Date": "26 APRIL 1995",
        "Judge Names": "Hon'ble Mr. Justice P.B. Sawant\n*, Hon'ble Mr. Justice S.B. Majmudar",
        "PDF Link": "https://digiscr.sci.gov.in/pdf_viewer?dir=YWRtaW4vanVkZ2VtZW50X2ZpbGUvanVkZ2VtZW50X3BkZi8xOTk1L3ZvbHVtZSAzL1BhcnQgSS9QYXJyaXBhdGkgQ2hhbmRyYXNla2hhcnJhbyBBbmQgU29ucyBfIEFsYXBhdGkgSmFsYWlhaF8xNzAxNjg2OTUwLnBkZg=="
    },
    {
        "volume": "1995Volume 3",
        "Case Name": "SHREEDHARAN KALLAT VS. THE UNION OF INDIA AND ORS.",
        "Case Link": "https://digiscr.sci.gov.in/view_judgment?id=MTM2Mjg=",
        "Citation": "[1995] 3 S.C.R. 828",
        "Case Type": "(CIVIL APPEAL /3565/1989)",
        "Date": "26 APRIL 1995",
        "Judge Names": "Hon'ble Mr. Justice R.M. Sahai, Hon'ble Ms. Justice Sujata V Manohar",
        "PDF Link": "https://digiscr.sci.gov.in/pdf_viewer?dir=YWRtaW4vanVkZ2VtZW50X2ZpbGUvanVkZ2VtZW50X3BkZi8xOTk1L3ZvbHVtZSAzL1BhcnQgSS9TaHJlZWRoYXJhbiBLYWxsYXQgXyBUaGUgVW5pb24gT2YgSW5kaWEgQW5kIE9ycy5fMTcwMTY4NzA1Ny5wZGY="
    },
    {
        "volume": "1995Volume 3",
        "Case Name": "SHYAM LAL (DEAD) BY LRS. AND ORS VS. KESHO LAL (DEAD) AND ANR.",
        "Case Link": "https://digiscr.sci.gov.in/view_judgment?id=MTM2MzM=",
        "Citation": "[1995] 3 S.C.R. 833",
        "Case Type": "(CIVIL APPEAL /1190/1977)",
        "Date": "26 APRIL 1995",
        "Judge Names": "Hon'ble Mr. Justice K. Ramaswamy, Hon'ble Mr. Justice B.L. Hansaria",
        "PDF Link": "https://digiscr.sci.gov.in/pdf_viewer?dir=YWRtaW4vanVkZ2VtZW50X2ZpbGUvanVkZ2VtZW50X3BkZi8xOTk1L3ZvbHVtZSAzL1BhcnQgSS9TaHlhbSBMYWwgKGRlYWQpIEJ5IExycy4gQW5kIE9ycyBfIEtlc2hvIExhbCAoZGVhZCkgQW5kIEFuci5fMTcwMTY4NzE2Ny5wZGY="
    },
    {
        "volume": "1995Volume 3",
        "Case Name": "RAM BHAJAN SINGH AND ORS. VS. MADHESHWAR SINGH (DEAD) BY LRS. AND ORS.",
        "Case Link": "https://digiscr.sci.gov.in/view_judgment?id=MTM2NTQ=",
        "Citation": "[1995] 3 S.C.R. 836",
        "Case Type": "(CIVIL APPEAL /2480/1979)",
        "Date": "26 APRIL 1995",
        "Judge Names": "Hon'ble Mr. Justice K. Ramaswamy, Hon'ble Mr. Justice B.L. Hansaria",
        "PDF Link": "https://digiscr.sci.gov.in/pdf_viewer?dir=YWRtaW4vanVkZ2VtZW50X2ZpbGUvanVkZ2VtZW50X3BkZi8xOTk1L3ZvbHVtZSAzL1BhcnQgSS9SYW0gQmhhamFuIFNpbmdoIEFuZCBPcnMuIF8gTWFkaGVzaHdhciBTaW5naCAoZGVhZCkgQnkgTHJzLiBBbmQgT3JzLl8xNzAxNjg3Mzg0LnBkZg=="
    },
    {
        "volume": "1995Volume 3",
        "Case Name": "M/S HINDUSTAN PETROLEUM CORPORATION LTD. VS. THE COLLECTOR OF CENTRAL EXCISE",
        "Case Link": "https://digiscr.sci.gov.in/view_judgment?id=MTM2NzM=",
        "Citation": "[1995] 3 S.C.R. 839",
        "Case Type": "(CIVIL APPEAL /971-72/1986)",
        "Date": "27 APRIL 1995",
        "Judge Names": "Hon'ble Mr. Justice R.M. Sahai, Hon'ble Mr. Justice S.B. Majmudar\n*",
        "PDF Link": "https://digiscr.sci.gov.in/pdf_viewer?dir=YWRtaW4vanVkZ2VtZW50X2ZpbGUvanVkZ2VtZW50X3BkZi8xOTk1L3ZvbHVtZSAzL1BhcnQgSS8xOTk1XzNfODM5IC0gODU0XzE3MDMyNDA4NDkucGRm"
    },
    {
        "volume": "1995Volume 3",
        "Case Name": "SUNIL KUMAR JAIN VS. KISHAN AND ORS.",
        "Case Link": "https://digiscr.sci.gov.in/view_judgment?id=MTM2ODA=",
        "Citation": "[1995] 3 S.C.R. 855",
        "Case Type": "(SPECIAL LEAVE PETITION (CIVIL) /9886/1987)",
        "Date": "27 APRIL 1995",
        "Judge Names": "Hon'ble Mr. Justice K. Ramaswamy, Hon'ble Mr. Justice B.L. Hansaria",
        "PDF Link": "https://digiscr.sci.gov.in/pdf_viewer?dir=YWRtaW4vanVkZ2VtZW50X2ZpbGUvanVkZ2VtZW50X3BkZi8xOTk1L3ZvbHVtZSAzL1BhcnQgSS9TdW5pbCBLdW1hciBKYWluIF8gS2lzaGFuIEFuZCBPcnMuXzE3MDE2ODc5OTAucGRm"
    },
    {
        "volume": "1995Volume 3",
        "Case Name": "STATE OF BIHAR VS. DHIRENDRA KUMAR AND ORS.",
        "Case Link": "https://digiscr.sci.gov.in/view_judgment?id=MTM2ODU=",
        "Citation": "[1995] 3 S.C.R. 857",
        "Case Type": "(CIVIL APPEAL /5753/1995)",
        "Date": "27 APRIL 1995",
        "Judge Names": "Hon'ble Mr. Justice K. Ramaswamy",
        "PDF Link": "https://digiscr.sci.gov.in/pdf_viewer?dir=YWRtaW4vanVkZ2VtZW50X2ZpbGUvanVkZ2VtZW50X3BkZi8xOTk1L3ZvbHVtZSAzL1BhcnQgSS9TdGF0ZSBPZiBCaWhhciBfIERoaXJlbmRyYSBLdW1hciBBbmQgT3JzLl8xNzAxNjg4MDk2LnBkZg=="
    },
    {
        "volume": "1995Volume 3",
        "Case Name": "LALITHA J. RAJ VS. AITHAPPA RAJ",
        "Case Link": "https://digiscr.sci.gov.in/view_judgment?id=MTM2ODk=",
        "Citation": "[1995] 3 S.C.R. 861",
        "Case Type": "(CIVIL APPEAL /5699/1995)",
        "Date": "27 APRIL 1995",
        "Judge Names": "Hon'ble Mr. Justice B.L. Hansaria, Hon'ble Mr. Justice K. Ramaswamy",
        "PDF Link": "https://digiscr.sci.gov.in/pdf_viewer?dir=YWRtaW4vanVkZ2VtZW50X2ZpbGUvanVkZ2VtZW50X3BkZi8xOTk1L3ZvbHVtZSAzL1BhcnQgSS8xOTk1XzNfODYxLTg2M18xNzA0NDM0MjIwLnBkZg=="
    },
    {
        "volume": "1995Volume 3",
        "Case Name": "AKHILESH HAJAM VS. THE STATE OF BIHAR",
        "Case Link": "https://digiscr.sci.gov.in/view_judgment?id=MTM3MDY=",
        "Citation": "[1995] 3 S.C.R. 864",
        "Case Type": "(CRIMINAL APPEAL /540/1987)",
        "Date": "28 APRIL 1995",
        "Judge Names": "Hon'ble Mr. Justice G.N. Ray, Hon'ble Mr. Justice Faizanuddin\n*",
        "PDF Link": "https://digiscr.sci.gov.in/pdf_viewer?dir=YWRtaW4vanVkZ2VtZW50X2ZpbGUvanVkZ2VtZW50X3BkZi8xOTk1L3ZvbHVtZSAzL1BhcnQgSS9Ba2hpbGVzaCBIYWphbSBfIFRoZSBTdGF0ZSBPZiBCaWhhcl8xNzAxNjg4Njk3LnBkZg=="
    },
    {
        "volume": "1995Volume 3",
        "Case Name": "J. RANGASWAMY VS. STATE OF ANDHRA PRADESH AND ORS.",
        "Case Link": "https://digiscr.sci.gov.in/view_judgment?id=MTM3MTE=",
        "Citation": "[1995] 3 S.C.R. 874",
        "Case Type": "(CONTEMPT PETITION (CIVIL) /211/1994)",
        "Date": "28 APRIL 1995",
        "Judge Names": "Hon'ble Mr. Justice B.P. Jeevan Reddy, Hon'ble Mr. Justice S.C. Sen",
        "PDF Link": "https://digiscr.sci.gov.in/pdf_viewer?dir=YWRtaW4vanVkZ2VtZW50X2ZpbGUvanVkZ2VtZW50X3BkZi8xOTk1L3ZvbHVtZSAzL1BhcnQgSS9KLiBSYW5nYXN3YW15IF8gU3RhdGUgT2YgQW5kaHJhIFByYWRlc2ggQW5kIE9ycy5fMTcwMTY4ODgyMS5wZGY="
    },
    {
        "volume": "1995Volume 3",
        "Case Name": "S.A. RASHEED VS. DIRECTOR OF MINES AND GEOLOGY AND ANOTHER",
        "Case Link": "https://digiscr.sci.gov.in/view_judgment?id=MTM3MTQ=",
        "Citation": "[1995] 3 S.C.R. 883",
        "Case Type": "(CIVIL APPEAL /5278/1995)",
        "Date": "28 APRIL 1995",
        "Judge Names": "Hon'ble Mr. Justice B.P. Jeevan Reddy\n*, Hon'ble Mr. Justice S.C. Sen",
        "PDF Link": "https://digiscr.sci.gov.in/pdf_viewer?dir=YWRtaW4vanVkZ2VtZW50X2ZpbGUvanVkZ2VtZW50X3BkZi8xOTk1L3ZvbHVtZSAzL1BhcnQgSS9TLmEuIFJhc2hlZWQgXyBEaXJlY3RvciBPZiBNaW5lcyBBbmQgR2VvbG9neSBBbmQgQW5vdGhlcl8xNzAxNjg5MDI4LnBkZg=="
    },
    {
        "volume": "1995Volume 3",
        "Case Name": "GOSAR FAMILY TRUST, JAMNAGAR ETC. VS. COMMISSIONER OF INCOME TAX",
        "Case Link": "https://digiscr.sci.gov.in/view_judgment?id=MTM3MTk=",
        "Citation": "[1995] 3 S.C.R. 894",
        "Case Type": "(CIVIL APPEAL /1180/1991)",
        "Date": "28 APRIL 1995",
        "Judge Names": "Hon'ble Mr. Justice B.P. Jeevan Reddy\n*, Hon'ble Mr. Justice S.C. Sen, Hon'ble Mr. Justice G.T. Nanavati",
        "PDF Link": "https://digiscr.sci.gov.in/pdf_viewer?dir=YWRtaW4vanVkZ2VtZW50X2ZpbGUvanVkZ2VtZW50X3BkZi8xOTk1L3ZvbHVtZSAzL1BhcnQgSS9Hb3NhciBGYW1pbHkgVHJ1c3QsIEphbW5hZ2FyIEV0Yy4gXyBDb21taXNzaW9uZXIgT2YgSW5jb21lIFRheF8xNzAxNjg5MTQ3LnBkZg=="
    },
    {
        "volume": "1995Volume 3",
        "Case Name": "UNION OF INDIA VS. THAMISHARASI AND ORS.",
        "Case Link": "https://digiscr.sci.gov.in/view_judgment?id=MTM3MjQ=",
        "Citation": "[1995] 3 S.C.R. 905",
        "Case Type": "(CRIMINAL APPEAL /611-612/1995)",
        "Date": "01 MAY 1995",
        "Judge Names": "Hon'ble Mr. Justice J.S. Verma\n*, Hon'ble Ms. Justice Sujata V Manohar",
        "PDF Link": "https://digiscr.sci.gov.in/pdf_viewer?dir=YWRtaW4vanVkZ2VtZW50X2ZpbGUvanVkZ2VtZW50X3BkZi8xOTk1L3ZvbHVtZSAzL1BhcnQgSS9VbmlvbiBPZiBJbmRpYSBfIFRoYW1pc2hhcmFzaSBBbmQgT3JzLl8xNzAxNjg5MzAwLnBkZg=="
    },
    {
        "volume": "1995Volume 3",
        "Case Name": "MAHARASHTRA RAJYA MATHADI TRANSPORT AND CENTRAL KAMGAR UNION VS. STATE OF MAHARASHTRA AND ORS.",
        "Case Link": "https://digiscr.sci.gov.in/view_judgment?id=MTM3NzE=",
        "Citation": "[1995] 3 S.C.R. 920",
        "Case Type": "(CIVIL APPEAL /7415/1994)",
        "Date": "01 MAY 1995",
        "Judge Names": "Hon'ble Mr. Justice Kuldip Singh, Hon'ble Mr. Justice N. Venkatachala\n*, Hon'ble Mr. Justice S. Saghir Ahmad",
        "PDF Link": "https://digiscr.sci.gov.in/pdf_viewer?dir=YWRtaW4vanVkZ2VtZW50X2ZpbGUvanVkZ2VtZW50X3BkZi8xOTk1L3ZvbHVtZSAzL1BhcnQgSS9NYWhhcmFzaHRyYSBSYWp5YSBNYXRoYWRpIFRyYW5zcG9ydCBBbmQgQ2VudHJhbCBLYW1nYXIgVW5pb24gXyBTdGF0ZSBPZiBNYWhhcmFzaHRyYSBBbmQgT3JzLl8xNzAxNjkxMjIyLnBkZg=="
    },
    {
        "volume": "1995Volume 3",
        "Case Name": "SRI R.N.A. BRITTO VS. THE CHIEF EXECUTIVE OFFICER AND ORS.",
        "Case Link": "https://digiscr.sci.gov.in/view_judgment?id=MTM3Nzg=",
        "Citation": "[1995] 3 S.C.R. 932",
        "Case Type": "(CIVIL APPEAL /718/1993)",
        "Date": "01 MAY 1995",
        "Judge Names": "Hon'ble Mr. Justice Kuldip Singh, Hon'ble Mr. Justice N. Venkatachala\n*",
        "PDF Link": "https://digiscr.sci.gov.in/pdf_viewer?dir=YWRtaW4vanVkZ2VtZW50X2ZpbGUvanVkZ2VtZW50X3BkZi8xOTk1L3ZvbHVtZSAzL1BhcnQgSS9TcmkgUi5uLmEuIEJyaXRpbyBfIFRoZSBDaGllZiBFeGVjdXRpdmUgT2ZmaWNlciBBbmQgT3JzLl8xNzAxNjkxNDg5LnBkZg=="
    },
    {
        "volume": "1995Volume 3",
        "Case Name": "CITIZENS FOR DEMOCRACY VS. THE STATE OF ASSAM AND ORS.",
        "Case Link": "https://digiscr.sci.gov.in/view_judgment?id=MTY4NTc=",
        "Citation": "[1995] 3 S.C.R. 943",
        "Case Type": "(WRIT PETITION (CIVIL) /22/1995)",
        "Date": "01 MAY 1995",
        "Judge Names": "Hon'ble Mr. Justice Kuldip Singh\n*, Hon'ble Mr. Justice N. Venkatachala",
        "PDF Link": "https://digiscr.sci.gov.in/pdf_viewer?dir=YWRtaW4vanVkZ2VtZW50X2ZpbGUvanVkZ2VtZW50X3BkZi8xOTk1L3ZvbHVtZSAzL1BhcnQgSS9DaXRpemVucyBGb3IgRGVtb2NyYWN5ICB2cyAgVGhlIFN0YXRlIE9mIEFzc2FtIEFuZCBPcnMxNzAxOTI0NDE1LnBkZg=="
    },
    {
        "volume": "1995Volume 3",
        "Case Name": "VIDYAWATI VS. MAN MOHAN AND OTHERS",
        "Case Link": "https://digiscr.sci.gov.in/view_judgment?id=MTY4Njg=",
        "Citation": "[1995] 3 S.C.R. 956",
        "Case Type": "(SPECIAL LEAVE PETITION (CIVIL) /9356/1995)",
        "Date": "01 MAY 1995",
        "Judge Names": "Hon'ble Mr. Justice K. Ramaswamy",
        "PDF Link": "https://digiscr.sci.gov.in/pdf_viewer?dir=YWRtaW4vanVkZ2VtZW50X2ZpbGUvanVkZ2VtZW50X3BkZi8xOTk1L3ZvbHVtZSAzL1BhcnQgSS9WaWR5YXdhdGkgIHZzICBNYW4gTW9oYW4gQW5kIE90aGVyczE3MDE5MjQ1NjIucGRm"
    },
    {
        "volume": "1995Volume 3",
        "Case Name": "K. RAHEJA CONSTRUCTIONS LTD. AND ANR. VS. ALLIANCE MINISTRIES AND ORS.",
        "Case Link": "https://digiscr.sci.gov.in/view_judgment?id=MTY4Nzg=",
        "Citation": "[1995] 3 S.C.R. 960",
        "Case Type": "(SPECIAL LEAVE PETITION (CIVIL) /9397/1995)",
        "Date": "01 MAY 1995",
        "Judge Names": "Hon'ble Mr. Justice K. Ramaswamy",
        "PDF Link": "https://digiscr.sci.gov.in/pdf_viewer?dir=YWRtaW4vanVkZ2VtZW50X2ZpbGUvanVkZ2VtZW50X3BkZi8xOTk1L3ZvbHVtZSAzL1BhcnQgSS8xOTk1XzNfOTYwIC0gOTYzXzE3MDMyNDA5MDEucGRm"
    },
    {
        "volume": "1995Volume 3",
        "Case Name": "DHANANJAY SHARMA VS. STATE OF HARYANA AND ORS.",
        "Case Link": "https://digiscr.sci.gov.in/view_judgment?id=MTY4ODQ=",
        "Citation": "[1995] 3 S.C.R. 964",
        "Case Type": "(WRIT PETITION(CRIMINAL) /15/1994)",
        "Date": "02 MAY 1995",
        "Judge Names": "Hon'ble Dr. Justice A.S. Anand\n*, Hon'ble Mr. Justice Faizanuddin",
        "PDF Link": "https://digiscr.sci.gov.in/pdf_viewer?dir=YWRtaW4vanVkZ2VtZW50X2ZpbGUvanVkZ2VtZW50X3BkZi8xOTk1L3ZvbHVtZSAzL1BhcnQgSS9EaGFuYW5qYXkgU2hhcm1hICB2cyAgU3RhdGUgT2YgSGFyeWFuYSBBbmQgT3JzMTcwMTkyNDgyOS5wZGY="
    },
    {
        "volume": "1995Volume 3",
        "Case Name": "U.P. STATE SUGAR CORPN. LTD VS. U.P. STATE SUGAR CORPN. KARAMCHARI ASSO. AND ORS",
        "Case Link": "https://digiscr.sci.gov.in/view_judgment?id=MTY4ODk=",
        "Citation": "[1995] 3 S.C.R. 1004",
        "Case Type": "(CIVIL APPEAL /817/1995)",
        "Date": "02 MAY 1995",
        "Judge Names": "Hon'ble Mr. Justice S.C. Agrawal\n*, Hon'ble Ms. Justice Sujata V Manohar",
        "PDF Link": "https://digiscr.sci.gov.in/pdf_viewer?dir=YWRtaW4vanVkZ2VtZW50X2ZpbGUvanVkZ2VtZW50X3BkZi8xOTk1L3ZvbHVtZSAzL1BhcnQgSS8xOTk1XzNfMTAwNCAtIDEwMzZfMTcwMzI0MDk4MC5wZGY="
    },
    {
        "volume": "1995Volume 3",
        "Case Name": "M/S. RAJA RADIO CO., BOMBAY VS. COLLECTOR OF CUSTOMS, BOMBAY",
        "Case Link": "https://digiscr.sci.gov.in/view_judgment?id=MTY5MTI=",
        "Citation": "[1995] 3 S.C.R. 1037",
        "Case Type": "(CIVIL APPEAL /32-39/1986)",
        "Date": "02 MAY 1995",
        "Judge Names": "Hon'ble Mr. Justice R.M. Sahai\n*, Hon'ble Mr. Justice S.B. Majmudar, Hon'ble Ms. Justice Sujata V Manohar",
        "PDF Link": "https://digiscr.sci.gov.in/pdf_viewer?dir=YWRtaW4vanVkZ2VtZW50X2ZpbGUvanVkZ2VtZW50X3BkZi8xOTk1L3ZvbHVtZSAzL1BhcnQgSS9NcyBSYWphIFJhZGlvIENvIEJvbWJheSAgdnMgIENvbGxlY3RvciBPZiBDdXN0b21zIEJvbWJheTE3MDE5MjUzMDUucGRm"
    },
    {
        "volume": "1995Volume 3",
        "Case Name": "LORD LINGARAJ BIJE, BHUBANESWAR AND ANR. VS. SH. NITYANANDA MISHRA AND ORS.",
        "Case Link": "https://digiscr.sci.gov.in/view_judgment?id=MTY5MzE=",
        "Citation": "[1995] 3 S.C.R. 1046",
        "Case Type": "(CIVIL APPEAL /5256/1995)",
        "Date": "02 MAY 1995",
        "Judge Names": "Hon'ble Mr. Justice G.T. Nanavati, Hon'ble Mr. Justice R.M. Sahai\n*",
        "PDF Link": "https://digiscr.sci.gov.in/pdf_viewer?dir=YWRtaW4vanVkZ2VtZW50X2ZpbGUvanVkZ2VtZW50X3BkZi8xOTk1L3ZvbHVtZSAzL1BhcnQgSS9Mb3JkIExpbmdhcmFqIEJpamUgQmh1YmFuZXN3YXIgQW5kIEFuciAgdnMgIFNoIE5pdHlhbmFuZGEgTWlzaHJhIEFuZCBPcnMxNzAxOTI1NTc2LnBkZg=="
    },
    {
        "volume": "1995Volume 3",
        "Case Name": "COLLECTOR OF CENTRAL EXCISE, CHANDIGARH VS. M/S. STEEL STRIPS LTD. SANGRUR",
        "Case Link": "https://digiscr.sci.gov.in/view_judgment?id=MTY5NDQ=",
        "Citation": "[1995] 3 S.C.R. 1051",
        "Case Type": "(CIVIL APPEAL /438/1989)",
        "Date": "02 MAY 1995",
        "Judge Names": "Hon'ble Mr. Justice A.M. Ahmadi, Hon'ble Mr. Justice S.P. Bharucha\n*, Hon'ble Mr. Justice K.S. Paripoornan",
        "PDF Link": "https://digiscr.sci.gov.in/pdf_viewer?dir=YWRtaW4vanVkZ2VtZW50X2ZpbGUvanVkZ2VtZW50X3BkZi8xOTk1L3ZvbHVtZSAzL1BhcnQgSS9Db2xsZWN0b3IgT2YgQ2VudHJhbCBFeGNpc2UgQ2hhbmRpZ2FyaCAgdnMgIE1zIFN0ZWVsIFN0cmlwcyBMdGQgU2FuZ3J1cjE3MDE5MjU4MDgucGRm"
    },
    {
        "volume": "1995Volume 3",
        "Case Name": "PADMAVATHY AMMA VS. AMMUNNI PANICKER AND ANR.",
        "Case Link": "https://digiscr.sci.gov.in/view_judgment?id=MTY5NTc=",
        "Citation": "[1995] 3 S.C.R. 1056",
        "Case Type": "(CIVIL APPEAL /5259/1995)",
        "Date": "02 MAY 1995",
        "Judge Names": "Hon'ble Mr. Justice R.M. Sahai, Hon'ble Mr. Justice B.L. Hansaria\n*",
        "PDF Link": "https://digiscr.sci.gov.in/pdf_viewer?dir=YWRtaW4vanVkZ2VtZW50X2ZpbGUvanVkZ2VtZW50X3BkZi8xOTk1L3ZvbHVtZSAzL1BhcnQgSS9QYWRtYXZhdGh5IEFtbWEgIHZzICBBbW11bm5pIFBhbmlja2VyIEFuZCBBbnIxNzAxOTI1OTczLnBkZg=="
    },
    {
        "volume": "1995Volume 3",
        "Case Name": "PT. RISHIKESH AND ANR. ETC. VS. SMT. SALMA BEGUM ETC. ETC.",
        "Case Link": "https://digiscr.sci.gov.in/view_judgment?id=MTY5NzA=",
        "Citation": "[1995] 3 S.C.R. 1062",
        "Case Type": "(CIVIL APPEAL /1266/1979)",
        "Date": "02 MAY 1995",
        "Judge Names": "Hon'ble Mr. Justice K. Ramaswamy\n*, Hon'ble Mr. Justice N. Venkatachala, Hon'ble Mr. Justice S. Saghir Ahmad",
        "PDF Link": "https://digiscr.sci.gov.in/pdf_viewer?dir=YWRtaW4vanVkZ2VtZW50X2ZpbGUvanVkZ2VtZW50X3BkZi8xOTk1L3ZvbHVtZSAzL1BhcnQgSS9QdCBSaXNoaWtlc2ggQW5kIEFuciBFdGMgIHZzICBTbXQgU2FsbWEgQmVndW0gRXRjIEV0YzE3MDE5MjYxNTgucGRm"
    },
    {
        "volume": "1995Volume 3",
        "Case Name": "COMMISSIONER OF INCOME TAX, JULLUNDUR VS. AJANTA ELECTRICALS, PUNJAB",
        "Case Link": "https://digiscr.sci.gov.in/view_judgment?id=MTY5OTA=",
        "Citation": "[1995] 3 S.C.R. 1083",
        "Case Type": "(CIVIL APPEAL /2636/1977)",
        "Date": "02 MAY 1995",
        "Judge Names": "Hon'ble Mr. Justice B.P. Jeevan Reddy, Hon'ble Mr. Justice G.T. Nanavati\n*",
        "PDF Link": "https://digiscr.sci.gov.in/pdf_viewer?dir=YWRtaW4vanVkZ2VtZW50X2ZpbGUvanVkZ2VtZW50X3BkZi8xOTk1L3ZvbHVtZSAzL1BhcnQgSS8xOTk1XzNfMTA4My0xMDkyXzE3MDQ0MzQ0OTcucGRm"
    },
    {
        "volume": "1995Volume 3",
        "Case Name": "RAGHUBAR DAYAL (DEAD) VS. STATE OF U.P. AND ORS.",
        "Case Link": "https://digiscr.sci.gov.in/view_judgment?id=MTcwMTQ=",
        "Citation": "[1995] 3 S.C.R. 1093",
        "Case Type": "(CIVIL APPEAL /3012/1979)",
        "Date": "02 MAY 1995",
        "Judge Names": "Hon'ble Mr. Justice B.L. Hansaria, Hon'ble Mr. Justice K. Ramaswamy",
        "PDF Link": "https://digiscr.sci.gov.in/pdf_viewer?dir=YWRtaW4vanVkZ2VtZW50X2ZpbGUvanVkZ2VtZW50X3BkZi8xOTk1L3ZvbHVtZSAzL1BhcnQgSS8xOTk1XzNfMTA5MyAtIDEwOTlfMTcwMzI0MTA4My5wZGY="
    },
    {
        "volume": "1995Volume 3",
        "Case Name": "INDORE DEVELOPMENT AUTHORITY VS. TARAK SINGH AND ORS. ETC. ETC.",
        "Case Link": "https://digiscr.sci.gov.in/view_judgment?id=MTcwMjM=",
        "Citation": "[1995] 3 S.C.R. 1100",
        "Case Type": "(CIVIL APPEAL /5645-46/1995)",
        "Date": "01 MAY 1995",
        "Judge Names": "Hon'ble Mr. Justice K. Ramaswamy, Hon'ble Mr. Justice B.L. Hansaria",
        "PDF Link": "https://digiscr.sci.gov.in/pdf_viewer?dir=YWRtaW4vanVkZ2VtZW50X2ZpbGUvanVkZ2VtZW50X3BkZi8xOTk1L3ZvbHVtZSAzL1BhcnQgSS9JbmRvcmUgRGV2ZWxvcG1lbnQgQXV0aG9yaXR5ICB2cyAgVGFyYWsgU2luZ2ggQW5kIE9ycyBFdGMgRXRjMTcwMTkyNjczNS5wZGY="
    },
    {
        "volume": "1995Volume 3",
        "Case Name": "ARJUNA AND ORS. VS. STATE OF MAHARASHTRA AND ORS.",
        "Case Link": "https://digiscr.sci.gov.in/view_judgment?id=MTcwMzU=",
        "Citation": "[1995] 3 S.C.R. 1105",
        "Case Type": "(CIVIL APPEAL /2446/1978)",
        "Date": "02 MAY 1995",
        "Judge Names": "Hon'ble Mr. Justice K. Ramaswamy, Hon'ble Mr. Justice B.L. Hansaria",
        "PDF Link": "https://digiscr.sci.gov.in/pdf_viewer?dir=YWRtaW4vanVkZ2VtZW50X2ZpbGUvanVkZ2VtZW50X3BkZi8xOTk1L3ZvbHVtZSAzL1BhcnQgSS9Bcmp1bmEgQW5kIE9ycyAgdnMgIFN0YXRlIE9mIE1haGFyYXNodHJhIEFuZCBPcnMxNzAxOTI2ODMyLnBkZg=="
    },
    {
        "volume": "1995Volume 3",
        "Case Name": "VIJAY PAL SINGH AND ANR. VS. DY. DIRECTOR OF CONSOLIDATION AND ORS.",
        "Case Link": "https://digiscr.sci.gov.in/view_judgment?id=MTcwNDQ=",
        "Citation": "[1995] 3 S.C.R. 1107",
        "Case Type": "(CIVIL APPEAL /991-93/1979)",
        "Date": "02 MAY 1995",
        "Judge Names": "Hon'ble Mr. Justice K. Ramaswamy, Hon'ble Mr. Justice B.L. Hansaria",
        "PDF Link": "https://digiscr.sci.gov.in/pdf_viewer?dir=YWRtaW4vanVkZ2VtZW50X2ZpbGUvanVkZ2VtZW50X3BkZi8xOTk1L3ZvbHVtZSAzL1BhcnQgSS9WaWpheSBQYWwgU2luZ2ggQW5kIEFuciAgdnMgIER5IERpcmVjdG9yIE9mIENvbnNvbGlkYXRpb24gQW5kIE9yczE3MDE5MjY5NTIucGRm"
    },
    {
        "volume": "1995Volume 3",
        "Case Name": "U.P. AVAS EVAM VIKAS PARISHAD AND ANR. VS. RAVI KUMAR ANAND AND ORS.",
        "Case Link": "https://digiscr.sci.gov.in/view_judgment?id=MTcwNTY=",
        "Citation": "[1995] 3 S.C.R. 1112",
        "Case Type": "(CIVIL APPEAL /5713/1995)",
        "Date": "02 MAY 1995",
        "Judge Names": "Hon'ble Mr. Justice R.M. Sahai, Hon'ble Ms. Justice Sujata V Manohar",
        "PDF Link": "https://digiscr.sci.gov.in/pdf_viewer?dir=YWRtaW4vanVkZ2VtZW50X2ZpbGUvanVkZ2VtZW50X3BkZi8xOTk1L3ZvbHVtZSAzL1BhcnQgSS9VcCBBdmFzIEV2YW0gVmlrYXMgUGFyaXNoYWQgQW5kIEFuciAgdnMgIFJhdmkgS3VtYXIgQW5hbmQgQW5kIE9yczE3MDE5MjcxMjQucGRm"
    },
    {
        "volume": "1995Volume 3",
        "Case Name": "RAJASTHAN STATE ROAD TRANSPORT CORPORATION AND ANR. ETC. VS. KRISHNA KANT ETC. ETC.",
        "Case Link": "https://digiscr.sci.gov.in/view_judgment?id=MTcwNzE=",
        "Citation": "[1995] 3 S.C.R. 1118",
        "Case Type": "(CIVIL APPEAL /3100/1991)",
        "Date": "03 MAY 1995",
        "Judge Names": "Hon'ble Mr. Justice B.P. Jeevan Reddy\n*, Hon'ble Mr. Justice G.T. Nanavati, Hon'ble Mr. Justice S.C. Sen",
        "PDF Link": "https://digiscr.sci.gov.in/pdf_viewer?dir=YWRtaW4vanVkZ2VtZW50X2ZpbGUvanVkZ2VtZW50X3BkZi8xOTk1L3ZvbHVtZSAzL1BhcnQgSS9SYWphc3RoYW4gU3RhdGUgUm9hZCBUcmFuc3BvcnQgQ29ycG9yYXRpb24gQW5kIEFuciBFdGMgIHZzICBLcmlzaG5hIEthbnQgRXRjIEV0YzE3MDE5MjcyNjEucGRm"
    },
    {
        "volume": "1995Volume 3",
        "Case Name": "THE GOVT. OF INDIA AND ORS. ETC. VS. THE MADRAS RUBBER FACTORY LTD. ETC.",
        "Case Link": "https://digiscr.sci.gov.in/view_judgment?id=MTcwODM=",
        "Citation": "[1995] 3 S.C.R. 1143",
        "Case Type": "(CIVIL APPEAL /3195/1979)",
        "Date": "03 MAY 1995",
        "Judge Names": "Hon'ble Mr. Justice B.P. Jeevan Reddy\n*, Hon'ble Mr. Justice S.C. Sen, Hon'ble Mr. Justice G.T. Nanavati",
        "PDF Link": "https://digiscr.sci.gov.in/pdf_viewer?dir=YWRtaW4vanVkZ2VtZW50X2ZpbGUvanVkZ2VtZW50X3BkZi8xOTk1L3ZvbHVtZSAzL1BhcnQgSS9UaGUgR292dCBPZiBJbmRpYSBBbmQgT3JzIEV0YyAgdnMgIFRoZSBNYWRyYXMgUnViYmVyIEZhY3RvcnkgTHRkIEV0YzE3MDE5MjczOTcucGRm"
    },
    {
        "volume": "1995Volume 3",
        "Case Name": "SHAMSHUL KANWAR VS. STATE OF U.P.",
        "Case Link": "https://digiscr.sci.gov.in/view_judgment?id=MTcwOTI=",
        "Citation": "[1995] 3 S.C.R. 1197",
        "Case Type": "(CRIMINAL APPEAL /887/1994)",
        "Date": "04 MAY 1995",
        "Judge Names": "Hon'ble Mr. Justice M.M. Punchhi, Hon'ble Mr. Justice K. Jayachandra Reddy\n*",
        "PDF Link": "https://digiscr.sci.gov.in/pdf_viewer?dir=YWRtaW4vanVkZ2VtZW50X2ZpbGUvanVkZ2VtZW50X3BkZi8xOTk1L3ZvbHVtZSAzL1BhcnQgSS9TaGFtc2h1bCBLYW53YXIgIHZzICBTdGF0ZSBPZiBVcDE3MDE5Mjc1MjEucGRm"
    },
    {
        "volume": "1995Volume 3",
        "Case Name": "B.P.L. PHARMACEUTICALS LTD VS. COLLECTOR OF CENTRAL EXCISE, VADODARA",
        "Case Link": "https://digiscr.sci.gov.in/view_judgment?id=MTcxMDM=",
        "Citation": "[1995] 3 S.C.R. 1235",
        "Case Type": "(CIVIL APPEAL /2516- 2517/1994)",
        "Date": "04 MAY 1995",
        "Judge Names": "Hon'ble Mr. Justice P.B. Sawant, Hon'ble Mr. Justice K. Venkataswami\n*",
        "PDF Link": "https://digiscr.sci.gov.in/pdf_viewer?dir=YWRtaW4vanVkZ2VtZW50X2ZpbGUvanVkZ2VtZW50X3BkZi8xOTk1L3ZvbHVtZSAzL1BhcnQgSS9CcGwgUGhhcm1hY2V1dGljYWxzIEx0ZCAgdnMgIENvbGxlY3RvciBPZiBDZW50cmFsIEV4Y2lzZSBWYWRvZGFyYTE3MDE5Mjc2MzMucGRm"
    },
    {
        "volume": "1995Volume 3",
        "Case Name": "KANWAR LAL VS. IIND ADDITIONAL DISTT. JUDGE, NAINITAL AND ORS.",
        "Case Link": "https://digiscr.sci.gov.in/view_judgment?id=MzU3NDc=",
        "Citation": "[1995] 3 S.C.R. 622",
        "Case Type": "(CIVIL APPEAL /4609/1995)",
        "Date": "20 APRIL 1995",
        "Judge Names": "Hon'ble Mr. Justice P.B. Sawant\n*, Hon'ble Mr. Justice S.C. Agrawal",
        "PDF Link": "https://digiscr.sci.gov.in/pdf_viewer?dir=YWRtaW4vanVkZ2VtZW50X2ZpbGUvanVkZ2VtZW50X3BkZi8xOTk1L3ZvbHVtZSAzL1BhcnQgSS8xOTk1XzNfNjIyLTYzM18xNzAzMzI4MTA1LnBkZg=="
    },
    {
        "volume": "1995Volume 3",
        "Case Name": "THE SCHEDULED CASTE UPLIFT UNION AND ANR. V. VS. UNION OF INDIA AND ORS.",
        "Case Link": "https://digiscr.sci.gov.in/view_judgment?id=MzU3NTc=",
        "Citation": "[1995] 3 S.C.R. 634",
        "Case Type": "(WRIT PETITION (CIVIL) /390/1995)",
        "Date": "20 APRIL 1995",
        "Judge Names": "Hon'ble Mr. Justice B.L. Hansaria, Hon'ble Mr. Justice R.M. Sahai",
        "PDF Link": "https://digiscr.sci.gov.in/pdf_viewer?dir=YWRtaW4vanVkZ2VtZW50X2ZpbGUvanVkZ2VtZW50X3BkZi8xOTk1L3ZvbHVtZSAzL1BhcnQgSS8xOTk1XzNfNjM0LTYzOF8xNzAzMzI4MjcwLnBkZg=="
    }
]